Workbook

Sheet SUMMARY
B4: SUMMARY
B5: NO. | C5: INDICATORS | D5: FIGURES
B6: 1 | C6: TOTAL NO. OF FARMERS | D6: ='GOD FIRST'!C43+GYASEHENE!C42+ADIEPANA!C43+BAAKOYE!C43+'0'!C43 -> 68
B7: =B6+1 -> 2 | C7: AV.INPUTS LOAN SIZE | D7: =D8/D6 -> 11034.647
B8: 3 | C8: TOTAL INPUTS LOAN (GHc) | D8: ='1.'!AC42+GYASEHENE!AC42+ADIEPANA!AC43+'1'!AC43+BAAKOYE!AC43+'GOD FIRST'!AC43+'0'!AC43+YAWOWUSUKROM!AC39+'kramokrom 1'!AC43+'SH1'!AC40+ADAMSO.!AC42+'13'!AC42+'12'!AC43+'5'!AC43+'3'!AC43+'4'!AC42+'11'!AC43+'SHEET 18'!AC43+'SHEET 19'!AC43+'SHEET 20'!AC43+'SHEET 21'!AC43+'SHEET 22'!AC43+'SHEET 23'!AC43+'SHEET 24'!AC43+'SHEET 25'!AC43+'SHEET 26'!AC43+'SHEET 27'!AC43+'SHEET 28'!AC43+'SHEET 29'!AC43+'SHEET 30'!AC43+'SHEET 31'!AC43+'SHEET 32'!AC43+'SHEET 33'!AC43+'SHEET 34'!AC43+'SHEET 35'!AC43+'SHEET 36'!AC43+'SHEET 37'!AC43+'SHEET 38'!AC43+'SHEET 39'!AC43+'SHEET 40'!AC43+'SHEET 41'!AC43+'SHEET 42'!AC43+'SHEET 43'!AC43+'SHEET 44'!AC43+'SHEET 45'!AC43+'SHEET 46'!AC43+'SHEET 47'!AC43+'SHEET 48'!AC43+'SHEET 49'!AC43+'SHEET 50'!AC43 -> 750356
B9: =B8+1 -> 4 | C9: TOTAL DEPOSIT PAID (GHc) | D9: ='1.'!AD42+GYASEHENE!AD42+ADIEPANA!AD43+'1'!AD43+BAAKOYE!AD43+'GOD FIRST'!AD43+'0'!AD43+YAWOWUSUKROM!AD39+'kramokrom 1'!AD43+'SH1'!AD40+ADAMSO.!AD42+'13'!AD42+'12'!AD43+'5'!AD43+'3'!AD43+'4'!AD42+'11'!AD43+'SHEET 18'!AD43+'SHEET 19'!AD43+'SHEET 20'!AD43+'SHEET 21'!AD43+'SHEET 22'!AD43+'SHEET 23'!AD43+'SHEET 24'!AD43+'SHEET 25'!AD43+'SHEET 26'!AD43+'SHEET 27'!AD43+'SHEET 28'!AD43+'SHEET 29'!AD43+'SHEET 30'!AD43+'SHEET 31'!AD43+'SHEET 32'!AD43+'SHEET 33'!AD43+'SHEET 34'!AD43+'SHEET 35'!AD43+'SHEET 36'!AD43+'SHEET 37'!AD43+'SHEET 38'!AD43+'SHEET 39'!AD43+'SHEET 40'!AD43+'SHEET 41'!AD43+'SHEET 42'!AD43+'SHEET 43'!AD43+'SHEET 44'!AD43+'SHEET 45'!AD43+'SHEET 46'!AD43+'SHEET 47'!AD43+'SHEET 48'!AD43+'SHEET 49'!AD43+'SHEET 50'!AD43 -> 75035.6
B10: 5 | C10: TOTAL OUTS.BALANCE (GHc) | D10: ='1.'!AE42+GYASEHENE!AE42+ADIEPANA!AE43+'1'!AE43+BAAKOYE!AE43+'GOD FIRST'!AE43+'0'!AE43+YAWOWUSUKROM!AE39+'kramokrom 1'!AE43+'SH1'!AE40+ADAMSO.!AE42+'13'!AE42+'12'!AE43+'5'!AE43+'3'!AE43+'4'!AE42+'11'!AE43+'SHEET 18'!AE43+'SHEET 19'!AE43+'SHEET 20'!AE43+'SHEET 21'!AE43+'SHEET 22'!AE43+'SHEET 23'!AE43+'SHEET 24'!AE43+'SHEET 25'!AE43+'SHEET 26'!AE43+'SHEET 27'!AE43+'SHEET 28'!AE43+'SHEET 29'!AE43+'SHEET 30'!AE43+'SHEET 31'!AE43+'SHEET 32'!AE43+'SHEET 33'!AE43+'SHEET 34'!AE43+'SHEET 35'!AE43+'SHEET 36'!AE43+'SHEET 37'!AE43+'SHEET 38'!AE43+'SHEET 39'!AE43+'SHEET 40'!AE43+'SHEET 41'!AE43+'SHEET 42'!AE43+'SHEET 43'!AE43+'SHEET 44'!AE43+'SHEET 45'!AE43+'SHEET 46'!AE43+'SHEET 47'!AE43+'SHEET 48'!AE43+'SHEET 49'!AE43+'SHEET 50'!AE43 -> 675320.4
B11: =B10+1 -> 6 | C11: TOTAL PAYMENT MADE (GHc) | D11: ='1.'!AO42+GYASEHENE!AO42+ADIEPANA!AO43+BAAKOYE!AO43+'GOD FIRST'!AO43+'0'!AO43+YAWOWUSUKROM!AO39+'kramokrom 1'!AO43+'SH1'!AO40+ADAMSO.!AO42+'13'!AO42+'12'!AO43+'5'!AO43+'4'!AO42 -> 48304
B13: EXPECTED REPAYMENT
B14: 8 | C14: OCTOBER | D14: ='1.'!AG42+GYASEHENE!AG42+ADIEPANA!AG43+'1'!AF43+BAAKOYE!AG43+'GOD FIRST'!AF43+'0'!AF43+YAWOWUSUKROM!AF39+'kramokrom 1'!AF43+'SH1'!AF40+ADAMSO.!AF42+'13'!AF42+'12'!AF43+'5'!AF43+'3'!AF43+'4'!AG42+'11'!AF43+'SHEET 18'!AF43+'SHEET 19'!AF43+'SHEET 20'!AF43+'SHEET 21'!AF43+'SHEET 22'!AF43+'SHEET 23'!AF43+'SHEET 24'!AF43+'SHEET 25'!AF43+'SHEET 26'!AF43+'SHEET 27'!AF43+'SHEET 28'!AF43+'SHEET 29'!AF43+'SHEET 30'!AF43+'SHEET 31'!AF43+'SHEET 32'!AF43+'SHEET 33'!AF43+'SHEET 34'!AF43+'SHEET 35'!AF43+'SHEET 36'!AF43+'SHEET 37'!AF43+'SHEET 38'!AF43+'SHEET 39'!AF43+'SHEET 40'!AF43+'SHEET 41'!AF43+'SHEET 42'!AF43+'SHEET 43'!AF43+'SHEET 44'!AF43+'SHEET 45'!AF43+'SHEET 46'!AF43+'SHEET 47'!AF43+'SHEET 48'!AF43+'SHEET 49'!AF43+'SHEET 50'!AF43 -> 0
B15: 9 | C15: NOVEMBER | D15: ='1.'!AH42+GYASEHENE!AH42+ADIEPANA!AH43+'1'!AG43+BAAKOYE!AH43+'GOD FIRST'!AG43+'0'!AG43+YAWOWUSUKROM!AG39+'kramokrom 1'!AG43+'SH1'!AG40+ADAMSO.!AG42+'13'!AG42+'12'!AG43+'5'!AG43+'3'!AG43+'4'!AH42+'11'!AG43+'SHEET 18'!AG43+'SHEET 19'!AG43+'SHEET 20'!AG43+'SHEET 21'!AG43+'SHEET 22'!AG43+'SHEET 23'!AG43+'SHEET 24'!AG43+'SHEET 25'!AG43+'SHEET 26'!AG43+'SHEET 27'!AG43+'SHEET 28'!AG43+'SHEET 29'!AG43+'SHEET 30'!AG43+'SHEET 31'!AG43+'SHEET 32'!AG43+'SHEET 33'!AG43+'SHEET 34'!AG43+'SHEET 35'!AG43+'SHEET 36'!AG43+'SHEET 37'!AG43+'SHEET 38'!AG43+'SHEET 39'!AG43+'SHEET 40'!AG43+'SHEET 41'!AG43+'SHEET 42'!AG43+'SHEET 43'!AG43+'SHEET 44'!AG43+'SHEET 45'!AG43+'SHEET 46'!AG43+'SHEET 47'!AG43+'SHEET 48'!AG43+'SHEET 49'!AG43+'SHEET 50'!AG43 -> 0
B16: 10 | C16: DECEMBER | D16: ='1.'!AI42+GYASEHENE!AI42+ADIEPANA!AI43+'1'!AH43+BAAKOYE!AI43+'GOD FIRST'!AH43+'0'!AH43+YAWOWUSUKROM!AH39+'kramokrom 1'!AH43+'SH1'!AH40+ADAMSO.!AH42+'13'!AH42+'12'!AH43+'5'!AH43+'3'!AH43+'4'!AI42+'11'!AH43+'SHEET 18'!AH43+'SHEET 19'!AH43+'SHEET 20'!AH43+'SHEET 21'!AH43+'SHEET 22'!AH43+'SHEET 23'!AH43+'SHEET 24'!AH43+'SHEET 25'!AH43+'SHEET 26'!AH43+'SHEET 27'!AH43+'SHEET 28'!AH43+'SHEET 29'!AH43+'SHEET 30'!AH43+'SHEET 31'!AH43+'SHEET 32'!AH43+'SHEET 33'!AH43+'SHEET 34'!AH43+'SHEET 35'!AH43+'SHEET 36'!AH43+'SHEET 37'!AH43+'SHEET 38'!AH43+'SHEET 39'!AH43+'SHEET 40'!AH43+'SHEET 41'!AH43+'SHEET 42'!AH43+'SHEET 43'!AH43+'SHEET 44'!AH43+'SHEET 45'!AH43+'SHEET 46'!AH43+'SHEET 47'!AH43+'SHEET 48'!AH43+'SHEET 49'!AH43+'SHEET 50'!AH43 -> 0

Sheet 1.
C2: NOTE:
C3: 1. Enter the quantity of agro inputs requested by the farmer either in pcs or boxes under each agro input
C4: 2. Do not change any thing in the excel sheet. The cells are linked
C6: REGION:
C7: DISTRICT:
C8: SOCIETY: | D8: NKABOM MA NKCSUO
B10: NO. | C10: FARMER NAME | D10: MOBILE NO. | E10: AcetaStar -Adama (1Lt) | G10: Galil | I10: AKATE BRAFO | K10: PHYTOGREEN | M10: BEGREEN | O10: Agyenkwa Liquid Fertilizer (5Lt) | Q10: Matabi (15Lt) | R10: PLANTFEED | T10: Solo Machine | U10: All Wedicides (Glyphosate) | W10: NODOX | X10: ALL GRAMO | Z10: STANDARD PRUNNER | AA10: WELLINGTON BOOT | AB10: OVERALL | AC10: TOTAL AMOUNT (GHc) | AD10: DEPOSIT | AE10: OUTS. BALANCE (GHc) | AF10: REPAYMENT PLAN(GHC)
E11: PCs | F11: Box (12pcs) | G11: PCs | H11: Box | I11: PCs | J11: Box | K11: 1LT | L11: BOX(15) | M11: 1GALLON | N11: BOX(6) | O11: PCs | P11: Box(4) | Q11: PCs | R11: 1 GALLON | S11: BOX(4) | T11: PCs | U11: PCS | V11: BOX(12) | W11: PCs | X11: PCS | Y11: BOX(12) | Z11: PC | AA11: PC | AB11: PC | AF11: OCT | AG11: NOV | AL11: OCT | AM11: NOV | AN11: DEC | AO11: TOTAL PAYMENT | AP11: REMN
B12: =B11+1 -> 1 | AC12: =(E12*E45)+(F12*F45)+(G12*G45)+(H12*H45)+(I12*I45)+(J12*J45)+(K12*K45)+(L12*L45)+(M12*M45)+(N12*N45)+(O12*O45)+(P12*P45)+(Q12*Q45)+(R12*R45)+(S12*S45)+(T12*T45)+(U12*U45)+(V12*V45)+(W12*W45)+(X12*X45)+(Y12*Y45)+(Z12*Z45)+(AA12*AA45)+(AB12*AB45) -> 0 | AD12: =10%*AC12 -> 0 | AE12: =AC12-AD12 -> 0 | AL12: =AE12/3 -> 0 | AM12: =AL12 -> 0 | AN12: =AM12 -> 0 | AO12: =AD12+AF12+AG12+AH12+AI12+AJ12+AK12 -> 0 | AP12: =AC12-AO12 -> 0
B13: 2 | AC13: =(E13*E45)+(F13*F45)+(G13*G45)+(H13*H45)+(I13*I45)+(J13*J45)+(K13*K45)+(L13*L45)+(M13*M45)+(N13*N45)+(O13*O45)+(P13*P45)+(Q13*Q45)+(R13*R45)+(S13*S45)+(T13*T45)+(U13*U45)+(V13*V45)+(W13*W45)+(X13*X45)+(Y13*Y45)+(Z13*Z45)+(AA13*AA45)+(AB13*AB45) -> 0 | AD13: =10%*AC13 -> 0 | AE13: =AC13-AD13 -> 0 | AL13: =AE13/3 -> 0 | AM13: =AL13 -> 0 | AN13: =AM13 -> 0 | AO13: =AD13+AF13+AG13+AH13+AI13+AJ13+AK13 -> 0 | AP13: =AC13-AO13 -> 0
B14: =B13+1 -> 3 | AC14: =(E14*E45)+(F14*F45)+(G14*G45)+(H14*H45)+(I14*I45)+(J14*J49)+(K14*K45)+(L14*L45)+(M14*M45)+(N14*N45)+(O14*O45)+(P14*P45)+(Q14*Q45)+(R14*R45)+(S14*S45)+(T14*T45)+(U14*U45)+(V14*V45)+(W14*W45)+(X14*X45)+(Y14*Y45)+(Z14*Z45)+(AA14*AA45)+(AB14*AB45) -> 0 | AD14: =10%*AC14 -> 0 | AE14: =AC14-AD14 -> 0 | AL14: =AE14/3 -> 0 | AM14: =AL14 -> 0 | AN14: =AM14 -> 0 | AO14: =AD14+AF14+AG14+AH14+AI14+AJ14+AK14 -> 0 | AP14: =AC14-AO14 -> 0
B15: =B14+1 -> 4 | AC15: =(E15*E45)+(F15*F45)+(G15*G45)+(H15*H45)+(I15*I45)+(J15*J45)+(K15*K45)+(L15*L45)+(M15*M45)+(N15*N45)+(O15*O45)+(P15*P45)+(Q15*Q45)+(R15*R45)+(S15*S45)+(T15*T45)+(U15*U45)+(V15*V45)+(W15*W45)+(X15*X45)+(Y15*Y45)+(Z15*Z45)+(AA15*AA45)+(AB15*AB45) -> 0 | AD15: =10%*AC15 -> 0 | AE15: =AC15-AD15 -> 0 | AL15: =AE15/3 -> 0 | AM15: =AL15 -> 0 | AN15: =AM15 -> 0 | AO15: =AD15+AF15+AG15+AH15+AI15+AJ15+AK15 -> 0 | AP15: =AC15-AO15 -> 0
B16: =B15+1 -> 5 | AC16: =(E16*E45)+(F16*F45)+(G16*G45)+(H16*H45)+(I16*I45)+(J16*J45)+(K16*K45)+(L16*L45)+(M16*M45)+(N16*N45)+(O16*O45)+(P16*P45)+(Q16*Q45)+(R16*R45)+(S16*S45)+(T16*T45)+(U16*U45)+(V16*V45)+(W16*W45)+(X16*X45)+(Y16*Y45)+(Z16*Z45)+(AA16*AA45)+(AB16*AB45) -> 0 | AD16: =10%*AC16 -> 0 | AE16: =AC16-AD16 -> 0 | AL16: =AE16/3 -> 0 | AM16: =AL16 -> 0 | AN16: =AM16 -> 0 | AO16: =AD16+AF16+AG16+AH16+AI16+AJ16+AK16 -> 0 | AP16: =AC16-AO16 -> 0
B17: =B16+1 -> 6 | AC17: =(E17*E45)+(F17*F45)+(G17*G45)+(H17*H45)+(I17*I45)+(J17*J45)+(K17*K45)+(L17*L45)+(M17*M45)+(N17*N45)+(O17*O45)+(P17*P45)+(Q17*Q45)+(R17*R45)+(S17*S45)+(T17*T45)+(U17*U45)+(V17*V45)+(W17*W45)+(X17*X45)+(Y17*Y45)+(Z17*Z45)+(AA17*AA45)+(AB17*AB45) -> 0 | AD17: =10%*AC17 -> 0 | AE17: =AC17-AD17 -> 0 | AL17: =AE17/3 -> 0 | AM17: =AL17 -> 0 | AN17: =AM17 -> 0 | AO17: =AD17+AF17+AG17+AH17+AI17+AJ17+AK17 -> 0 | AP17: =AC17-AO17 -> 0
B18: =B17+1 -> 7 | AC18: =(E18*E45)+(F18*F45)+(G18*G45)+(H18*H45)+(I18*I45)+(J18*J45)+(K18*K45)+(L18*L45)+(M18*M45)+(N18*N45)+(O18*O45)+(P18*P45)+(Q18*Q45)+(R18*R45)+(S18*S45)+(T18*T45)+(U18*U45)+(V18*V45)+(W18*W45)+(X18*X45)+(Y18*Y45)+(Z18*Z45)+(AA18*AA45)+(AB18*AB45) -> 0 | AD18: =10%*AC18 -> 0 | AE18: =AC18-AD18 -> 0 | AL18: =AE18/3 -> 0 | AM18: =AL18 -> 0 | AN18: =AM18 -> 0 | AO18: =AD18+AF18+AG18+AH18+AI18+AJ18+AK18 -> 0 | AP18: =AC18-AO18 -> 0
B19: =B18+1 -> 8 | AC19: =(E19*E45)+(F19*F45)+(G19*G45)+(H19*H45)+(I19*I45)+(J19*J45)+(K19*K45)+(L19*L45)+(M19*M45)+(N19*N45)+(O19*O45)+(P19*P45)+(Q19*Q45)+(R19*R45)+(S19*S45)+(T19*T45)+(U19*U45)+(V19*V45)+(W19*W45)+(X19*X45)+(Y19*Y45)+(Z19*Z45)+(AA19*AA45)+(AB19*AB45) -> 0 | AD19: =10%*AC19 -> 0 | AE19: =AC19-AD19 -> 0 | AL19: =AE19/3 -> 0 | AM19: =AL19 -> 0 | AN19: =AM19 -> 0 | AP19: =AC19-AO19 -> 0
B20: =B19+1 -> 9 | AC20: =(E20*E45)+(F20*F45)+(G20*G45)+(H20*H45)+(I20*I45)+(J20*J45)+(K20*K45)+(L20*L45)+(M20*M45)+(N20*N45)+(O20*O45)+(P20*P45)+(Q20*Q45)+(R20*R45)+(S20*S45)+(T20*T45)+(U20*U45)+(V20*V45)+(W20*W45)+(X20*X45)+(Y20*Y45)+(Z20*Z45)+(AA20*AA45)+(AB20*AB45) -> 0 | AD20: =10%*AC20 -> 0 | AE20: =AC20-AD20 -> 0 | AL20: =AE20/3 -> 0 | AM20: =AL20 -> 0 | AN20: =AM20 -> 0 | AO20: =AD20+AF20+AG20+AH20+AI20+AJ20+AK20 -> 0 | AP20: =AC20-AO20 -> 0
B21: =B20+1 -> 10 | AC21: =(E21*E45)+(F21*F45)+(G21*G45)+(H21*H45)+(I21*I45)+(J21*J45)+(K21*K45)+(L21*L45)+(M21*M45)+(N21*N45)+(O21*O45)+(P21*P45)+(Q21*Q45)+(R21*R45)+(S21*S45)+(T21*T45)+(U21*U45)+(V21*V45)+(W21*W45)+(X21*X45)+(Y21*Y45)+(Z21*Z45)+(AA21*AA45)+(AB21*AB45) -> 0 | AD21: =10%*AC21 -> 0 | AE21: =AC21-AD21 -> 0 | AL21: =AE21/3 -> 0 | AM21: =AL21 -> 0 | AN21: =AM21 -> 0
B22: =B21+1 -> 11 | AC22: =(E22*E45)+(F22*F45)+(G22*G45)+(H22*H45)+(I22*I45)+(J22*J45)+(K22*J45)+(L22*L45)+(M22*M45)+(N22*N45)+(O22*O45)+(P22*P45)+(Q22*Q45)+(R22*R45)+(S22*S45)+(T22*T45)+(U22*U45)+(V22*V45)+(W22*W45)+(X22*X45)+(Y22*Y45)+(Z22*Z45)+(AA22*AA45)+(AB22*AB45) -> 0 | AD22: =10%*AC22 -> 0 | AE22: =AC22-AD22 -> 0 | AL22: =AE22/3 -> 0 | AM22: =AL22 -> 0 | AN22: =AM22 -> 0
B23: =B22+1 -> 12 | AC23: =(E23*E45)+(F23*F45)+(G23*G45)+(H23*H45)+(I23*I45)+(J23*J45)+(K23*K45)+(L23*L45)+(M23*M45)+(N23*N45)+(O23*O45)+(P23*P45)+(Q23*Q45)+(R23*R45)+(S23*S45)+(T23*T45)+(U23*U45)+(V23*V45)+(W23*W45)+(X23*X45)+(Y23*Y45)+(Z23*Z45)+(AA23*AA45)+(AB23*AB45) -> 0 | AD23: =10%*AC23 -> 0 | AE23: =AC23-AD23 -> 0 | AL23: =AE23/3 -> 0 | AM23: =AL23 -> 0 | AN23: =AM23 -> 0
B24: =B23+1 -> 13 | AC24: =(E24*E45)+(F24*F45)+(G24*G45)+(H24*H45)+(I24*I45)+(J24*J45)+(K24*K45)+(L24*L45)+(M24*M45)+(N24*N45)+(O24*O45)+(P24*P45)+(Q24*Q45)+(R24*R45)+(S24*S45)+(T24*T45)+(U24*U45)+(V24*V45)+(W24*W45)+(X24*X45)+(Y24*Y45)+(Z24*Z45)+(AA24*AA45)+(AB24*AB45) -> 0 | AD24: =10%*AC24 -> 0 | AE24: =AC24-AD24 -> 0 | AL24: =AE24/3 -> 0 | AM24: =AL24 -> 0 | AN24: =AM24 -> 0
B25: =B24+1 -> 14 | AC25: =(E25*E45)+(F25*F45)+(G25*G45)+(H25*H45)+(I25*I45)+(J25*J45)+(K25*J45)+(L25*L45)+(M25*M45)+(N25*N45)+(O25*O45)+(P25*P45)+(Q25*Q45)+(R25*R45)+(S25*S45)+(T25*T45)+(U25*U45)+(V25*V45)+(W25*W45)+(X25*X45)+(Y25*Y45)+(Z25*Z45)+(AA25*AA45)+(AB25*AB45) -> 0 | AD25: =10%*AC25 -> 0 | AE25: =AC25-AD25 -> 0 | AL25: =AE25/3 -> 0 | AM25: =AL25 -> 0 | AN25: =AM25 -> 0
B26: =B25+1 -> 15 | AC26: =(E26*E45)+(F26*F45)+(G26*G45)+(H26*H45)+(I26*I45)+(J26*J45)+(K26*K45)+(L26*L45)+(M26*M45)+(N26*N45)+(O26*O45)+(P26*P45)+(Q26*Q45)+(R26*R45)+(S26*S45)+(T26*T45)+(U26*U45)+(V26*V45)+(W26*W45)+(X26*X45)+(Y26*Y45)+(Z26*Z45)+(AA26*AA45)+(AB26*AB45) -> 0 | AD26: =10%*AC26 -> 0 | AE26: =AC26-AD26 -> 0 | AL26: =AE26/3 -> 0 | AM26: =AL26 -> 0 | AN26: =AM26 -> 0
B27: =B26+1 -> 16 | AC27: =(E27*E45)+(F27*F45)+(G27*G45)+(H27*H45)+(I27*I45)+(J27*J45)+(K27*K45)+(L27*L45)+(M27*M45)+(N27*N45)+(O27*O45)+(P27*P45)+(Q27*Q45)+(R27*R45)+(S27*S45)+(T27*T45)+(U27*U45)+(V27*V45)+(W27*W45)+(X27*X45)+(Y27*Y45)+(Z27*Z45)+(AA27*AA45)+(AB27*AB45) -> 0 | AD27: =10%*AC27 -> 0 | AE27: =AC27-AD27 -> 0 | AL27: =AE27/3 -> 0 | AM27: =AL27 -> 0 | AN27: =AM27 -> 0
B28: =B27+1 -> 17 | AC28: =(E28*E45)+(F28*F45)+(G28*G45)+(H28*H45)+(I28*I45)+(J28*J45)+(K28*J45)+(L28*L45)+(M28*M45)+(N28*N45)+(O28*O45)+(P28*P45)+(Q28*Q45)+(R28*R45)+(S28*S45)+(T28*T45)+(U28*U45)+(V28*V45)+(W28*W45)+(X28*X45)+(Y28*Y45)+(Z28*Z45)+(AA28*AA45)+(AB28*AB45) -> 0 | AD28: =10%*AC28 -> 0 | AE28: =AC28-AD28 -> 0 | AL28: =AE28/3 -> 0 | AM28: =AL28 -> 0 | AN28: =AM28 -> 0
B29: =B28+1 -> 18 | AC29: =(E29*E45)+(F29*F45)+(G29*G45)+(H29*H45)+(I29*I45)+(J29*J45)+(K29*K45)+(L29*L45)+(M29*M45)+(N29*N45)+(O29*O45)+(P29*P45)+(Q29*Q45)+(R29*R45)+(S29*S45)+(T29*T45)+(U29*U45)+(V29*V45)+(W29*W45)+(X29*X45)+(Y29*Y45)+(Z29*Z45)+(AA29*AA45)+(AB29*AB45) -> 0 | AD29: =10%*AC29 -> 0 | AE29: =AC29-AD29 -> 0 | AL29: =AE29/3 -> 0 | AM29: =AL29 -> 0 | AN29: =AM29 -> 0
B30: =B29+1 -> 19 | AC30: =(E30*E45)+(F30*F45)+(G30*G45)+(H30*H45)+(I30*I45)+(J30*J45)+(K30*K45)+(L30*L45)+(M30*M45)+(N30*N45)+(O30*O45)+(P30*P45)+(Q30*Q45)+(R30*R45)+(S30*S45)+(T30*T45)+(U30*U45)+(V30*V45)+(W30*W45)+(X30*X45)+(Y30*Y45)+(Z30*Z45)+(AA30*AA45)+(AB30*AB45) -> 0 | AD30: =10%*AC30 -> 0 | AE30: =AC30-AD30 -> 0 | AL30: =AE30/3 -> 0 | AM30: =AL30 -> 0 | AN30: =AM30 -> 0
B31: =B30+1 -> 20 | AC31: =(E31*E45)+(F31*F45)+(G31*G45)+(H31*H45)+(I31*I45)+(J31*J45)+(K31*J45)+(L31*L45)+(M31*M45)+(N31*N45)+(O31*O45)+(P31*P45)+(Q31*Q45)+(R31*R45)+(S31*S45)+(T31*T45)+(U31*U45)+(V31*V45)+(W31*W45)+(X31*X45)+(Y31*Y45)+(Z31*Z45)+(AA31*AA45)+(AB31*AB45) -> 0 | AD31: =10%*AC31 -> 0 | AE31: =AC31-AD31 -> 0 | AL31: =AE31/3 -> 0 | AM31: =AL31 -> 0 | AN31: =AM31 -> 0
B32: =B31+1 -> 21 | AC32: =(E32*E45)+(F32*F45)+(G32*G45)+(H32*H45)+(I32*I45)+(J32*J45)+(K32*K45)+(L32*L45)+(M32*M45)+(N32*N45)+(O32*O45)+(P32*P45)+(Q32*Q45)+(R32*R45)+(S32*S45)+(T32*T45)+(U32*U45)+(V32*V45)+(W32*W45)+(X32*X45)+(Y32*Y45)+(Z32*Z45)+(AA32*AA45)+(AB32*AB45) -> 0 | AD32: =10%*AC32 -> 0 | AE32: =AC32-AD32 -> 0 | AL32: =AE32/3 -> 0 | AM32: =AL32 -> 0 | AN32: =AM32 -> 0
B33: =B32+1 -> 22 | AC33: =(E33*E45)+(F33*F45)+(G33*G45)+(H33*H45)+(I33*I45)+(J33*J45)+(K33*K45)+(L33*L45)+(M33*M45)+(N33*N45)+(O33*O45)+(P33*P45)+(Q33*Q45)+(R33*R45)+(S33*S45)+(T33*T45)+(U33*U45)+(V33*V45)+(W33*W45)+(X33*X45)+(Y33*Y45)+(Z33*Z45)+(AA33*AA45)+(AB33*AB45) -> 0 | AD33: =10%*AC33 -> 0 | AE33: =AC33-AD33 -> 0 | AL33: =AE33/3 -> 0 | AM33: =AL33 -> 0 | AN33: =AM33 -> 0
B34: =B33+1 -> 23 | AC34: =(E34*E45)+(F34*F45)+(G34*G45)+(H34*H45)+(I34*I45)+(J34*J45)+(K34*J45)+(L34*L45)+(M34*M45)+(N34*N45)+(O34*O45)+(P34*P45)+(Q34*Q45)+(R34*R45)+(S34*S45)+(T34*T45)+(U34*U45)+(V34*V45)+(W34*W45)+(X34*X45)+(Y34*Y45)+(Z34*Z45)+(AA34*AA45)+(AB34*AB45) -> 0 | AD34: =10%*AC34 -> 0 | AE34: =AC34-AD34 -> 0 | AL34: =AE34/3 -> 0 | AM34: =AL34 -> 0 | AN34: =AM34 -> 0
B35: =B34+1 -> 24 | AC35: =(E35*E45)+(F35*F45)+(G35*G45)+(H35*H45)+(I35*I45)+(J35*J45)+(K35*K45)+(L35*L45)+(M35*M45)+(N35*N45)+(O35*O45)+(P35*P45)+(Q35*Q45)+(R35*R45)+(S35*S45)+(T35*T45)+(U35*U45)+(V35*V45)+(W35*W45)+(X35*X45)+(Y35*Y45)+(Z35*Z45)+(AA35*AA45)+(AB35*AB45) -> 0 | AD35: =10%*AC35 -> 0 | AE35: =AC35-AD35 -> 0 | AL35: =AE35/3 -> 0 | AM35: =AL35 -> 0 | AN35: =AM35 -> 0
B36: =B35+1 -> 25 | AC36: =(E36*E45)+(F36*F45)+(G36*G45)+(H36*H45)+(I36*I45)+(J36*J45)+(K36*K45)+(L36*L45)+(M36*M45)+(N36*N45)+(O36*O45)+(P36*P45)+(Q36*Q45)+(R36*R45)+(S36*S45)+(T36*T45)+(U36*U45)+(V36*V45)+(W36*W45)+(X36*X45)+(Y36*Y45)+(Z36*Z45)+(AA36*AA45)+(AB36*AB45) -> 0 | AD36: =10%*AC36 -> 0 | AE36: =AC36-AD36 -> 0 | AL36: =AE36/3 -> 0 | AM36: =AL36 -> 0 | AN36: =AM36 -> 0
B37: =B36+1 -> 26 | AC37: =(E37*E45)+(F37*F45)+(G37*G45)+(H37*H45)+(I37*I45)+(J37*J45)+(K37*J45)+(L37*L45)+(M37*M45)+(N37*N45)+(O37*O45)+(P37*P45)+(Q37*Q45)+(R37*R45)+(S37*S45)+(T37*T45)+(U37*U45)+(V37*V45)+(W37*W45)+(X37*X45)+(Y37*Y45)+(Z37*Z45)+(AA37*AA45)+(AB37*AB45) -> 0 | AD37: =10%*AC37 -> 0 | AE37: =AC37-AD37 -> 0 | AL37: =AE37/3 -> 0 | AM37: =AL37 -> 0 | AN37: =AM37 -> 0
B38: =B37+1 -> 27 | AC38: =(E38*E45)+(F38*F45)+(G38*G45)+(H38*H45)+(I38*I45)+(J38*J45)+(K38*K45)+(L38*L45)+(M38*M45)+(N38*N45)+(O38*O45)+(P38*P45)+(Q38*Q45)+(R38*R45)+(S38*S45)+(T38*T45)+(U38*U45)+(V38*V45)+(W38*W45)+(X38*X45)+(Y38*Y45)+(Z38*Z45)+(AA38*AA45)+(AB38*AB45) -> 0 | AD38: =10%*AC38 -> 0 | AE38: =AC38-AD38 -> 0 | AL38: =AE38/3 -> 0 | AM38: =AL38 -> 0 | AN38: =AM38 -> 0
B39: =B38+1 -> 28
B40: =B39+1 -> 29
B41: =B40+1 -> 30
B42: TOTAL | AF42: =SUM(AF12:AF39) -> 0 | AG42: =SUM(AG12:AG39) -> 0 | AH42: =SUM(AH12:AH39) -> 0 | AI42: =SUM(AI12:AI39) -> 0 | AJ42: =SUM(AJ12:AJ39) -> 0 | AK42: =SUM(AK12:AK39) -> 0 | AL42: =SUM(AL12:AL39) -> 0 | AM42: =SUM(AM12:AM39) -> 0 | ... AP42: =SUM(AP12:AP39) -> 0
C45: Price | E45: 204 | F45: =12*E45 -> 2448 | G45: 177 | H45: =G45*48 -> 8496 | I45: 204 | J45: =I45*12 -> 2448 | K45: 177 | L45: =K45*15 -> 2655 | M45: 34 | N45: =M45*6 -> 204 | O45: 272 | P45: =O45*4 -> 1088 | Q45: 1496 | R45: 272 | S45: =R45*4 -> 1088 | T45: 6800 | U45: 75 | V45: =U45*12 -> 900 | W45: 13.6 | X45: 68 | Y45: =X45*12 -> 816 | Z45: 1904 | AA45: 122 | AB45: 340

Sheet GOD FIRST
C2: NOTE:
C3: 1. Enter the quantity of agro inputs requested by the farmer either in pcs or boxes under each agro input
C4: 2. Do not change any thing in the excel sheet. The cells are linked
C6: REGION: | D6: ASHANTI | AF6: ASHANTI
C7: DISTRICT: | D7: OBUASI | AF7: OBUASI
C8: SOCIETY: | D8: GOD FIRST | AF8: GOD FIRST
B10: NO. | C10: FARMER NAME | D10: MOBILE NO. | E10: AcetaStar -Adama (1Lt) | G10: Galil | I10: AKATE BRAFO | K10: PHYTOGREEN | M10: BEGREEN | O10: Agyenkwa Liquid Fertilizer (5Lt) | Q10: Matabi (15Lt) | R10: PLANTFEED | T10: Solo Machine | U10: All Wedicides (Glyphosate) | W10: NODOX | X10: ALL GRAMO | Z10: STANDARD PRUNNER | AA10: WELLINGTON BOOT | AB10: OVERALL | AC10: TOTAL AMOUNT (GHc) | AD10: DEPOSIT PAID (GHc) | AE10: OUTS. BALANCE (GHc) | AF10: REPAYMENT PLAN(GHC)
E11: PCs | F11: Box (12pcs) | G11: PCs | H11: Box | I11: PCs | J11: Box | K11: 1LT | L11: BOX(15) | M11: 1GALLON | N11: BOX(6) | O11: PCs | P11: Box(4) | Q11: PCs | R11: 1 GALLON | S11: BOX(4) | T11: PCs | U11: PCS | V11: BOX(12) | W11: PCs | X11: PCS | Y11: BOX(12) | Z11: PC | AA11: PC | AB11: PC | AF11: oct | AI11: DEC | AL11: OCT | AM11: NOV | AN11: DEC | AO11: TOTAL PAYMENT
B12: =B11+1 -> 1 | C12: OSEI RITA | D12: 0244198138 | F12: 1 | Q12: 1 | T12: 1 | AC12: =(E12*E46)+(F12*F46)+(G12*G46)+(H12*H46)+(I12*I46)+(J12*J46)+(K12*K46)+(L12*L46)+(M12*M46)+(N12*N46)+(O12*O46)+(P12*P46)+(Q12*Q46)+(R12*R46)+(S12*S46)+(T12*T46)+(U12*U46)+(V12*V46)+(W12*W46)+(X12*X46)+(Y12*Y46)+(Z12*Z46)+(AA12*AA46)+(AB12*AB46) -> 10744 | AD12: =10%*AC12 -> 1074.4 | AE12: =AC12-AD12 -> 9669.6 | AL12: =AE12/3 -> 3223.2 | AM12: =AL12 -> 3223.2 | AN12: =AM12 -> 3223.2 | AO12: =AD12+AF12+AG12+AH12+AI12+AJ12+AK12 -> 1074.4 | AP12: =AC12-AO12 -> 9669.6
B13: =B12+1 -> 2 | C13: MARTEY NYARKO JOSEPH | D13: 0246774535 | T13: 1 | V13: 1 | AC13: =(E13*E46)+(F13*F46)+(G13*G46)+(H13*H46)+(I13*I46)+(J13*J46)+(K13*K46)+(L13*L46)+(M13*M46)+(N13*N46)+(O13*O46)+(P13*P46)+(Q13*Q46)+(R13*R46)+(S13*S46)+(T13*T46)+(U13*U46)+(V13*V46)+(W13*W46)+(X13*X46)+(Y13*Y46)+(Z13*Z46)+(AA13*AA46)+(AB13*AB46) -> 7700 | AD13: =10%*AC13 -> 770 | AE13: =AC13-AD13 -> 6930 | AL13: =AE13/3 -> 2310 | AM13: =AL13 -> 2310 | AN13: =AM13 -> 2310 | AO13: =AD13+AF13+AG13+AH13+AI13+AJ13+AK13 -> 770 | AP13: =AC13-AO13 -> 6930
B14: =B13+1 -> 3 | C14: TEYE STEPHEN | D14: 05330590788 | F14: 1 | T14: 1 | V14: 1 | AC14: =(E14*E46)+(F14*F46)+(G14*G46)+(H14*H46)+(I14*I46)+(J14*J46)+(K14*K46)+(L14*L46)+(M14*M46)+(N14*N46)+(O14*O46)+(P14*P46)+(Q14*Q46)+(R14*R46)+(S14*S46)+(T14*T46)+(U14*U46)+(V14*V46)+(W14*W46)+(X14*X46)+(Y14*Y46)+(Z14*Z46)+(AA14*AA46)+(AB14*AB46) -> 10148 | AD14: =10%*AC14 -> 1014.8 | AE14: =AC14-AD14 -> 9133.2 | AL14: =AE14/3 -> 3044.4 | AM14: =AL14 -> 3044.4 | AN14: =AM14 -> 3044.4 | AO14: =AD14+AF14+AG14+AH14+AI14+AJ14+AK14 -> 1014.8 | AP14: =AC14-AO14 -> 9133.2
B15: =B14+1 -> 4 | C15: NYARKO AKOSUA | D15: 0552370981 | F15: 1 | V15: 1 | AC15: =(E15*E46)+(F15*F46)+(G15*G46)+(H15*H46)+(I15*I46)+(J15*J46)+(K15*K46)+(L15*L46)+(M15*M46)+(N15*N46)+(O15*O46)+(P15*P46)+(Q15*Q46)+(R15*R46)+(S15*S46)+(T15*T46)+(U15*U46)+(V15*V46)+(W15*W46)+(X15*X46)+(Y15*Y46)+(Z15*Z46)+(AA15*AA46)+(AB15*AB46) -> 3348 | AD15: =10%*AC15 -> 334.8 | AE15: =AC15-AD15 -> 3013.2 | AL15: =AE15/3 -> 1004.4 | AM15: =AL15 -> 1004.4 | AN15: =AM15 -> 1004.4 | AO15: =AD15+AF15+AG15+AH15+AI15+AJ15+AK15 -> 334.8 | AP15: =AC15-AO15 -> 3013.2
B16: =B15+1 -> 5 | C16: MENSAH GRACE | D16: 0247474621 | Y16: 1 | AC16: =(E16*E46)+(F16*F46)+(G16*G46)+(H16*H46)+(I16*I46)+(J16*J46)+(K16*K46)+(L16*L46)+(M16*M46)+(N16*N46)+(O16*O46)+(P16*P46)+(Q16*Q46)+(R16*R46)+(S16*S46)+(T16*T46)+(U16*U46)+(V16*V46)+(W16*W46)+(X16*X46)+(Y16*Y46)+(Z16*Z46)+(AA16*AA46)+(AB16*AB46) -> 816 | AD16: =10%*AC16 -> 81.6 | AE16: =AC16-AD16 -> 734.4 | AL16: =AE16/3 -> 244.8 | AM16: =AL16 -> 244.8 | AN16: =AM16 -> 244.8 | AO16: =AD16+AF16+AG16+AH16+AI16+AJ16+AK16 -> 81.6 | AP16: =AC16-AO16 -> 734.4
B17: =B16+1 -> 6 | C17: TETTEH ERIC | D17: 0555043418 | Q17: 1 | AC17: =(E17*E46)+(F17*F46)+(G17*G46)+(H17*H46)+(I17*I46)+(J17*J50)+(K17*K46)+(L17*L46)+(M17*M46)+(N17*N46)+(O17*O46)+(P17*P46)+(Q17*Q46)+(R17*R46)+(S17*S46)+(T17*T46)+(U17*U46)+(V17*V46)+(W17*W46)+(X17*X46)+(Y17*Y46)+(Z17*Z46)+(AA17*AA46)+(AB17*AB46) -> 1496 | AD17: =10%*AC17 -> 149.6 | AE17: =AC17-AD17 -> 1346.4 | AL17: =AE17/3 -> 448.8 | AM17: =AL17 -> 448.8 | AN17: =AM17 -> 448.8 | AO17: =AD17+AF17+AG17+AH17+AI17+AJ17+AK17 -> 149.6 | AP17: =AC17-AO17 -> 1346.4
B18: =B17+1 -> 7 | C18: AJETTEY NOAH | D18: 0559596078 | T18: 1 | V18: 1 | AC18: =(E18*E46)+(F18*F46)+(G18*G46)+(H18*H46)+(I18*I46)+(J18*J46)+(K18*K46)+(L18*L46)+(M18*M46)+(N18*N46)+(O18*O46)+(P18*P46)+(Q18*Q46)+(R18*R46)+(S18*S46)+(T18*T46)+(U18*U46)+(V18*V46)+(W18*W46)+(X18*X46)+(Y18*Y46)+(Z18*Z46)+(AA18*AA46)+(AB18*AB46) -> 7700 | AD18: =10%*AC18 -> 770 | AE18: =AC18-AD18 -> 6930 | AL18: =AE18/3 -> 2310 | AM18: =AL18 -> 2310 | AN18: =AM18 -> 2310 | AO18: =AD18+AF18+AG18+AH18+AI18+AJ18+AK18 -> 770 | AP18: =AC18-AO18 -> 6930
B19: =B18+1 -> 8 | C19: AMUSITEY LAWLEY | G19: 6 | I19: 6 | AC19: =(E19*E46)+(F19*F46)+(G19*G46)+(H19*H46)+(I19*I46)+(J19*J46)+(K19*K46)+(L19*L46)+(M19*M46)+(N19*N46)+(O19*O46)+(P19*P46)+(Q19*Q46)+(R19*R46)+(S19*S46)+(T19*T46)+(U19*U46)+(V19*V46)+(W19*W46)+(X19*X46)+(Y19*Y46)+(Z19*Z46)+(AA19*AA46)+(AB19*AB46) -> 2286 | AD19: =10%*AC19 -> 228.6 | AE19: =AC19-AD19 -> 2057.4 | AL19: =AE19/3 -> 685.8 | AM19: =AL19 -> 685.8 | AN19: =AM19 -> 685.8 | AO19: =AD19+AF19+AG19+AH19+AI19+AJ19+AK19 -> 228.6
B20: =B19+1 -> 9 | C20: MARY SARKODIE | D20: 02488221121 | T20: 1 | AC20: =(E20*E46)+(F20*F46)+(G20*G46)+(H20*H46)+(I20*I46)+(J20*J46)+(K20*K46)+(L20*L46)+(M20*M46)+(N20*N46)+(O20*O46)+(P20*P46)+(Q20*Q46)+(R20*R46)+(S20*S46)+(T20*T46)+(U20*U46)+(V20*V46)+(W20*W46)+(X20*X46)+(Y20*Y46)+(Z20*Z46)+(AA20*AA46)+(AB20*AB46) -> 6800 | AD20: =10%*AC20 -> 680 | AE20: =AC20-AD20 -> 6120 | AL20: =AE20/3 -> 2040 | AM20: =AL20 -> 2040 | AN20: =AM20 -> 2040 | AO20: =AD20+AF20+AG20+AH20+AI20+AJ20+AK20 -> 680
B21: =B20+1 -> 10 | C21: AWINI YAW | D21: 0545111843 | Z21: 1 | AC21: =(E21*E46)+(F21*F46)+(G21*G46)+(H21*H46)+(I21*I46)+(J21*J46)+(K21*K46)+(L21*L46)+(M21*M46)+(N21*N46)+(O21*O46)+(P21*P46)+(Q21*Q46)+(R21*R46)+(S21*S46)+(T21*T46)+(U21*U46)+(V21*V46)+(W21*W46)+(X21*X46)+(Y21*Y46)+(Z21*Z46)+(AA21*AA46)+(AB21*AB46) -> 1904 | AD21: =10%*AC21 -> 190.4 | AE21: =AC21-AD21 -> 1713.6 | AL21: =AE21/3 -> 571.2 | AM21: =AL21 -> 571.2 | AN21: =AM21 -> 571.2
B22: =B21+1 -> 11 | C22: ADU GYAMFI THOMAS | D22: 0244198138 | T22: 1 | AC22: =(E22*E46)+(F22*F46)+(G22*G46)+(H22*H46)+(I22*I46)+(J22*J46)+(K22*K46)+(L22*L46)+(M22*M46)+(N22*N46)+(O22*O46)+(P22*P46)+(Q22*Q46)+(R22*R46)+(S22*S46)+(T22*T46)+(U22*U46)+(V22*V46)+(W22*W46)+(X22*X46)+(Y22*Y46)+(Z22*Z46)+(AA22*AA46)+(AB22*AB46) -> 6800 | AD22: =10%*AC22 -> 680 | AE22: =AC22-AD22 -> 6120 | AL22: =AE22/3 -> 2040 | AM22: =AL22 -> 2040 | AN22: =AM22 -> 2040
B23: =B22+1 -> 12 | C23: ACHAAMA MILLICENT | D23: 0542349614 | E23: 2 | V23: 1 | AC23: =(E23*E46)+(F23*F46)+(G23*G46)+(H23*H46)+(I23*I46)+(J23*J46)+(K23*K46)+(L23*L46)+(M23*M46)+(N23*N46)+(O23*O46)+(P23*P46)+(Q23*Q46)+(R23*R46)+(S23*S46)+(T23*T46)+(U23*U46)+(V23*V46)+(W23*W46)+(X23*X46)+(Y23*Y46)+(Z23*Z46)+(AA23*AA46)+(AB23*AB46) -> 1308 | AD23: =10%*AC23 -> 130.8 | AE23: =AC23-AD23 -> 1177.2 | AL23: =AE23/3 -> 392.4 | AM23: =AL23 -> 392.4 | AN23: =AM23 -> 392.4
B24: =B23+1 -> 13 | C24: AYISAH ASIBI | D24: 0241557179 | T24: 1 | AC24: =(E24*E46)+(F24*F46)+(G24*G46)+(H24*H46)+(I24*I46)+(J24*J46)+(K24*K46)+(L24*L46)+(M24*M46)+(N24*N46)+(O24*O46)+(P24*P46)+(Q24*Q46)+(R24*R46)+(S24*S46)+(T24*T46)+(U24*U46)+(V24*V46)+(W24*W46)+(X24*X46)+(Y24*Y46)+(Z24*Z46)+(AA24*AA46)+(AB24*AB46) -> 6800 | AD24: =10%*AC24 -> 680 | AE24: =AC24-AD24 -> 6120 | AL24: =AE24/3 -> 2040 | AM24: =AL24 -> 2040 | AN24: =AM24 -> 2040
B25: =B24+1 -> 14 | C25: EMMANUEL ASARE | D25: 0542614482 | F25: 1 | AC25: =(E25*E46)+(F25*F46)+(G25*G46)+(H25*H46)+(I25*I46)+(J25*J46)+(K25*J46)+(L25*L46)+(M25*M46)+(N25*N46)+(O25*O46)+(P25*P46)+(Q25*Q46)+(R25*R46)+(S25*S46)+(T25*T46)+(U25*U46)+(V25*V46)+(W25*W46)+(X25*X46)+(Y25*Y46)+(Z25*Z46)+(AA25*AA46)+(AB25*AB46) -> 2448 | AD25: =10%*AC25 -> 244.8 | AE25: =AC25-AD25 -> 2203.2 | AL25: =AE25/3 -> 734.4 | AM25: =AL25 -> 734.4 | AN25: =AM25 -> 734.4
B26: =B25+1 -> 15 | C26: ASANTEWAA RUTH | D26: 0256294169 | V26: 1 | AC26: =(E26*E46)+(F26*F46)+(G26*G46)+(H26*H46)+(I26*I46)+(J26*J46)+(K26*K46)+(L26*L46)+(M26*M46)+(N26*N46)+(O26*O46)+(P26*P46)+(Q26*Q46)+(R26*R46)+(S26*S46)+(T26*T46)+(U26*U46)+(V26*V46)+(W26*W46)+(X26*X46)+(Y26*Y46)+(Z26*Z46)+(AA26*AA46)+(AB26*AB46) -> 900 | AD26: =10%*AC26 -> 90 | AE26: =AC26-AD26 -> 810 | AL26: =AE26/3 -> 270 | AM26: =AL26 -> 270 | AN26: =AM26 -> 270
B27: =B26+1 -> 16 | C27: ADUSEI DOUGLAS | D27: 0542614482 | F27: 1 | Q27: 1 | V27: 1 | AC27: =(E27*E46)+(F27*F46)+(G27*G46)+(H27*H46)+(I27*I46)+(J27*J46)+(K27*K46)+(L27*L46)+(M27*M46)+(N27*N46)+(O27*O46)+(P27*P46)+(Q27*Q46)+(R27*R46)+(S27*S46)+(T27*T46)+(U27*U46)+(V27*V46)+(W27*W46)+(X27*X46)+(Y27*Y46)+(Z27*Z46)+(AA27*AA46)+(AB27*AB46) -> 4844 | AD27: =10%*AC27 -> 484.4 | AE27: =AC27-AD27 -> 4359.6 | AL27: =AE27/3 -> 1453.2 | AM27: =AL27 -> 1453.2 | AN27: =AM27 -> 1453.2
B28: =B27+1 -> 17 | C28: AGYEMANG MICHEAL | D28: 0543567266 | E28: 6 | T28: 1 | AC28: =(E28*E46)+(F28*F46)+(G28*G46)+(H28*H46)+(I28*I46)+(J28*J46)+(K28*J46)+(L28*L46)+(M28*M46)+(N28*N46)+(O28*O46)+(P28*P46)+(Q28*Q46)+(R28*R46)+(S28*S46)+(T28*T46)+(U28*U46)+(V28*V46)+(W28*W46)+(X28*X46)+(Y28*Y46)+(Z28*Z46)+(AA28*AA46)+(AB28*AB46) -> 8024 | AD28: =10%*AC28 -> 802.4 | AE28: =AC28-AD28 -> 7221.6 | AL28: =AE28/3 -> 2407.2 | AM28: =AL28 -> 2407.2 | AN28: =AM28 -> 2407.2
B29: =B28+1 -> 18 | C29: BENYIN COMFORT | D29: 0593434089 | F29: 1 | V29: 1 | AC29: =(E29*E46)+(F29*F46)+(G29*G46)+(H29*H46)+(I29*I46)+(J29*J46)+(K29*K46)+(L29*L46)+(M29*M46)+(N29*N46)+(O29*O46)+(P29*P46)+(Q29*Q46)+(R29*R46)+(S29*S46)+(T29*T46)+(U29*U46)+(V29*V46)+(W29*W46)+(X29*X46)+(Y29*Y46)+(Z29*Z46)+(AA29*AA46)+(AB29*AB46) -> 3348 | AD29: =10%*AC29 -> 334.8 | AE29: =AC29-AD29 -> 3013.2 | AL29: =AE29/3 -> 1004.4 | AM29: =AL29 -> 1004.4 | AN29: =AM29 -> 1004.4
B30: =B29+1 -> 19 | C30: AFFUL KOFI ISAAC | D30: 0549530895 | F30: 3 | AC30: =(E30*E46)+(F30*F46)+(G30*G46)+(H30*H46)+(I30*I46)+(J30*J46)+(K30*K46)+(L30*L46)+(M30*M46)+(N30*N46)+(O30*O46)+(P30*P46)+(Q30*Q46)+(R30*R46)+(S30*S46)+(T30*T46)+(U30*U46)+(V30*V46)+(W30*W46)+(X30*X46)+(Y30*Y46)+(Z30*Z46)+(AA30*AA46)+(AB30*AB46) -> 7344 | AD30: =10%*AC30 -> 734.4 | AE30: =AC30-AD30 -> 6609.6 | AL30: =AE30/3 -> 2203.2 | AM30: =AL30 -> 2203.2 | AN30: =AM30 -> 2203.2
B31: =B30+1 -> 20 | C31: ASARE ERASMUS | D31: 0553883893 | P31: 1 | Q31: 1 | AC31: =(E31*E46)+(F31*F46)+(G31*G46)+(H31*H46)+(I31*I46)+(J31*J46)+(K31*J46)+(L31*L46)+(M31*M46)+(N31*N46)+(O31*O46)+(P31*P46)+(Q31*Q46)+(R31*R46)+(S31*S46)+(T31*T46)+(U31*U46)+(V31*V46)+(W31*W46)+(X31*X46)+(Y31*Y46)+(Z31*Z46)+(AA31*AA46)+(AB31*AB46) -> 2584 | AD31: =10%*AC31 -> 258.4 | AE31: =AC31-AD31 -> 2325.6 | AL31: =AE31/3 -> 775.2 | AM31: =AL31 -> 775.2 | AN31: =AM31 -> 775.2
B32: =B31+1 -> 21 | C32: DANFUL KWAME | D32: 0535977781 | F32: 2 | T32: 1 | Y32: 2 | AC32: =(E32*E46)+(F32*F46)+(G32*G46)+(H32*H46)+(I32*I46)+(J32*J46)+(K32*K46)+(L32*L46)+(M32*M46)+(N32*N46)+(O32*O46)+(P32*P46)+(Q32*Q46)+(R32*R46)+(S32*S46)+(T32*T46)+(U32*U46)+(V32*V46)+(W32*W46)+(X32*X46)+(Y32*Y46)+(Z32*Z46)+(AA32*AA46)+(AB32*AB46) -> 13328 | AD32: =10%*AC32 -> 1332.8 | AE32: =AC32-AD32 -> 11995.2 | AL32: =AE32/3 -> 3998.4 | AM32: =AL32 -> 3998.4 | AN32: =AM32 -> 3998.4
B33: =B32+1 -> 22 | C33: NYANKSON DAVID | D33: 0240352195 | E33: 6 | K33: 6 | Z33: 1 | AB33: 1 | AC33: =(E33*E46)+(F33*F46)+(G33*G46)+(H33*H46)+(I33*I46)+(J33*J46)+(K33*K46)+(L33*L46)+(M33*M46)+(N33*N46)+(O33*O46)+(P33*P46)+(Q33*Q46)+(R33*R46)+(S33*S46)+(T33*T46)+(U33*U46)+(V33*V46)+(W33*W46)+(X33*X46)+(Y33*Y46)+(Z33*Z46)+(AA33*AA46)+(AB33*AB46) -> 5100 | AD33: =10%*AC33 -> 510 | AE33: =AC33-AD33 -> 4590 | AL33: =AE33/3 -> 1530 | AM33: =AL33 -> 1530 | AN33: =AM33 -> 1530
B34: =B33+1 -> 23 | C34: NYANKSON LORD | D34: 0257671950 | F34: 1 | T34: 1 | AC34: =(E34*E46)+(F34*F46)+(G34*G46)+(H34*H46)+(I34*I46)+(J34*J46)+(K34*J46)+(L34*L46)+(M34*M46)+(N34*N46)+(O34*O46)+(P34*P46)+(Q34*Q46)+(R34*R46)+(S34*S46)+(T34*T46)+(U34*U46)+(V34*V46)+(W34*W46)+(X34*X46)+(Y34*Y46)+(Z34*Z46)+(AA34*AA46)+(AB34*AB46) -> 9248 | AD34: =10%*AC34 -> 924.8 | AE34: =AC34-AD34 -> 8323.2 | AL34: =AE34/3 -> 2774.4 | AM34: =AL34 -> 2774.4 | AN34: =AM34 -> 2774.4
B35: =B34+1 -> 24 | AC35: =(E35*E46)+(F35*F46)+(G35*G46)+(H35*H46)+(I35*I46)+(J35*J46)+(K35*K46)+(L35*L46)+(M35*M46)+(N35*N46)+(O35*O46)+(P35*P46)+(Q35*Q46)+(R35*R46)+(S35*S46)+(T35*T46)+(U35*U46)+(V35*V46)+(W35*W46)+(X35*X46)+(Y35*Y46)+(Z35*Z46)+(AA35*AA46)+(AB35*AB46) -> 0 | AD35: =10%*AC35 -> 0 | AE35: =AC35-AD35 -> 0 | AL35: =AE35/3 -> 0 | AM35: =AL35 -> 0 | AN35: =AM35 -> 0
B36: =B35+1 -> 25 | AC36: =(E36*E46)+(F36*F46)+(G36*G46)+(H36*H46)+(I36*I46)+(J36*J46)+(K36*K46)+(L36*L46)+(M36*M46)+(N36*N46)+(O36*O46)+(P36*P46)+(Q36*Q46)+(R36*R46)+(S36*S46)+(T36*T46)+(U36*U46)+(V36*V46)+(W36*W46)+(X36*X46)+(Y36*Y46)+(Z36*Z46)+(AA36*AA46)+(AB36*AB46) -> 0 | AD36: =10%*AC36 -> 0 | AE36: =AC36-AD36 -> 0 | AL36: =AE36/3 -> 0 | AM36: =AL36 -> 0 | AN36: =AM36 -> 0
B37: =B36+1 -> 26 | AC37: =(E37*E46)+(F37*F46)+(G37*G46)+(H37*H46)+(I37*I46)+(J37*J46)+(K37*J46)+(L37*L46)+(M37*M46)+(N37*N46)+(O37*O46)+(P37*P46)+(Q37*Q46)+(R37*R46)+(S37*S46)+(T37*T46)+(U37*U46)+(V37*V46)+(W37*W46)+(X37*X46)+(Y37*Y46)+(Z37*Z46)+(AA37*AA46)+(AB37*AB46) -> 0 | AD37: =10%*AC37 -> 0 | AE37: =AC37-AD37 -> 0 | AL37: =AE37/3 -> 0 | AM37: =AL37 -> 0 | AN37: =AM37 -> 0
B38: =B37+1 -> 27 | AC38: =(E38*E46)+(F38*F46)+(G38*G46)+(H38*H46)+(I38*I46)+(J38*J46)+(K38*K46)+(L38*L46)+(M38*M46)+(N38*N46)+(O38*O46)+(P38*P46)+(Q38*Q46)+(R38*R46)+(S38*S46)+(T38*T46)+(U38*U46)+(V38*V46)+(W38*W46)+(X38*X46)+(Y38*Y46)+(Z38*Z46)+(AA38*AA46)+(AB38*AB46) -> 0 | AD38: =10%*AC38 -> 0 | AE38: =AC38-AD38 -> 0 | AL38: =AE38/3 -> 0 | AM38: =AL38 -> 0 | AN38: =AM38 -> 0
B39: =B38+1 -> 28 | AC39: =(E39*E46)+(F39*F46)+(G39*G46)+(H39*H46)+(I39*I46)+(J39*J46)+(K39*K46)+(L39*L46)+(M39*M46)+(N39*N46)+(O39*O46)+(P39*P46)+(Q39*Q46)+(R39*R46)+(S39*S46)+(T39*T46)+(U39*U46)+(V39*V46)+(W39*W46)+(X39*X46)+(Y39*Y46)+(Z39*Z46)+(AA39*AA46)+(AB39*AB46) -> 0 | AD39: =10%*AC39 -> 0 | AE39: =AC39-AD39 -> 0 | AL39: =AE39/3 -> 0 | AM39: =AL39 -> 0 | AN39: =AM39 -> 0
B40: =B39+1 -> 29 | AC40: =(E40*E46)+(F40*F46)+(G40*G46)+(H40*H46)+(I40*I46)+(J40*J46)+(K40*J46)+(L40*L46)+(M40*M46)+(N40*N46)+(O40*O46)+(P40*P46)+(Q40*Q46)+(R40*R46)+(S40*S46)+(T40*T46)+(U40*U46)+(V40*V46)+(W40*W46)+(X40*X46)+(Y40*Y46)+(Z40*Z46)+(AA40*AA46)+(AB40*AB46) -> 0 | AD40: =10%*AC40 -> 0 | AE40: =AC40-AD40 -> 0 | AL40: =AE40/3 -> 0 | AM40: =AL40 -> 0 | AN40: =AM40 -> 0
B41: =B40+1 -> 30 | AC41: =(E41*E46)+(F41*F46)+(G41*G46)+(H41*H46)+(I41*I46)+(J41*J46)+(K41*K46)+(L41*L46)+(M41*M46)+(N41*N46)+(O41*O46)+(P41*P46)+(Q41*Q46)+(R41*R46)+(S41*S46)+(T41*T46)+(U41*U46)+(V41*V46)+(W41*W46)+(X41*X46)+(Y41*Y46)+(Z41*Z46)+(AA41*AA46)+(AB41*AB46) -> 0 | AD41: =10%*AC41 -> 0 | AE41: =AC41-AD41 -> 0 | AL41: =AE41/3 -> 0 | AM41: =AL41 -> 0 | AN41: =AM41 -> 0
B42: =B41+1 -> 31 | AC42: =(E42*E46)+(F42*F46)+(G42*G46)+(H42*H46)+(I42*I46)+(J42*J46)+(K42*K46)+(L42*L46)+(M42*M46)+(N42*N46)+(O42*O46)+(P42*P46)+(Q42*Q46)+(R42*R46)+(S42*S46)+(T42*T46)+(U42*U46)+(V42*V46)+(W42*W46)+(X42*X46)+(Y42*Y46)+(Z42*Z46)+(AA42*AA46)+(AB42*AB46) -> 0 | AD42: =10%*AC42 -> 0 | AE42: =AC42-AD42 -> 0 | AL42: =AE42/3 -> 0 | AM42: =AL42 -> 0 | AN42: =AM42 -> 0
B43: TOTAL | C43: =COUNTA(C12:C42) -> 23 | E43: =SUM(E12:E42) -> 14 | F43: =SUM(F12:F42) -> 12 | G43: =SUM(G12:G42) -> 6 | H43: =SUM(H12:H42) -> 0 | I43: =SUM(I12:I42) -> 6 | J43: =SUM(J12:J42) -> 0 | K43: =SUM(K12:K42) -> 6 | L43: =SUM(L12:L42) -> 0 | ... AP43: =SUM(AP12:AP42) -> 37756.8
C46: Price | E46: 204 | F46: =12*E46 -> 2448 | G46: 177 | H46: =G46*48 -> 8496 | I46: 204 | J46: =I46*12 -> 2448 | K46: 272 | L46: =K46*15 -> 4080 | M46: 116 | N46: =M46*6 -> 696 | O46: 272 | P46: =O46*4 -> 1088 | Q46: 1496 | R46: 272 | S46: =R46*4 -> 1088 | T46: 6800 | U46: 75 | V46: =U46*12 -> 900 | W46: 20 | X46: 68 | Y46: =X46*12 -> 816 | Z46: 1904 | AA46: 122 | AB46: 340

Sheet GYASEHENE
C2: NOTE:
C3: 1. Enter the quantity of agro inputs requested by the farmer either in pcs or boxes under each agro input
C4: 2. Do not change any thing in the excel sheet. The cells are linked
C6: REGION:
C7: DISTRICT:
C8: SOCIETY: | AD8: GYE NYAME
B10: NO. | C10: FARMER NAME | D10: MOBILE NO. | E10: AcetaStar -Adama (1Lt) | G10: Galil | I10: AKATE BRAFO | K10: PHYTOGREEN | M10: BEGREEN | O10: Agyenkwa Liquid Fertilizer (5Lt) | Q10: Matabi (15Lt) | R10: PLANTFEED | T10: Solo Machine | U10: All Wedicides (Glyphosate) | W10: NODOX | X10: ALL GRAMO | Z10: STANDARD PRUNNER | AA10: WELLINGTON BOOT | AB10: OVERALL | AC10: TOTAL AMOUNT (GHc) | AD10: DEPOSIT PAID (GHc) | AE10: OUTS. BALANCE (GHc) | AF10: REPAYMENT PLAN(GHC) | AO10: TOTAL PAYMENT | AP10: REMN
E11: PCs | F11: Box (12pcs) | G11: PCs | H11: Box | I11: PCs | J11: Box | K11: 1LT | L11: BOX(15) | M11: 1GALLON | N11: BOX(6) | O11: PCs | P11: Box(4) | Q11: PCs | R11: 1 GALLON | S11: BOX(4) | T11: PCs | U11: PCS | V11: BOX(12) | W11: PCs | X11: PCS | Y11: BOX(12) | Z11: PC | AA11: PC | AB11: PC | AF11: DEC | AL11: OCT | AM11: NOV | AN11: DEC | AO11: TOTAL PAYMENT | AP11: REMN
B12: =B11+1 -> 1 | C12: OBENG GLADYS | D12: 0558465075 | G12: 17 | AC12: =(E12*E45)+(F12*F45)+(G12*G45)+(H12*H45)+(I12*I45)+(J12*J45)+(K12*K45)+(L12*L45)+(M12*M45)+(N12*N45)+(O12*O45)+(P12*P45)+(Q12*Q45)+(R12*R45)+(S12*S45)+(T12*T45)+(U12*U45)+(V12*V45)+(W12*W45)+(X12*X45)+(Y12*Y45)+(Z12*Z45)+(AA12*AA45)+(AB12*AB45) -> 3009 | AD12: =10%*AC12 -> 300.9 | AE12: =AC12-AD12 -> 2708.1 | AL12: =AE12/3 -> 902.7 | AM12: =AL12 -> 902.7 | AN12: =AM12 -> 902.7 | AO12: =AD12+AF12+AG12+AH12+AI12+AJ12+AK12 -> 300.9 | AP12: =AC12-AO12 -> 2708.1
B13: =B12+1 -> 2 | C13: ANOTSE VERONICA | D13: 0548659133 | G13: 5 | AC13: =(E13*E45)+(F13*F45)+(G13*G45)+(H13*H45)+(I13*I45)+(J13*J45)+(K13*K45)+(L13*L45)+(M13*M45)+(N13*N45)+(O13*O45)+(P13*P45)+(Q13*Q45)+(R13*R45)+(S13*S45)+(T13*T45)+(U13*U45)+(V13*V45)+(W13*W45)+(X13*X45)+(Y13*Y45)+(Z13*Z45)+(AA13*AA45)+(AB13*AB45) -> 885 | AD13: =10%*AC13 -> 88.5 | AE13: =AC13-AD13 -> 796.5 | AL13: =AE13/3 -> 265.5 | AM13: =AL13 -> 265.5 | AN13: =AM13 -> 265.5 | AO13: =AD13+AF13+AG13+AH13+AI13+AJ13+AK13 -> 88.5 | AP13: =AC13-AO13 -> 796.5
B14: =B13+1 -> 3 | C14: SULEMANA SALAMATU | D14: 0558075173 | AC14: =(E14*E45)+(F14*F45)+(G14*G45)+(H14*H45)+(I14*I45)+(J14*J45)+(K14*K45)+(L14*L45)+(M14*M45)+(N14*N45)+(O14*O45)+(P14*P45)+(Q14*Q45)+(R14*R45)+(S14*S45)+(T14*T45)+(U14*U45)+(V14*V45)+(W14*W45)+(X14*X45)+(Y14*Y45)+(Z14*Z45)+(AA14*AA45)+(AB14*AB45) -> 0 | AD14: =10%*AC14 -> 0 | AE14: =AC14-AD14 -> 0 | AL14: =AE14/3 -> 0 | AM14: =AL14 -> 0 | AN14: =AM14 -> 0 | AO14: =AD14+AF14+AG14+AH14+AI14+AJ14+AK14 -> 0 | AP14: =AC14-AO14 -> 0
B15: =B14+1 -> 4 | C15: SALIFU ALHASSAN | D15: 0557102174 | AC15: =(E15*E45)+(F15*F45)+(G15*G45)+(H15*H45)+(I15*I45)+(J15*J45)+(K15*K45)+(L15*L45)+(M15*M45)+(N15*N45)+(O15*O45)+(P15*P45)+(Q15*Q45)+(R15*R45)+(S15*S45)+(T15*T45)+(U15*U45)+(V15*V45)+(W15*W45)+(X15*X45)+(Y15*Y45)+(Z15*Z45)+(AA15*AA45)+(AB15*AB45) -> 0 | AD15: =10%*AC15 -> 0 | AE15: =AC15-AD15 -> 0 | AL15: =AE15/3 -> 0 | AM15: =AL15 -> 0 | AN15: =AM15 -> 0 | AO15: =AD15+AF15+AG15+AH15+AI15+AJ15+AK15 -> 0 | AP15: =AC15-AO15 -> 0
B16: =B15+1 -> 5 | C16: SEIDU YAKUBU | D16: 0558075173 | AC16: =(E16*E45)+(F16*F45)+(G16*G45)+(H16*H45)+(I16*I45)+(J16*J45)+(K16*K45)+(L16*L45)+(M16*M45)+(N16*N45)+(O16*O45)+(P16*P45)+(Q16*Q45)+(R16*R45)+(S16*S45)+(T16*T45)+(U16*U45)+(V16*V45)+(W16*W45)+(X16*X45)+(Y16*Y45)+(Z16*Z45)+(AA16*AA45)+(AB16*AB45) -> 0 | AD16: =10%*AC16 -> 0 | AE16: =AC16-AD16 -> 0 | AL16: =AE16/3 -> 0 | AM16: =AL16 -> 0 | AN16: =AM16 -> 0 | AO16: =AD16+AF16+AG16+AH16+AI16+AJ16+AK16 -> 0 | AP16: =AC16-AO16 -> 0
B17: =B16+1 -> 6 | C17: ANINIG YAW | D17: 0553629978 | H17: 1 | T17: 1 | AC17: =(E17*E45)+(F17*F45)+(G17*G45)+(H17*H45)+(I17*I45)+(J17*J49)+(K17*K45)+(L17*L45)+(M17*M45)+(N17*N45)+(O17*O45)+(P17*P45)+(Q17*Q45)+(R17*R45)+(S17*S45)+(T17*T45)+(U17*U45)+(V17*V45)+(W17*W45)+(X17*X45)+(Y17*Y45)+(Z17*Z45)+(AA17*AA45)+(AB17*AB45) -> 15296 | AD17: =10%*AC17 -> 1529.6 | AE17: =AC17-AD17 -> 13766.4 | AL17: =AE17/3 -> 4588.8 | AM17: =AL17 -> 4588.8 | AN17: =AM17 -> 4588.8 | AO17: =AD17+AF17+AG17+AH17+AI17+AJ17+AK17 -> 1529.6 | AP17: =AC17-AO17 -> 13766.4
B18: =B17+1 -> 7 | C18: NKRUMAH ANTHONY | D18: 0247342328 | G18: 10 | AC18: =(E18*E45)+(F18*F45)+(G18*G45)+(H18*H45)+(I18*I45)+(J18*J45)+(K18*K45)+(L18*L45)+(M18*M45)+(N18*N45)+(O18*O45)+(P18*P45)+(Q18*Q45)+(R18*R45)+(S18*S45)+(T18*T45)+(U18*U45)+(V18*V45)+(W18*W45)+(X18*X45)+(Y18*Y45)+(Z18*Z45)+(AA18*AA45)+(AB18*AB45) -> 1770 | AD18: =10%*AC18 -> 177 | AE18: =AC18-AD18 -> 1593 | AL18: =AE18/3 -> 531 | AM18: =AL18 -> 531 | AN18: =AM18 -> 531 | AO18: =AD18+AF18+AG18+AH18+AI18+AJ18+AK18 -> 177 | AP18: =AC18-AO18 -> 1593
B19: =B18+1 -> 8 | C19: AGBOZA JULIANA | D19: 0241558481 | G19: 10 | AC19: =(E19*E45)+(F19*F45)+(G19*G45)+(H19*H45)+(I19*I45)+(J19*J45)+(K19*K45)+(L19*L45)+(M19*M45)+(N19*N45)+(O19*O45)+(P19*P45)+(Q19*Q45)+(R19*R45)+(S19*S45)+(T19*T45)+(U19*U45)+(V19*V45)+(W19*W45)+(X19*X45)+(Y19*Y45)+(Z19*Z45)+(AA19*AA45)+(AB19*AB45) -> 1770 | AD19: =10%*AC19 -> 177 | AE19: =AC19-AD19 -> 1593 | AL19: =AE19/3 -> 531 | AM19: =AL19 -> 531 | AN19: =AM19 -> 531 | AO19: =AD19+AF19+AG19+AH19+AI19+AJ19+AK19 -> 177 | AP19: =AC19-AO19 -> 1593
B20: =B19+1 -> 9 | C20: BADU HANNAH | D20: 0248161111 | G20: 15 | T20: 1 | AC20: =(E20*E45)+(F20*F45)+(G20*G45)+(H20*H45)+(I20*I45)+(J20*J45)+(K20*K45)+(L20*L45)+(M20*M45)+(N20*N45)+(O20*O45)+(P20*P45)+(Q20*Q45)+(R20*R45)+(S20*S45)+(T20*T45)+(U20*U45)+(V20*V45)+(W20*W45)+(X20*X45)+(Y20*Y45)+(Z20*Z45)+(AA20*AA45)+(AB20*AB45) -> 9455 | AD20: =10%*AC20 -> 945.5 | AE20: =AC20-AD20 -> 8509.5 | AL20: =AE20/3 -> 2836.5 | AM20: =AL20 -> 2836.5 | AN20: =AM20 -> 2836.5 | AO20: =AD20+AF20+AG20+AH20+AI20+AJ20+AK20 -> 945.5 | AP20: =AC20-AO20 -> 8509.5
B21: =B20+1 -> 10 | C21: MENSAH GEORGINA | D21: 0535230538 | G21: 2 | AA21: 1 | AC21: =(E21*E45)+(F21*F45)+(G21*G45)+(H21*H45)+(I21*I45)+(J21*J45)+(K21*K45)+(L21*L45)+(M21*M45)+(N21*N45)+(O21*O45)+(P21*P45)+(Q21*Q45)+(R21*R45)+(S21*S45)+(T21*T45)+(U21*U45)+(V21*V45)+(W21*W45)+(X21*X45)+(Y21*Y45)+(Z21*Z45)+(AA21*AA45)+(AB21*AB45) -> 476 | AD21: =10%*AC21 -> 47.6 | AE21: =AC21-AD21 -> 428.4 | AL21: =AE21/3 -> 142.8 | AM21: =AL21 -> 142.8 | AN21: =AM21 -> 142.8 | AO21: =AD21+AF21+AG21+AH21+AI21+AJ21+AK21 -> 47.6 | AP21: =AC21-AO21 -> 428.4
B22: =B21+1 -> 11 | AC22: =(E22*E45)+(F22*F45)+(G22*G45)+(H22*H45)+(I22*I45)+(J22*J45)+(K22*K45)+(L22*L45)+(M22*M45)+(N22*N45)+(O22*O45)+(P22*P45)+(Q22*Q45)+(R22*R45)+(S22*S45)+(T22*T45)+(U22*U45)+(V22*V45)+(W22*W45)+(X22*X45)+(Y22*Y45)+(Z22*Z45)+(AA22*AA45)+(AB22*AB45) -> 0 | AD22: =10%*AC22 -> 0 | AE22: =AC22-AD22 -> 0 | AG22: =AE22/3 -> 0 | AH22: =AG22 -> 0 | AI22: =AH22 -> 0
B23: =B22+1 -> 12 | AC23: =(E23*E45)+(F23*F45)+(G23*G45)+(H23*H45)+(I23*I45)+(J23*J45)+(K23*K45)+(L23*L45)+(M23*M45)+(N23*N45)+(O23*O45)+(P23*P45)+(Q23*Q45)+(R23*R45)+(S23*S45)+(T23*T45)+(U23*U45)+(V23*V45)+(W23*W45)+(X23*X45)+(Y23*Y45)+(Z23*Z45)+(AA23*AA45)+(AB23*AB45) -> 0 | AD23: =10%*AC23 -> 0 | AE23: =AC23-AD23 -> 0 | AG23: =AE23/3 -> 0 | AH23: =AG23 -> 0 | AI23: =AH23 -> 0
B24: =B23+1 -> 13 | AC24: =(E24*E45)+(F24*F45)+(G24*G45)+(H24*H45)+(I24*I45)+(J24*J45)+(K24*J45)+(L24*L45)+(M24*M45)+(N24*N45)+(O24*O45)+(P24*P45)+(Q24*Q45)+(R24*R45)+(S24*S45)+(T24*T45)+(U24*U45)+(V24*V45)+(W24*W45)+(X24*X45)+(Y24*Y45)+(Z24*Z45)+(AA24*AA45)+(AB24*AB45) -> 0 | AD24: =10%*AC24 -> 0 | AE24: =AC24-AD24 -> 0 | AG24: =AE24/3 -> 0 | AH24: =AG24 -> 0 | AI24: =AH24 -> 0
B25: =B24+1 -> 14 | AC25: =(E25*E45)+(F25*F45)+(G25*G45)+(H25*H45)+(I25*I45)+(J25*J45)+(K25*K45)+(L25*L45)+(M25*M45)+(N25*N45)+(O25*O45)+(P25*P45)+(Q25*Q45)+(R25*R45)+(S25*S45)+(T25*T45)+(U25*U45)+(V25*V45)+(W25*W45)+(X25*X45)+(Y25*Y45)+(Z25*Z45)+(AA25*AA45)+(AB25*AB45) -> 0 | AD25: =10%*AC25 -> 0 | AE25: =AC25-AD25 -> 0 | AG25: =AE25/3 -> 0 | AH25: =AG25 -> 0 | AI25: =AH25 -> 0
B26: =B25+1 -> 15 | AC26: =(E26*E45)+(F26*F45)+(G26*G45)+(H26*H45)+(I26*I45)+(J26*J45)+(K26*K45)+(L26*L45)+(M26*M45)+(N26*N45)+(O26*O45)+(P26*P45)+(Q26*Q45)+(R26*R45)+(S26*S45)+(T26*T45)+(U26*U45)+(V26*V45)+(W26*W45)+(X26*X45)+(Y26*Y45)+(Z26*Z45)+(AA26*AA45)+(AB26*AB45) -> 0 | AD26: =10%*AC26 -> 0 | AE26: =AC26-AD26 -> 0 | AG26: =AE26/3 -> 0 | AH26: =AG26 -> 0 | AI26: =AH26 -> 0
B27: =B26+1 -> 16 | AC27: =(E27*E45)+(F27*F45)+(G27*G45)+(H27*H45)+(I27*I45)+(J27*J45)+(K27*J45)+(L27*L45)+(M27*M45)+(N27*N45)+(O27*O45)+(P27*P45)+(Q27*Q45)+(R27*R45)+(S27*S45)+(T27*T45)+(U27*U45)+(V27*V45)+(W27*W45)+(X27*X45)+(Y27*Y45)+(Z27*Z45)+(AA27*AA45)+(AB27*AB45) -> 0 | AD27: =10%*AC27 -> 0 | AE27: =AC27-AD27 -> 0 | AG27: =AE27/3 -> 0 | AH27: =AG27 -> 0 | AI27: =AH27 -> 0
B28: =B27+1 -> 17 | AC28: =(E28*E45)+(F28*F45)+(G28*G45)+(H28*H45)+(I28*I45)+(J28*J45)+(K28*K45)+(L28*L45)+(M28*M45)+(N28*N45)+(O28*O45)+(P28*P45)+(Q28*Q45)+(R28*R45)+(S28*S45)+(T28*T45)+(U28*U45)+(V28*V45)+(W28*W45)+(X28*X45)+(Y28*Y45)+(Z28*Z45)+(AA28*AA45)+(AB28*AB45) -> 0 | AD28: =10%*AC28 -> 0 | AE28: =AC28-AD28 -> 0 | AG28: =AE28/3 -> 0 | AH28: =AG28 -> 0 | AI28: =AH28 -> 0
B29: =B28+1 -> 18 | AC29: =(E29*E45)+(F29*F45)+(G29*G45)+(H29*H45)+(I29*I45)+(J29*J45)+(K29*K45)+(L29*L45)+(M29*M45)+(N29*N45)+(O29*O45)+(P29*P45)+(Q29*Q45)+(R29*R45)+(S29*S45)+(T29*T45)+(U29*U45)+(V29*V45)+(W29*W45)+(X29*X45)+(Y29*Y45)+(Z29*Z45)+(AA29*AA45)+(AB29*AB45) -> 0 | AD29: =10%*AC29 -> 0 | AE29: =AC29-AD29 -> 0 | AG29: =AE29/3 -> 0 | AH29: =AG29 -> 0 | AI29: =AH29 -> 0
B30: =B29+1 -> 19 | AC30: =(E30*E45)+(F30*F45)+(G30*G45)+(H30*H45)+(I30*I45)+(J30*J45)+(K30*J45)+(L30*L45)+(M30*M45)+(N30*N45)+(O30*O45)+(P30*P45)+(Q30*Q45)+(R30*R45)+(S30*S45)+(T30*T45)+(U30*U45)+(V30*V45)+(W30*W45)+(X30*X45)+(Y30*Y45)+(Z30*Z45)+(AA30*AA45)+(AB30*AB45) -> 0 | AD30: =10%*AC30 -> 0 | AE30: =AC30-AD30 -> 0 | AG30: =AE30/3 -> 0 | AH30: =AG30 -> 0 | AI30: =AH30 -> 0
B31: =B30+1 -> 20 | AC31: =(E31*E45)+(F31*F45)+(G31*G45)+(H31*H45)+(I31*I45)+(J31*J45)+(K31*K45)+(L31*L45)+(M31*M45)+(N31*N45)+(O31*O45)+(P31*P45)+(Q31*Q45)+(R31*R45)+(S31*S45)+(T31*T45)+(U31*U45)+(V31*V45)+(W31*W45)+(X31*X45)+(Y31*Y45)+(Z31*Z45)+(AA31*AA45)+(AB31*AB45) -> 0 | AD31: =10%*AC31 -> 0 | AE31: =AC31-AD31 -> 0 | AG31: =AE31/3 -> 0 | AH31: =AG31 -> 0 | AI31: =AH31 -> 0
B32: =B31+1 -> 21 | AC32: =(E32*E45)+(F32*F45)+(G32*G45)+(H32*H45)+(I32*I45)+(J32*J45)+(K32*K45)+(L32*L45)+(M32*M45)+(N32*N45)+(O32*O45)+(P32*P45)+(Q32*Q45)+(R32*R45)+(S32*S45)+(T32*T45)+(U32*U45)+(V32*V45)+(W32*W45)+(X32*X45)+(Y32*Y45)+(Z32*Z45)+(AA32*AA45)+(AB32*AB45) -> 0 | AD32: =10%*AC32 -> 0 | AE32: =AC32-AD32 -> 0 | AG32: =AE32/3 -> 0 | AH32: =AG32 -> 0 | AI32: =AH32 -> 0
B33: =B32+1 -> 22 | AC33: =(E33*E45)+(F33*F45)+(G33*G45)+(H33*H45)+(I33*I45)+(J33*J45)+(K33*J45)+(L33*L45)+(M33*M45)+(N33*N45)+(O33*O45)+(P33*P45)+(Q33*Q45)+(R33*R45)+(S33*S45)+(T33*T45)+(U33*U45)+(V33*V45)+(W33*W45)+(X33*X45)+(Y33*Y45)+(Z33*Z45)+(AA33*AA45)+(AB33*AB45) -> 0 | AD33: =10%*AC33 -> 0 | AE33: =AC33-AD33 -> 0 | AG33: =AE33/3 -> 0 | AH33: =AG33 -> 0 | AI33: =AH33 -> 0
B34: =B33+1 -> 23 | AC34: =(E34*E45)+(F34*F45)+(G34*G45)+(H34*H45)+(I34*I45)+(J34*J45)+(K34*K45)+(L34*L45)+(M34*M45)+(N34*N45)+(O34*O45)+(P34*P45)+(Q34*Q45)+(R34*R45)+(S34*S45)+(T34*T45)+(U34*U45)+(V34*V45)+(W34*W45)+(X34*X45)+(Y34*Y45)+(Z34*Z45)+(AA34*AA45)+(AB34*AB45) -> 0 | AD34: =10%*AC34 -> 0 | AE34: =AC34-AD34 -> 0 | AG34: =AE34/3 -> 0 | AH34: =AG34 -> 0 | AI34: =AH34 -> 0
B35: =B34+1 -> 24 | AC35: =(E35*E45)+(F35*F45)+(G35*G45)+(H35*H45)+(I35*I45)+(J35*J45)+(K35*K45)+(L35*L45)+(M35*M45)+(N35*N45)+(O35*O45)+(P35*P45)+(Q35*Q45)+(R35*R45)+(S35*S45)+(T35*T45)+(U35*U45)+(V35*V45)+(W35*W45)+(X35*X45)+(Y35*Y45)+(Z35*Z45)+(AA35*AA45)+(AB35*AB45) -> 0 | AD35: =10%*AC35 -> 0 | AE35: =AC35-AD35 -> 0 | AG35: =AE35/3 -> 0 | AH35: =AG35 -> 0 | AI35: =AH35 -> 0
B36: =B35+1 -> 25 | AC36: =(E36*E45)+(F36*F45)+(G36*G45)+(H36*H45)+(I36*I45)+(J36*J45)+(K36*J45)+(L36*L45)+(M36*M45)+(N36*N45)+(O36*O45)+(P36*P45)+(Q36*Q45)+(R36*R45)+(S36*S45)+(T36*T45)+(U36*U45)+(V36*V45)+(W36*W45)+(X36*X45)+(Y36*Y45)+(Z36*Z45)+(AA36*AA45)+(AB36*AB45) -> 0 | AD36: =10%*AC36 -> 0 | AE36: =AC36-AD36 -> 0 | AG36: =AE36/3 -> 0 | AH36: =AG36 -> 0 | AI36: =AH36 -> 0
B37: =B36+1 -> 26 | AC37: =(E37*E45)+(F37*F45)+(G37*G45)+(H37*H45)+(I37*I45)+(J37*J45)+(K37*K45)+(L37*L45)+(M37*M45)+(N37*N45)+(O37*O45)+(P37*P45)+(Q37*Q45)+(R37*R45)+(S37*S45)+(T37*T45)+(U37*U45)+(V37*V45)+(W37*W45)+(X37*X45)+(Y37*Y45)+(Z37*Z45)+(AA37*AA45)+(AB37*AB45) -> 0 | AD37: =10%*AC37 -> 0 | AE37: =AC37-AD37 -> 0 | AG37: =AE37/3 -> 0 | AH37: =AG37 -> 0 | AI37: =AH37 -> 0
B38: =B37+1 -> 27 | AC38: =(E38*E45)+(F38*F45)+(G38*G45)+(H38*H45)+(I38*I45)+(J38*J45)+(K38*K45)+(L38*L45)+(M38*M45)+(N38*N45)+(O38*O45)+(P38*P45)+(Q38*Q45)+(R38*R45)+(S38*S45)+(T38*T45)+(U38*U45)+(V38*V45)+(W38*W45)+(X38*X45)+(Y38*Y45)+(Z38*Z45)+(AA38*AA45)+(AB38*AB45) -> 0 | AD38: =10%*AC38 -> 0 | AE38: =AC38-AD38 -> 0 | AG38: =AE38/3 -> 0 | AH38: =AG38 -> 0 | AI38: =AH38 -> 0
B39: =B38+1 -> 28 | AC39: =(E39*E45)+(F39*F45)+(G39*G45)+(H39*H45)+(I39*I45)+(J39*J45)+(K39*J45)+(L39*L45)+(M39*M45)+(N39*N45)+(O39*O45)+(P39*P45)+(Q39*Q45)+(R39*R45)+(S39*S45)+(T39*T45)+(U39*U45)+(V39*V45)+(W39*W45)+(X39*X45)+(Y39*Y45)+(Z39*Z45)+(AA39*AA45)+(AB39*AB45) -> 0 | AD39: =10%*AC39 -> 0 | AE39: =AC39-AD39 -> 0 | AG39: =AE39/3 -> 0 | AH39: =AG39 -> 0 | AI39: =AH39 -> 0
B40: =B39+1 -> 29 | AC40: =(E40*E45)+(F40*F45)+(G40*G45)+(H40*H45)+(I40*I45)+(J40*J45)+(K40*K45)+(L40*L45)+(M40*M45)+(N40*N45)+(O40*O45)+(P40*P45)+(Q40*Q45)+(R40*R45)+(S40*S45)+(T40*T45)+(U40*U45)+(V40*V45)+(W40*W45)+(X40*X45)+(Y40*Y45)+(Z40*Z45)+(AA40*AA45)+(AB40*AB45) -> 0 | AD40: =10%*AC40 -> 0 | AE40: =AC40-AD40 -> 0 | AG40: =AE40/3 -> 0 | AH40: =AG40 -> 0 | AI40: =AH40 -> 0
B41: =B40+1 -> 30 | AC41: =(E41*E45)+(F41*F45)+(G41*G45)+(H41*H45)+(I41*I45)+(J41*J45)+(K41*K45)+(L41*L45)+(M41*M45)+(N41*N45)+(O41*O45)+(P41*P45)+(Q41*Q45)+(R41*R45)+(S41*S45)+(T41*T45)+(U41*U45)+(V41*V45)+(W41*W45)+(X41*X45)+(Y41*Y45)+(Z41*Z45)+(AA41*AA45)+(AB41*AB45) -> 0 | AD41: =10%*AC41 -> 0 | AE41: =AC41-AD41 -> 0 | AG41: =AE41/3 -> 0 | AH41: =AG41 -> 0 | AI41: =AH41 -> 0
B42: TOTAL | C42: =COUNTA(C12:C41) -> 10 | E42: =SUM(E12:E41) -> 0 | F42: =SUM(F12:F41) -> 0 | G42: =SUM(G12:G41) -> 59 | H42: =SUM(H12:H41) -> 1 | I42: =SUM(I12:I41) -> 0 | J42: =SUM(J12:J41) -> 0 | K42: =SUM(K12:K41) -> 0 | L42: =SUM(L12:L41) -> 0 | ... AE42: =SUM(AE12:AE41) -> 29394.9 | AG42: =SUM(AG12:AG41) -> 0 | AH42: =SUM(AH12:AH41) -> 0 | AI42: =SUM(AI12:AI41) -> 0 | AJ42: =SUM(AJ12:AJ41) -> 0 | AK42: =SUM(AK12:AK41) -> 0 | AL42: =SUM(AL12:AL41) -> 9798.3 | AM42: =SUM(AM12:AM41) -> 9798.3 | AN42: =SUM(AN12:AN41) -> 9798.3 | ... AP42: =SUM(AP12:AP41) -> 29394.9
C45: Price | E45: 204 | F45: =12*E45 -> 2448 | G45: 177 | H45: =G45*48 -> 8496 | I45: 204 | J45: =I45*12 -> 2448 | K45: 177 | L45: =K45*15 -> 2655 | M45: 34 | N45: =M45*6 -> 204 | O45: 272 | P45: =O45*4 -> 1088 | Q45: 1496 | R45: 204 | S45: =R45*4 -> 816 | T45: 6800 | U45: 75 | V45: =U45*12 -> 900 | W45: 13.6 | X45: 68 | Y45: =X45*12 -> 816 | Z45: 1904 | AA45: 122 | AB45: 340

Sheet ADIEPANA
C2: NOTE:
C3: 1. Enter the quantity of agro inputs requested by the farmer either in pcs or boxes under each agro input
C4: 2. Do not change any thing in the excel sheet. The cells are linked
C6: REGION:
C7: DISTRICT:
C8: SOCIETY: | D8: ADOM
B10: NO. | C10: FARMER NAME | D10: MOBILE NO. | E10: AcetaStar -Adama (1Lt) | G10: Galil | I10: AKATE BRAFO | K10: PHYTOGREEN | M10: BEGREEN | O10: Agyenkwa Liquid Fertilizer (5Lt) | Q10: Matabi (15Lt) | R10: PLANTFEED | T10: Solo Machine | U10: All Wedicides (Glyphosate) | W10: NODOX | X10: ALL GRAMO | Z10: STANDARD PRUNNER | AA10: WELLINGTON BOOT | AB10: OVERALL | AC10: TOTAL AMOUNT (GHc) | AD10: DEPOSIT PAID (GHc) | AE10: OUTS. BALANCE (GHc) | AF10: REPAYMENT PLAN(GHC) | AO10: TOTAL PAYMENT | AP10: REMN
E11: PCs | F11: Box (12pcs) | G11: PCs | H11: Box | I11: PCs | J11: Box | K11: 1LT | L11: BOX(15) | M11: 1GALLON | N11: BOX(6) | O11: PCs | P11: Box(4) | Q11: PCs | R11: 1 GALLON | S11: BOX(4) | T11: PCs | U11: PCS | V11: BOX(12) | W11: PCs | X11: PCS | Y11: BOX(12) | Z11: PC | AA11: PC | AB11: PC | AF11: OCT | AG11: NOV | AH11: NOV | AI11: DEC | AL11: OCT | AM11: NOV | AN11: DEC
B12: =B11+1 -> 1 | C12: ANANE ROSE | D12: 0591979426 | F12: 3 | Z12: 1 | AC12: =(E12*E46)+(F12*F46)+(G12*G46)+(H12*H46)+(I12*I46)+(J12*J46)+(K12*K46)+(L12*L46)+(M12*M46)+(N12*N46)+(O12*O46)+(P12*P46)+(Q12*Q46)+(R12*R46)+(S12*S46)+(T12*T46)+(U12*U46)+(V12*V46)+(W12*W46)+(X12*X46)+(Y12*Y46)+(Z12*Z46)+(AA12*AA46)+(AB12*AB46) -> 9248 | AD12: =10%*AC12 -> 924.8 | AE12: =AC12-AD12 -> 8323.2 | AL12: =AE12/3 -> 2774.4 | AM12: =AL12 -> 2774.4 | AN12: =AM12 -> 2774.4 | AO12: =AD12+AF12+AG12+AH12+AI12+AJ12+AK12 -> 924.8 | AP12: =AC12-AO12 -> 8323.2
B13: =B12+1 -> 2 | C13: MENSAH AMOS | D13: 0543364140 | F13: 1 | T13: 1 | AC13: =(E13*E46)+(F13*F46)+(G13*G46)+(H13*H46)+(I13*I46)+(J13*J46)+(K13*K46)+(L13*L46)+(M13*M46)+(N13*N46)+(O13*O46)+(P13*P46)+(Q13*Q46)+(R13*R46)+(S13*S46)+(T13*T46)+(U13*U46)+(V13*V46)+(W13*W46)+(X13*X46)+(Y13*Y46)+(Z13*Z46)+(AA13*AA46)+(AB13*AB46) -> 9248 | AD13: =10%*AC13 -> 924.8 | AE13: =AC13-AD13 -> 8323.2 | AL13: =AE13/3 -> 2774.4 | AM13: =AL13 -> 2774.4 | AN13: =AM13 -> 2774.4 | AO13: =AD13+AF13+AG13+AH13+AI13+AJ13+AK13 -> 924.8 | AP13: =AC13-AO13 -> 8323.2
B14: =B13+1 -> 3 | C14: ADDAI ERNEST | D14: 0243341869 | G14: 10 | AC14: =(E14*E46)+(F14*F46)+(G14*G46)+(H14*H46)+(I14*I46)+(J14*J46)+(K14*K46)+(L14*L46)+(M14*M46)+(N14*N46)+(O14*O46)+(P14*P46)+(Q14*Q46)+(R14*R46)+(S14*S46)+(T14*T46)+(U14*U46)+(V14*V46)+(W14*W46)+(X14*X46)+(Y14*Y46)+(Z14*Z46)+(AA14*AA46)+(AB14*AB46) -> 1770 | AD14: =10%*AC14 -> 177 | AE14: =AC14-AD14 -> 1593 | AL14: =AE14/3 -> 531 | AM14: =AL14 -> 531 | AN14: =AM14 -> 531 | AO14: =AD14+AF14+AG14+AH14+AI14+AJ14+AK14 -> 177 | AP14: =AC14-AO14 -> 1593
B15: =B14+1 -> 4 | C15: ISSAKA ANTHONY | D15: 0554992080 | G15: 10 | AC15: =(E15*E46)+(F15*F46)+(G15*G46)+(H15*H46)+(I15*I46)+(J15*J46)+(K15*K46)+(L15*L46)+(M15*M46)+(N15*N46)+(O15*O46)+(P15*P46)+(Q15*Q46)+(R15*R46)+(S15*S46)+(T15*T46)+(U15*U46)+(V15*V46)+(W15*W46)+(X15*X46)+(Y15*Y46)+(Z15*Z46)+(AA15*AA46)+(AB15*AB46) -> 1770 | AD15: =10%*AC15 -> 177 | AE15: =AC15-AD15 -> 1593 | AL15: =AE15/3 -> 531 | AM15: =AL15 -> 531 | AN15: =AM15 -> 531 | AO15: =AD15+AF15+AG15+AH15+AI15+AJ15+AK15 -> 177 | AP15: =AC15-AO15 -> 1593
B16: =B15+1 -> 5 | C16: AKAWBOAH ROBERT | D16: 0249061171 | G16: 1 | AC16: =(E16*E46)+(F16*F46)+(G16*G46)+(H16*H46)+(I16*I46)+(J16*J46)+(K16*K46)+(L16*L46)+(M16*M46)+(N16*N46)+(O16*O46)+(P16*P46)+(Q16*Q46)+(R16*R46)+(S16*S46)+(T16*T46)+(U16*U46)+(V16*V46)+(W16*W46)+(X16*X46)+(Y16*Y46)+(Z16*Z46)+(AA16*AA46)+(AB16*AB46) -> 177 | AD16: =10%*AC16 -> 17.7 | AE16: =AC16-AD16 -> 159.3 | AL16: =AE16/3 -> 53.1 | AM16: =AL16 -> 53.1 | AN16: =AM16 -> 53.1 | AO16: =AD16+AF16+AG16+AH16+AI16+AJ16+AK16 -> 17.7 | AP16: =AC16-AO16 -> 159.3
B17: =B16+1 -> 6 | C17: AYOMAN MARTIN | D17: 0547277885 | G17: 10 | AC17: =(E17*E46)+(F17*F46)+(G17*G46)+(H17*H46)+(I17*I46)+(J17*J50)+(K17*K46)+(L17*L46)+(M17*M46)+(N17*N46)+(O17*O46)+(P17*P46)+(Q17*Q46)+(R17*R46)+(S17*S46)+(T17*T46)+(U17*U46)+(V17*V46)+(W17*W46)+(X17*X46)+(Y17*Y46)+(Z17*Z46)+(AA17*AA46)+(AB17*AB46) -> 1770 | AD17: =10%*AC17 -> 177 | AE17: =AC17-AD17 -> 1593 | AL17: =AE17/3 -> 531 | AM17: =AL17 -> 531 | AN17: =AM17 -> 531 | AO17: =AD17+AF17+AG17+AH17+AI17+AJ17+AK17 -> 177 | AP17: =AC17-AO17 -> 1593
B18: =B17+1 -> 7 | C18: ASIMARTEY GEORGE | D18: 0592892457 | G18: 2 | T18: 1 | AC18: =(E18*E46)+(F18*F46)+(G18*G46)+(H18*H46)+(I18*I46)+(J18*J46)+(K18*K46)+(L18*L46)+(M18*M46)+(N18*N46)+(O18*O46)+(P18*P46)+(Q18*Q46)+(R18*R46)+(S18*S46)+(T18*T46)+(U18*U46)+(V18*V46)+(W18*W46)+(X18*X46)+(Y18*Y46)+(Z18*Z46)+(AA18*AA46)+(AB18*AB46) -> 7154 | AD18: =10%*AC18 -> 715.4 | AE18: =AC18-AD18 -> 6438.6 | AL18: =AE18/3 -> 2146.2 | AM18: =AL18 -> 2146.2 | AN18: =AM18 -> 2146.2 | AO18: =AD18+AF18+AG18+AH18+AI18+AJ18+AK18 -> 715.4 | AP18: =AC18-AO18 -> 6438.6
B19: =B18+1 -> 8 | C19: KYEREWAA MERCY | D19: 0533350145 | I19: 2 | O19: 2 | AC19: =(E19*E46)+(F19*F46)+(G19*G46)+(H19*H46)+(I19*I46)+(J19*J46)+(K19*K46)+(L19*L46)+(M19*M46)+(N19*N46)+(O19*O46)+(P19*P46)+(Q19*Q46)+(R19*R46)+(S19*S46)+(T19*T46)+(U19*U46)+(V19*V46)+(W19*W46)+(X19*X46)+(Y19*Y46)+(Z19*Z46)+(AA19*AA46)+(AB19*AB46) -> 762 | AD19: =10%*AC19 -> 76.2 | AE19: =AC19-AD19 -> 685.8 | AL19: =AE19/3 -> 228.6 | AM19: =AL19 -> 228.6 | AN19: =AM19 -> 228.6 | AO19: =AD19+AF19+AG19+AH19+AI19+AJ19+AK19 -> 76.2 | AP19: =AC19-AO19 -> 685.8
B20: =B19+1 -> 9 | C20: KANKAM KINGSLEY | D20: 0535760424 | F20: 1 | J20: 2 | T20: 1 | AC20: =(E20*E46)+(F20*F46)+(G20*G46)+(H20*H46)+(I20*I46)+(J20*J46)+(K20*K46)+(L20*L46)+(M20*M46)+(N20*N46)+(O20*O46)+(P20*P46)+(Q20*Q46)+(R20*R46)+(S20*S46)+(T20*T46)+(U20*U46)+(V20*V46)+(W20*W46)+(X20*X46)+(Y20*Y46)+(Z20*Z46)+(AA20*AA46)+(AB20*AB46) -> 13496 | AD20: =10%*AC20 -> 1349.6 | AE20: =AC20-AD20 -> 12146.4 | AL20: =AE20/3 -> 4048.8 | AM20: =AL20 -> 4048.8 | AN20: =AM20 -> 4048.8 | AO20: =AD20+AF20+AG20+AH20+AI20+AJ20+AK20 -> 1349.6 | AP20: =AC20-AO20 -> 12146.4
B21: =B20+1 -> 10 | C21: OFOSU JANET | D21: 0532503326 | E21: 6 | T21: 1 | AC21: =(E21*E46)+(F21*F46)+(G21*G46)+(H21*H46)+(I21*I46)+(J21*J46)+(K21*K46)+(L21*L46)+(M21*M46)+(N21*N46)+(O21*O46)+(P21*P46)+(Q21*Q46)+(R21*R46)+(S21*S46)+(T21*T46)+(U21*U46)+(V21*V46)+(W21*W46)+(X21*X46)+(Y21*Y46)+(Z21*Z46)+(AA21*AA46)+(AB21*AB46) -> 8024 | AD21: =10%*AC21 -> 802.4 | AE21: =AC21-AD21 -> 7221.6 | AL21: =AE21/3 -> 2407.2 | AM21: =AL21 -> 2407.2 | AN21: =AM21 -> 2407.2 | AO21: =AD21+AF21+AG21+AH21+AI21+AJ21+AK21 -> 802.4 | AP21: =AC21-AO21 -> 7221.6
B22: =B21+1 -> 11 | C22: APPIAH EMMANUEL | D22: 0554185817 | T22: 1 | AC22: =(E22*E46)+(F22*F46)+(G22*G46)+(H22*H46)+(I22*I46)+(J22*J46)+(K22*K46)+(L22*L46)+(M22*M46)+(N22*N46)+(O22*O46)+(P22*P46)+(Q22*Q46)+(R22*R46)+(S22*S46)+(T22*T46)+(U22*U46)+(V22*V46)+(W22*W46)+(X22*X46)+(Y22*Y46)+(Z22*Z46)+(AA22*AA46)+(AB22*AB46) -> 6800 | AD22: =10%*AC22 -> 680 | AE22: =AC22-AD22 -> 6120 | AL22: =AE22/3 -> 2040 | AM22: =AL22 -> 2040 | AN22: =AM22 -> 2040 | AO22: =AD22+AF22+AG22+AH22+AI22+AJ22+AK22 -> 680 | AP22: =AC22-AO22 -> 6120
B23: =B22+1 -> 12 | C23: BOADIWAA JANET | D23: 0554185817 | I23: 2 | O23: 2 | AC23: =(E23*E46)+(F23*F46)+(G23*G46)+(H23*H46)+(I23*I46)+(J23*J46)+(K23*K46)+(L23*L46)+(M23*M46)+(N23*N46)+(O23*O46)+(P23*P46)+(Q23*Q46)+(R23*R46)+(S23*S46)+(T23*T46)+(U23*U46)+(V23*V46)+(W23*W46)+(X23*X46)+(Y23*Y46)+(Z23*Z46)+(AA23*AA46)+(AB23*AB46) -> 762 | AD23: =10%*AC23 -> 76.2 | AE23: =AC23-AD23 -> 685.8 | AL23: =AE23/3 -> 228.6 | AM23: =AL23 -> 228.6 | AN23: =AM23 -> 228.6 | AO23: =AD23+AF23+AG23+AH23+AI23+AJ23+AK23 -> 76.2 | AP23: =AC23-AO23 -> 685.8
B24: =B23+1 -> 13 | C24: TIPURA AGNES | D24: 0535584924 | F24: 1 | Q24: 1 | Y24: 1 | AC24: =(E24*E46)+(F24*F46)+(G24*G46)+(H24*H46)+(I24*I46)+(J24*J46)+(K24*K46)+(L24*L46)+(M24*M46)+(N24*N46)+(O24*O46)+(P24*P46)+(Q24*Q46)+(R24*R46)+(S24*S46)+(T24*T46)+(U24*U46)+(V24*V46)+(W24*W46)+(X24*X46)+(Y24*Y46)+(Z24*Z46)+(AA24*AA46)+(AB24*AB46) -> 3536 | AD24: =10%*AC24 -> 353.6 | AE24: =AC24-AD24 -> 3182.4
B25: =B24+1 -> 14 | C25: DONKOR GRACE | D25: 0248048543 | F25: 1 | T25: 1 | Y25: 1 | AC25: =(E25*E46)+(F25*F46)+(G25*G46)+(H25*H46)+(I25*I46)+(J25*J46)+(K25*J46)+(L25*L46)+(M25*M46)+(N25*N46)+(O25*O46)+(P25*P46)+(Q25*Q46)+(R25*R46)+(S25*S46)+(T25*T46)+(U25*U46)+(V25*V46)+(W25*W46)+(X25*X46)+(Y25*Y46)+(Z25*Z46)+(AA25*AA46)+(AB25*AB46) -> 10064 | AD25: =10%*AC25 -> 1006.4 | AE25: =AC25-AD25 -> 9057.6
B26: =B25+1 -> 15 | C26: TAWIA ESTHER | D26: 0548335117 | G26: 40 | T26: 1 | AC26: =(E26*E46)+(F26*F46)+(G26*G46)+(H26*H46)+(I26*I46)+(J26*J46)+(K26*K46)+(L26*L46)+(M26*M46)+(N26*N46)+(O26*O46)+(P26*P46)+(Q26*Q46)+(R26*R46)+(S26*S46)+(T26*T46)+(U26*U46)+(V26*V46)+(W26*W46)+(X26*X46)+(Y26*Y46)+(Z26*Z46)+(AA26*AA46)+(AB26*AB46) -> 13880 | AD26: =10%*AC26 -> 1388 | AE26: =AC26-AD26 -> 12492
B27: =B26+1 -> 16 | C27: TETTEH BENJAMIN | D27: 0591463482 | G27: 24 | K27: 8 | P27: 2 | AC27: =(E27*E46)+(F27*F46)+(G27*G46)+(H27*H46)+(I27*I46)+(J27*J46)+(K27*K46)+(L27*L46)+(M27*M46)+(N27*N46)+(O27*O46)+(P27*P46)+(Q27*Q46)+(R27*R46)+(S27*S46)+(T27*T46)+(U27*U46)+(V27*V46)+(W27*W46)+(X27*X46)+(Y27*Y46)+(Z27*Z46)+(AA27*AA46)+(AB27*AB46) -> 7296 | AD27: =10%*AC27 -> 729.6 | AE27: =AC27-AD27 -> 6566.4
B28: =B27+1 -> 17 | C28: AMERSAKI DANIEL | D28: 0247024779 | E28: 6 | O28: 2 | T28: 1 | AC28: =(E28*E46)+(F28*F46)+(G28*G46)+(H28*H46)+(I28*I46)+(J28*J46)+(K28*J46)+(L28*L46)+(M28*M46)+(N28*N46)+(O28*O46)+(P28*P46)+(Q28*Q46)+(R28*R46)+(S28*S46)+(T28*T46)+(U28*U46)+(V28*V46)+(W28*W46)+(X28*X46)+(Y28*Y46)+(Z28*Z46)+(AA28*AA46)+(AB28*AB46) -> 8432 | AD28: =10%*AC28 -> 843.2 | AE28: =AC28-AD28 -> 7588.8
B29: =B28+1 -> 18 | C29: GAREBA ISSAKA | D29: 0247029576 | G29: 10 | AC29: =(E29*E46)+(F29*F46)+(G29*G46)+(H29*H46)+(I29*I46)+(J29*J46)+(K29*K46)+(L29*L46)+(M29*M46)+(N29*N46)+(O29*O46)+(P29*P46)+(Q29*Q46)+(R29*R46)+(S29*S46)+(T29*T46)+(U29*U46)+(V29*V46)+(W29*W46)+(X29*X46)+(Y29*Y46)+(Z29*Z46)+(AA29*AA46)+(AB29*AB46) -> 1770 | AD29: =10%*AC29 -> 177 | AE29: =AC29-AD29 -> 1593
B30: =B29+1 -> 19 | C30: AFRIYIE JOSEPH | D30: 0542014600 | F30: 2 | AC30: =(E30*E46)+(F30*F46)+(G30*G46)+(H30*H46)+(I30*I46)+(J30*J46)+(K30*K46)+(L30*L46)+(M30*M46)+(N30*N46)+(O30*O46)+(P30*P46)+(Q30*Q46)+(R30*R46)+(S30*S46)+(T30*T46)+(U30*U46)+(V30*V46)+(W30*W46)+(X30*X46)+(Y30*Y46)+(Z30*Z46)+(AA30*AA46)+(AB30*AB46) -> 4896 | AD30: =10%*AC30 -> 489.6 | AE30: =AC30-AD30 -> 4406.4
B31: =B30+1 -> 20 | C31: SACKEY ABRAHAM | D31: 0246895262 | E31: 6 | K31: 8 | T31: 1 | AC31: =(E31*E46)+(F31*F46)+(G31*G46)+(H31*H46)+(I31*I46)+(J31*J46)+(K31*J46)+(L31*L46)+(M31*M46)+(N31*N46)+(O31*O46)+(P31*P46)+(Q31*Q46)+(R31*R46)+(S31*S46)+(T31*T46)+(U31*U46)+(V31*V46)+(W31*W46)+(X31*X46)+(Y31*Y46)+(Z31*Z46)+(AA31*AA46)+(AB31*AB46) -> 25016 | AD31: =10%*AC31 -> 2501.6 | AE31: =AC31-AD31 -> 22514.4
B32: =B31+1 -> 21 | AC32: =(E32*E46)+(F32*F46)+(G32*G46)+(H32*H46)+(I32*I46)+(J32*J46)+(K32*K46)+(L32*L46)+(M32*M46)+(N32*N46)+(O32*O46)+(P32*P46)+(Q32*Q46)+(R32*R46)+(S32*S46)+(T32*T46)+(U32*U46)+(V32*V46)+(W32*W46)+(X32*X46)+(Y32*Y46)+(Z32*Z46)+(AA32*AA46)+(AB32*AB46) -> 0 | AD32: =10%*AC32 -> 0 | AE32: =AC32-AD32 -> 0
B33: =B32+1 -> 22 | AC33: =(E33*E46)+(F33*F46)+(G33*G46)+(H33*H46)+(I33*I46)+(J33*J46)+(K33*K46)+(L33*L46)+(M33*M46)+(N33*N46)+(O33*O46)+(P33*P46)+(Q33*Q46)+(R33*R46)+(S33*S46)+(T33*T46)+(U33*U46)+(V33*V46)+(W33*W46)+(X33*X46)+(Y33*Y46)+(Z33*Z46)+(AA33*AA46)+(AB33*AB46) -> 0 | AD33: =10%*AC33 -> 0 | AE33: =AC33-AD33 -> 0 | AG33: =AE33/3 -> 0 | AH33: =AG33 -> 0 | AI33: =AH33 -> 0
B34: =B33+1 -> 23 | AC34: =(E34*E46)+(F34*F46)+(G34*G46)+(H34*H46)+(I34*I46)+(J34*J46)+(K34*J46)+(L34*L46)+(M34*M46)+(N34*N46)+(O34*O46)+(P34*P46)+(Q34*Q46)+(R34*R46)+(S34*S46)+(T34*T46)+(U34*U46)+(V34*V46)+(W34*W46)+(X34*X46)+(Y34*Y46)+(Z34*Z46)+(AA34*AA46)+(AB34*AB46) -> 0 | AD34: =10%*AC34 -> 0 | AE34: =AC34-AD34 -> 0 | AG34: =AE34/3 -> 0 | AH34: =AG34 -> 0 | AI34: =AH34 -> 0
B35: =B34+1 -> 24 | AC35: =(E35*E46)+(F35*F46)+(G35*G46)+(H35*H46)+(I35*I46)+(J35*J46)+(K35*K46)+(L35*L46)+(M35*M46)+(N35*N46)+(O35*O46)+(P35*P46)+(Q35*Q46)+(R35*R46)+(S35*S46)+(T35*T46)+(U35*U46)+(V35*V46)+(W35*W46)+(X35*X46)+(Y35*Y46)+(Z35*Z46)+(AA35*AA46)+(AB35*AB46) -> 0 | AD35: =10%*AC35 -> 0 | AE35: =AC35-AD35 -> 0 | AG35: =AE35/3 -> 0 | AH35: =AG35 -> 0 | AI35: =AH35 -> 0
B36: =B35+1 -> 25 | AC36: =(E36*E46)+(F36*F46)+(G36*G46)+(H36*H46)+(I36*I46)+(J36*J46)+(K36*K46)+(L36*L46)+(M36*M46)+(N36*N46)+(O36*O46)+(P36*P46)+(Q36*Q46)+(R36*R46)+(S36*S46)+(T36*T46)+(U36*U46)+(V36*V46)+(W36*W46)+(X36*X46)+(Y36*Y46)+(Z36*Z46)+(AA36*AA46)+(AB36*AB46) -> 0 | AD36: =10%*AC36 -> 0 | AE36: =AC36-AD36 -> 0 | AG36: =AE36/3 -> 0 | AH36: =AG36 -> 0 | AI36: =AH36 -> 0
B37: =B36+1 -> 26 | AC37: =(E37*E46)+(F37*F46)+(G37*G46)+(H37*H46)+(I37*I46)+(J37*J46)+(K37*J46)+(L37*L46)+(M37*M46)+(N37*N46)+(O37*O46)+(P37*P46)+(Q37*Q46)+(R37*R46)+(S37*S46)+(T37*T46)+(U37*U46)+(V37*V46)+(W37*W46)+(X37*X46)+(Y37*Y46)+(Z37*Z46)+(AA37*AA46)+(AB37*AB46) -> 0 | AD37: =10%*AC37 -> 0 | AE37: =AC37-AD37 -> 0 | AG37: =AE37/3 -> 0 | AH37: =AG37 -> 0 | AI37: =AH37 -> 0
B38: =B37+1 -> 27 | AC38: =(E38*E46)+(F38*F46)+(G38*G46)+(H38*H46)+(I38*I46)+(J38*J46)+(K38*K46)+(L38*L46)+(M38*M46)+(N38*N46)+(O38*O46)+(P38*P46)+(Q38*Q46)+(R38*R46)+(S38*S46)+(T38*T46)+(U38*U46)+(V38*V46)+(W38*W46)+(X38*X46)+(Y38*Y46)+(Z38*Z46)+(AA38*AA46)+(AB38*AB46) -> 0 | AD38: =10%*AC38 -> 0 | AE38: =AC38-AD38 -> 0 | AG38: =AE38/3 -> 0 | AH38: =AG38 -> 0 | AI38: =AH38 -> 0
B39: =B38+1 -> 28 | AC39: =(E39*E46)+(F39*F46)+(G39*G46)+(H39*H46)+(I39*I46)+(J39*J46)+(K39*K46)+(L39*L46)+(M39*M46)+(N39*N46)+(O39*O46)+(P39*P46)+(Q39*Q46)+(R39*R46)+(S39*S46)+(T39*T46)+(U39*U46)+(V39*V46)+(W39*W46)+(X39*X46)+(Y39*Y46)+(Z39*Z46)+(AA39*AA46)+(AB39*AB46) -> 0 | AD39: =10%*AC39 -> 0 | AE39: =AC39-AD39 -> 0 | AG39: =AE39/3 -> 0 | AH39: =AG39 -> 0 | AI39: =AH39 -> 0
B40: =B39+1 -> 29 | AC40: =(E40*E46)+(F40*F46)+(G40*G46)+(H40*H46)+(I40*I46)+(J40*J46)+(K40*J46)+(L40*L46)+(M40*M46)+(N40*N46)+(O40*O46)+(P40*P46)+(Q40*Q46)+(R40*R46)+(S40*S46)+(T40*T46)+(U40*U46)+(V40*V46)+(W40*W46)+(X40*X46)+(Y40*Y46)+(Z40*Z46)+(AA40*AA46)+(AB40*AB46) -> 0 | AD40: =10%*AC40 -> 0 | AE40: =AC40-AD40 -> 0 | AG40: =AE40/3 -> 0 | AH40: =AG40 -> 0 | AI40: =AH40 -> 0
B41: =B40+1 -> 30 | AC41: =(E41*E46)+(F41*F46)+(G41*G46)+(H41*H46)+(I41*I46)+(J41*J46)+(K41*K46)+(L41*L46)+(M41*M46)+(N41*N46)+(O41*O46)+(P41*P46)+(Q41*Q46)+(R41*R46)+(S41*S46)+(T41*T46)+(U41*U46)+(V41*V46)+(W41*W46)+(X41*X46)+(Y41*Y46)+(Z41*Z46)+(AA41*AA46)+(AB41*AB46) -> 0 | AD41: =10%*AC41 -> 0 | AE41: =AC41-AD41 -> 0 | AG41: =AE41/3 -> 0 | AH41: =AG41 -> 0 | AI41: =AH41 -> 0
B42: =B41+1 -> 31 | AC42: =(E42*E46)+(F42*F46)+(G42*G46)+(H42*H46)+(I42*I46)+(J42*J46)+(K42*K46)+(L42*L46)+(M42*M46)+(N42*N46)+(O42*O46)+(P42*P46)+(Q42*Q46)+(R42*R46)+(S42*S46)+(T42*T46)+(U42*U46)+(V42*V46)+(W42*W46)+(X42*X46)+(Y42*Y46)+(Z42*Z46)+(AA42*AA46)+(AB42*AB46) -> 0 | AD42: =10%*AC42 -> 0 | AE42: =AC42-AD42 -> 0 | AG42: =AE42/3 -> 0 | AH42: =AG42 -> 0 | AI42: =AH42 -> 0
B43: TOTAL | C43: =COUNTA(C12:C42) -> 20 | E43: =SUM(E12:E42) -> 18 | F43: =SUM(F12:F42) -> 9 | G43: =SUM(G12:G42) -> 107 | H43: =SUM(H12:H42) -> 0 | I43: =SUM(I12:I42) -> 4 | J43: =SUM(J12:J42) -> 2 | K43: =SUM(K12:K42) -> 16 | L43: =SUM(L12:L42) -> 0 | ... AE43: =SUM(AE12:AE42) -> 122283.9 | AG43: =SUM(AG12:AG42) -> 0 | AH43: =SUM(AH12:AH42) -> 0 | AI43: =SUM(AI12:AI42) -> 0 | AJ43: =SUM(AJ12:AJ42) -> 0 | AK43: =SUM(AK12:AK42) -> 0 | AL43: =SUM(AL12:AL42) -> 18294.3 | AM43: =SUM(AM12:AM42) -> 18294.3 | AN43: =SUM(AN12:AN42) -> 18294.3 | ... AP43: =SUM(AP12:AP42) -> 54882.9
C46: Price | E46: 204 | F46: =12*E46 -> 2448 | G46: 177 | H46: =G46*48 -> 8496 | I46: 177 | J46: =I46*12 -> 2124 | K46: 177 | L46: =K46*15 -> 2655 | M46: 34 | N46: =M46*6 -> 204 | O46: 204 | P46: =O46*4 -> 816 | Q46: 272 | R46: 204 | S46: =R46*4 -> 816 | T46: 6800 | U46: 75 | V46: =U46*12 -> 900 | W46: 13.6 | X46: 68 | Y46: =X46*12 -> 816 | Z46: 1904 | AA46: 122 | AB46: 340

Sheet BAAKOYE
C2: NOTE:
C3: 1. Enter the quantity of agro inputs requested by the farmer either in pcs or boxes under each agro input
C4: 2. Do not change any thing in the excel sheet. The cells are linked
C6: REGION:
C7: DISTRICT: | D7: BAAKOYE
C8: SOCIETY: | D8: KWAMEKROM KRAMOKROM
B10: NO. | C10: FARMER NAME | D10: MOBILE NO. | E10: AcetaStar -Adama (1Lt) | G10: Galil | I10: AKATE BRAFO | K10: PHYTOGREEN | M10: BEGREEN | O10: Agyenkwa Liquid Fertilizer (5Lt) | Q10: Matabi (15Lt) | R10: PLANTFEED | T10: Solo Machine | U10: All Wedicides (Glyphosate) | W10: NODOX | X10: ALL GRAMO | Z10: STANDARD PRUNNER | AA10: WELLINGTON BOOT | AB10: OVERALL | AC10: TOTAL AMOUNT (GHc) | AD10: DEPOSIT PAID (GHc) | AE10: OUTS. BALANCE (GHc) | AF10: REPAYMENT PLAN(GHC)
E11: PCs | F11: Box (12pcs) | G11: PCs | H11: Box | I11: PCs | J11: Box | K11: 1LT | L11: BOX(15) | M11: 1GALLON | N11: BOX(6) | O11: PCs | P11: Box(4) | Q11: PCs | R11: 1 GALLON | S11: BOX(4) | T11: PCs | U11: PCS | V11: BOX(12) | W11: PCs | X11: PCS | Y11: BOX(12) | Z11: PC | AA11: PC | AB11: PC | AF11: OCT | AG11: NOV | AH11: nov b | AL11: OCT | AM11: NOV | AN11: DEC | AO11: TOTAL PAYMENT | AP11: REMN
B12: =B11+1 -> 1 | C12: TETTEH CHISTIAN KOFI | D12: 0240557465 | E12: 6 | AC12: =(E12*E46)+(F12*F46)+(G12*G46)+(H12*H46)+(I12*I46)+(J12*J46)+(K12*K46)+(L12*L46)+(M12*M46)+(N12*N46)+(O12*O46)+(P12*P46)+(Q12*Q46)+(R12*R46)+(S12*S46)+(T12*T46)+(U12*U46)+(V12*V46)+(W12*W46)+(X12*X46)+(Y12*Y46)+(Z12*Z46)+(AA12*AA46)+(AB12*AB46) -> 1224 | AD12: =10%*AC12 -> 122.4 | AE12: =AC12-AD12 -> 1101.6 | AL12: =AE12/3 -> 367.2 | AM12: =AL12 -> 367.2 | AN12: =AM12 -> 367.2 | AO12: =AD12+AF12+AG12+AH12+AI12+AJ12+AK12 -> 122.4 | AP12: =AC12-AO12 -> 1101.6
B13: =B12+1 -> 2 | C13: BINFOR ISAAC | T13: 1 | AC13: =(E13*E46)+(F13*F46)+(G13*G46)+(H13*H46)+(I13*I46)+(J13*J46)+(K13*K46)+(L13*L46)+(M13*M46)+(N13*N46)+(O13*O46)+(P13*P46)+(Q13*Q46)+(R13*R46)+(S13*S46)+(T13*T46)+(U13*U46)+(V13*V46)+(W13*W46)+(X13*X46)+(Y13*Y46)+(Z13*Z46)+(AA13*AA46)+(AB13*AB46) -> 6800 | AD13: =10%*AC13 -> 680 | AE13: =AC13-AD13 -> 6120 | AL13: =AE13/3 -> 2040 | AM13: =AL13 -> 2040 | AN13: =AM13 -> 2040 | AO13: =AD13+AF13+AG13+AH13+AI13+AJ13+AK13 -> 680 | AP13: =AC13-AO13 -> 6120
B14: =B13+1 -> 3 | C14: TETTEH COMFORT | D14: 0548918819 | G14: 24 | T14: 1 | AC14: =(E14*E46)+(F14*F46)+(G14*G46)+(H14*H46)+(I14*I46)+(J14*J46)+(K14*K46)+(L14*L46)+(M14*M46)+(N14*N46)+(O14*O46)+(P14*P46)+(Q14*Q46)+(R14*R46)+(S14*S46)+(T14*T46)+(U14*U46)+(V14*V46)+(W14*W46)+(X14*X46)+(Y14*Y46)+(Z14*Z46)+(AA14*AA46)+(AB14*AB46) -> 11048 | AD14: =10%*AC14 -> 1104.8 | AE14: =AC14-AD14 -> 9943.2 | AL14: =AE14/3 -> 3314.4 | AM14: =AL14 -> 3314.4 | AN14: =AM14 -> 3314.4 | AO14: =AD14+AF14+AG14+AH14+AI14+AJ14+AK14 -> 1104.8 | AP14: =AC14-AO14 -> 9943.2
B15: =B14+1 -> 4 | C15: TETTEH AGNES | H15: 1 | AC15: =(E15*E46)+(F15*F46)+(G15*G46)+(H15*H46)+(I15*I46)+(J15*J46)+(K15*K46)+(L15*L46)+(M15*M46)+(N15*N46)+(O15*O46)+(P15*P46)+(Q15*Q46)+(R15*R46)+(S15*S46)+(T15*T46)+(U15*U46)+(V15*V46)+(W15*W46)+(X15*X46)+(Y15*Y46)+(Z15*Z46)+(AA15*AA46)+(AB15*AB46) -> 8496 | AD15: =10%*AC15 -> 849.6 | AE15: =AC15-AD15 -> 7646.4 | AL15: =AE15/3 -> 2548.8 | AM15: =AL15 -> 2548.8 | AN15: =AM15 -> 2548.8 | AO15: =AD15+AF15+AG15+AH15+AI15+AJ15+AK15 -> 849.6 | AP15: =AC15-AO15 -> 7646.4
B16: =B15+1 -> 5 | C16: BOAHEN SOLOMON | D16: 0548578638 | E16: 6 | G16: 6 | T16: 1 | AC16: =(E16*E46)+(F16*F46)+(G16*G46)+(H16*H46)+(I16*I46)+(J16*J46)+(K16*K46)+(L16*L46)+(M16*M46)+(N16*N46)+(O16*O46)+(P16*P46)+(Q16*Q46)+(R16*R46)+(S16*S46)+(T16*T46)+(U16*U46)+(V16*V46)+(W16*W46)+(X16*X46)+(Y16*Y46)+(Z16*Z46)+(AA16*AA46)+(AB16*AB46) -> 9086 | AD16: =10%*AC16 -> 908.6 | AE16: =AC16-AD16 -> 8177.4 | AL16: =AE16/3 -> 2725.8 | AM16: =AL16 -> 2725.8 | AN16: =AM16 -> 2725.8 | AO16: =AD16+AF16+AG16+AH16+AI16+AJ16+AK16 -> 908.6 | AP16: =AC16-AO16 -> 8177.4
B17: =B16+1 -> 6 | C17: KWAW REBECCA | D17: 0531890058 | T17: 1 | AC17: =(E17*E46)+(F17*F46)+(G17*G46)+(H17*H46)+(I17*I46)+(J17*J50)+(K17*K46)+(L17*L46)+(M17*M46)+(N17*N46)+(O17*O46)+(P17*P46)+(Q17*Q46)+(R17*R46)+(S17*S46)+(T17*T46)+(U17*U46)+(V17*V46)+(W17*W46)+(X17*X46)+(Y17*Y46)+(Z17*Z46)+(AA17*AA46)+(AB17*AB46) -> 6800 | AD17: =10%*AC17 -> 680 | AE17: =AC17-AD17 -> 6120 | AL17: =AE17/3 -> 2040 | AM17: =AL17 -> 2040 | AN17: =AM17 -> 2040 | AO17: =AD17+AF17+AG17+AH17+AI17+AJ17+AK17 -> 680 | AP17: =AC17-AO17 -> 6120
B18: =B17+1 -> 7 | C18: NKANSAH ABRAHAM | D18: 0551354413 | F18: 1 | AC18: =(E18*E46)+(F18*F46)+(G18*G46)+(H18*H46)+(I18*I46)+(J18*J46)+(K18*K46)+(L18*L46)+(M18*M46)+(N18*N46)+(O18*O46)+(P18*P46)+(Q18*Q46)+(R18*R46)+(S18*S46)+(T18*T46)+(U18*U46)+(V18*V46)+(W18*W46)+(X18*X46)+(Y18*Y46)+(Z18*Z46)+(AA18*AA46)+(AB18*AB46) -> 2448 | AD18: =10%*AC18 -> 244.8 | AE18: =AC18-AD18 -> 2203.2 | AL18: =AE18/3 -> 734.4 | AM18: =AL18 -> 734.4 | AN18: =AM18 -> 734.4 | AO18: =AD18+AF18+AG18+AH18+AI18+AJ18+AK18 -> 244.8 | AP18: =AC18-AO18 -> 2203.2
B19: =B18+1 -> 8 | C19: TETTEH JOSEPH | D19: 0557832685 | F19: 1 | AC19: =(E19*E46)+(F19*F46)+(G19*G46)+(H19*H46)+(I19*I46)+(J19*J46)+(K19*K46)+(L19*L46)+(M19*M46)+(N19*N46)+(O19*O46)+(P19*P46)+(Q19*Q46)+(R19*R46)+(S19*S46)+(T19*T46)+(U19*U46)+(V19*V46)+(W19*W46)+(X19*X46)+(Y19*Y46)+(Z19*Z46)+(AA19*AA46)+(AB19*AB46) -> 2448 | AD19: =10%*AC19 -> 244.8 | AE19: =AC19-AD19 -> 2203.2 | AL19: =AE19/3 -> 734.4 | AM19: =AL19 -> 734.4 | AN19: =AM19 -> 734.4 | AO19: =AD19+AF19+AG19+AH19+AI19+AJ19+AK19 -> 244.8 | AP19: =AC19-AO19 -> 2203.2
B20: =B19+1 -> 9 | C20: NARTEH GEORGE | D20: 0546206580 | T20: 1 | AC20: =(E20*E46)+(F20*F46)+(G20*G46)+(H20*H46)+(I20*I46)+(J20*J46)+(K20*K46)+(L20*L46)+(M20*M46)+(N20*N46)+(O20*O46)+(P20*P46)+(Q20*Q46)+(R20*R46)+(S20*S46)+(T20*T46)+(U20*U46)+(V20*V46)+(W20*W46)+(X20*X46)+(Y20*Y46)+(Z20*Z46)+(AA20*AA46)+(AB20*AB46) -> 6800 | AD20: =10%*AC20 -> 680 | AE20: =AC20-AD20 -> 6120 | AI20: =AH20 -> 0
B21: =B20+1 -> 10 | C21: NARTEY LYDIA | D21: 0546371668 | F21: 1 | AC21: =(E21*E46)+(F21*F46)+(G21*G46)+(H21*H46)+(I21*I46)+(J21*J46)+(K21*K46)+(L21*L46)+(M21*M46)+(N21*N46)+(O21*O46)+(P21*P46)+(Q21*Q46)+(R21*R46)+(S21*S46)+(T21*T46)+(U21*U46)+(V21*V46)+(W21*W46)+(X21*X46)+(Y21*Y46)+(Z21*Z46)+(AA21*AA46)+(AB21*AB46) -> 2448 | AD21: =10%*AC21 -> 244.8 | AE21: =AC21-AD21 -> 2203.2
B22: =B21+1 -> 11 | C22: TETTEH MARY | D22: 0240094471 | F22: 1 | T22: 1 | AC22: =(E22*E46)+(F22*F46)+(G22*G46)+(H22*H46)+(I22*I46)+(J22*J46)+(K22*K46)+(L22*L46)+(M22*M46)+(N22*N46)+(O22*O46)+(P22*P46)+(Q22*Q46)+(R22*R46)+(S22*S46)+(T22*T46)+(U22*U46)+(V22*V46)+(W22*W46)+(X22*X46)+(Y22*Y46)+(Z22*Z46)+(AA22*AA46)+(AB22*AB46) -> 9248 | AD22: =10%*AC22 -> 924.8 | AE22: =AC22-AD22 -> 8323.2
B23: =B22+1 -> 12 | C23: AKWETEY DIDSON | D23: 0551354413 | G23: 6 | T23: 1 | AC23: =(E23*E46)+(F23*F46)+(G23*G46)+(H23*H46)+(I23*I46)+(J23*J46)+(K23*K46)+(L23*L46)+(M23*M46)+(N23*N46)+(O23*O46)+(P23*P46)+(Q23*Q46)+(R23*R46)+(S23*S46)+(T23*T46)+(U23*U46)+(V23*V46)+(W23*W46)+(X23*X46)+(Y23*Y46)+(Z23*Z46)+(AA23*AA46)+(AB23*AB46) -> 7862 | AD23: =10%*AC23 -> 786.2 | AE23: =AC23-AD23 -> 7075.8
B24: =B23+1 -> 13 | C24: TETTEH FREDRICK | T24: 1 | AC24: =(E24*E46)+(F24*F46)+(G24*G46)+(H24*H46)+(I24*I46)+(J24*J46)+(K24*K46)+(L24*L46)+(M24*M46)+(N24*N46)+(O24*O46)+(P24*P46)+(Q24*Q46)+(R24*R46)+(S24*S46)+(T24*T46)+(U24*U46)+(V24*V46)+(W24*W46)+(X24*X46)+(Y24*Y46)+(Z24*Z46)+(AA24*AA46)+(AB24*AB46) -> 6800 | AD24: =10%*AC24 -> 680 | AE24: =AC24-AD24 -> 6120
B25: =B24+1 -> 14 | C25: SEGBEFIA BRIGHT NANA YAW | T25: 1 | AC25: =(E25*E46)+(F25*F46)+(G25*G46)+(H25*H46)+(I25*I46)+(J25*J46)+(K25*J46)+(L25*L46)+(M25*M46)+(N25*N46)+(O25*O46)+(P25*P46)+(Q25*Q46)+(R25*R46)+(S25*S46)+(T25*T46)+(U25*U46)+(V25*V46)+(W25*W46)+(X25*X46)+(Y25*Y46)+(Z25*Z46)+(AA25*AA46)+(AB25*AB46) -> 6800 | AD25: =10%*AC25 -> 680 | AE25: =AC25-AD25 -> 6120
B26: =B25+1 -> 15 | C26: BOAKYE RICHMOND ABU | T26: 1 | AC26: =(E26*E46)+(F26*F46)+(G26*G46)+(H26*H46)+(I26*I46)+(J26*J46)+(K26*K46)+(L26*L46)+(M26*M46)+(N26*N46)+(O26*O46)+(P26*P46)+(Q26*Q46)+(R26*R46)+(S26*S46)+(T26*T46)+(U26*U46)+(V26*V46)+(W26*W46)+(X26*X46)+(Y26*Y46)+(Z26*Z46)+(AA26*AA46)+(AB26*AB46) -> 6800 | AD26: =10%*AC26 -> 680 | AE26: =AC26-AD26 -> 6120
B27: =B26+1 -> 16 | AC27: =(E27*E46)+(F27*F46)+(G27*G46)+(H27*H46)+(I27*I46)+(J27*J46)+(K27*K46)+(L27*L46)+(M27*M46)+(N27*N46)+(O27*O46)+(P27*P46)+(Q27*Q46)+(R27*R46)+(S27*S46)+(T27*T46)+(U27*U46)+(V27*V46)+(W27*W46)+(X27*X46)+(Y27*Y46)+(Z27*Z46)+(AA27*AA46)+(AB27*AB46) -> 0 | AD27: =10%*AC27 -> 0 | AE27: =AC27-AD27 -> 0
B28: =B27+1 -> 17 | AC28: =(E28*E46)+(F28*F46)+(G28*G46)+(H28*H46)+(I28*I46)+(J28*J46)+(K28*J46)+(L28*L46)+(M28*M46)+(N28*N46)+(O28*O46)+(P28*P46)+(Q28*Q46)+(R28*R46)+(S28*S46)+(T28*T46)+(U28*U46)+(V28*V46)+(W28*W46)+(X28*X46)+(Y28*Y46)+(Z28*Z46)+(AA28*AA46)+(AB28*AB46) -> 0 | AD28: =10%*AC28 -> 0 | AE28: =AC28-AD28 -> 0 | AG28: =AE28/3 -> 0 | AH28: =AG28 -> 0 | AI28: =AH28 -> 0
B29: =B28+1 -> 18 | AC29: =(E29*E46)+(F29*F46)+(G29*G46)+(H29*H46)+(I29*I46)+(J29*J46)+(K29*K46)+(L29*L46)+(M29*M46)+(N29*N46)+(O29*O46)+(P29*P46)+(Q29*Q46)+(R29*R46)+(S29*S46)+(T29*T46)+(U29*U46)+(V29*V46)+(W29*W46)+(X29*X46)+(Y29*Y46)+(Z29*Z46)+(AA29*AA46)+(AB29*AB46) -> 0 | AD29: =10%*AC29 -> 0 | AE29: =AC29-AD29 -> 0 | AG29: =AE29/3 -> 0 | AH29: =AG29 -> 0 | AI29: =AH29 -> 0
B30: =B29+1 -> 19 | AC30: =(E30*E46)+(F30*F46)+(G30*G46)+(H30*H46)+(I30*I46)+(J30*J46)+(K30*K46)+(L30*L46)+(M30*M46)+(N30*N46)+(O30*O46)+(P30*P46)+(Q30*Q46)+(R30*R46)+(S30*S46)+(T30*T46)+(U30*U46)+(V30*V46)+(W30*W46)+(X30*X46)+(Y30*Y46)+(Z30*Z46)+(AA30*AA46)+(AB30*AB46) -> 0 | AD30: =10%*AC30 -> 0 | AE30: =AC30-AD30 -> 0 | AG30: =AE30/3 -> 0 | AH30: =AG30 -> 0 | AI30: =AH30 -> 0
B31: =B30+1 -> 20 | AC31: =(E31*E46)+(F31*F46)+(G31*G46)+(H31*H46)+(I31*I46)+(J31*J46)+(K31*J46)+(L31*L46)+(M31*M46)+(N31*N46)+(O31*O46)+(P31*P46)+(Q31*Q46)+(R31*R46)+(S31*S46)+(T31*T46)+(U31*U46)+(V31*V46)+(W31*W46)+(X31*X46)+(Y31*Y46)+(Z31*Z46)+(AA31*AA46)+(AB31*AB46) -> 0 | AD31: =10%*AC31 -> 0 | AE31: =AC31-AD31 -> 0 | AG31: =AE31/3 -> 0 | AH31: =AG31 -> 0 | AI31: =AH31 -> 0
B32: =B31+1 -> 21 | AG32: =AE32/3 -> 0 | AH32: =AG32 -> 0 | AI32: =AH32 -> 0
B33: =B32+1 -> 22 | AC33: =(E33*E46)+(F33*F46)+(G33*G46)+(H33*H46)+(I33*I46)+(J33*J46)+(K33*K46)+(L33*L46)+(M33*M46)+(N33*N46)+(O33*O46)+(P33*P46)+(Q33*Q46)+(R33*R46)+(S33*S46)+(T33*T46)+(U32*U46)+(V33*V46)+(W33*W46)+(X33*X46)+(Y33*Y46)+(Z33*Z46)+(AA33*AA46)+(AB33*AB46) -> 0 | AD33: =10%*AC33 -> 0 | AE33: =AC33-AD33 -> 0 | AG33: =AE33/3 -> 0 | AH33: =AG33 -> 0 | AI33: =AH33 -> 0
B34: =B33+1 -> 23 | AC34: =(E34*E46)+(F34*F46)+(G34*G46)+(H34*H46)+(I34*I46)+(J34*J46)+(K34*J46)+(L34*L46)+(M34*M46)+(N34*N46)+(O34*O46)+(P34*P46)+(Q34*Q46)+(R34*R46)+(S34*S46)+(T34*T46)+(U34*U46)+(V34*V46)+(W34*W46)+(X34*X46)+(Y34*Y46)+(Z34*Z46)+(AA34*AA46)+(AB34*AB46) -> 0 | AD34: =10%*AC34 -> 0 | AE34: =AC34-AD34 -> 0 | AG34: =AE34/3 -> 0 | AH34: =AG34 -> 0 | AI34: =AH34 -> 0
B35: =B34+1 -> 24 | AC35: =(E35*E46)+(F35*F46)+(G35*G46)+(H35*H46)+(I35*I46)+(J35*J46)+(K35*K46)+(L35*L46)+(M35*M46)+(N35*N46)+(O35*O46)+(P35*P46)+(Q35*Q46)+(R35*R46)+(S35*S46)+(T35*T46)+(U35*U46)+(V35*V46)+(W35*W46)+(X35*X46)+(Y35*Y46)+(Z35*Z46)+(AA35*AA46)+(AB35*AB46) -> 0 | AD35: =10%*AC35 -> 0 | AE35: =AC35-AD35 -> 0 | AG35: =AE35/3 -> 0 | AH35: =AG35 -> 0 | AI35: =AH35 -> 0
B36: =B35+1 -> 25 | AC36: =(E36*E46)+(F36*F46)+(G36*G46)+(H36*H46)+(I36*I46)+(J36*J46)+(K36*K46)+(L36*L46)+(M36*M46)+(N36*N46)+(O36*O46)+(P36*P46)+(Q36*Q46)+(R36*R46)+(S36*S46)+(T36*T46)+(U36*U46)+(V36*V46)+(W36*W46)+(X36*X46)+(Y36*Y46)+(Z36*Z46)+(AA36*AA46)+(AB36*AB46) -> 0 | AD36: =10%*AC36 -> 0 | AE36: =AC36-AD36 -> 0 | AG36: =AE36/3 -> 0 | AH36: =AG36 -> 0 | AI36: =AH36 -> 0
B37: =B36+1 -> 26 | AC37: =(E37*E46)+(F37*F46)+(G37*G46)+(H37*H46)+(I37*I46)+(J37*J46)+(K37*J46)+(L37*L46)+(M37*M46)+(N37*N46)+(O37*O46)+(P37*P46)+(Q37*Q46)+(R37*R46)+(S37*S46)+(T37*T46)+(U37*U46)+(V37*V46)+(W37*W46)+(X37*X46)+(Y37*Y46)+(Z37*Z46)+(AA37*AA46)+(AB37*AB46) -> 0 | AD37: =10%*AC37 -> 0 | AE37: =AC37-AD37 -> 0 | AG37: =AE37/3 -> 0 | AH37: =AG37 -> 0 | AI37: =AH37 -> 0
B38: =B37+1 -> 27 | AC38: =(E38*E46)+(F38*F46)+(G38*G46)+(H38*H46)+(I38*I46)+(J38*J46)+(K38*K46)+(L38*L46)+(M38*M46)+(N38*N46)+(O38*O46)+(P38*P46)+(Q38*Q46)+(R38*R46)+(S38*S46)+(T38*T46)+(U38*U46)+(V38*V46)+(W38*W46)+(X38*X46)+(Y38*Y46)+(Z38*Z46)+(AA38*AA46)+(AB38*AB46) -> 0 | AD38: =10%*AC38 -> 0 | AE38: =AC38-AD38 -> 0 | AG38: =AE38/3 -> 0 | AH38: =AG38 -> 0 | AI38: =AH38 -> 0
B39: =B38+1 -> 28 | AC39: =(E39*E46)+(F39*F46)+(G39*G46)+(H39*H46)+(I39*I46)+(J39*J46)+(K39*K46)+(L39*L46)+(M39*M46)+(N39*N46)+(O39*O46)+(P39*P46)+(Q39*Q46)+(R39*R46)+(S39*S46)+(T39*T46)+(U39*U46)+(V39*V46)+(W39*W46)+(X39*X46)+(Y39*Y46)+(Z39*Z46)+(AA39*AA46)+(AB39*AB46) -> 0 | AD39: =10%*AC39 -> 0 | AE39: =AC39-AD39 -> 0 | AG39: =AE39/3 -> 0 | AH39: =AG39 -> 0 | AI39: =AH39 -> 0
B40: =B39+1 -> 29 | AC40: =(E40*E46)+(F40*F46)+(G40*G46)+(H40*H46)+(I40*I46)+(J40*J46)+(K40*J46)+(L40*L46)+(M40*M46)+(N40*N46)+(O40*O46)+(P40*P46)+(Q40*Q46)+(R40*R46)+(S40*S46)+(T40*T46)+(U40*U46)+(V40*V46)+(W40*W46)+(X40*X46)+(Y40*Y46)+(Z40*Z46)+(AA40*AA46)+(AB40*AB46) -> 0 | AD40: =10%*AC40 -> 0 | AE40: =AC40-AD40 -> 0 | AG40: =AE40/3 -> 0 | AH40: =AG40 -> 0 | AI40: =AH40 -> 0
B41: =B40+1 -> 30 | AC41: =(E41*E46)+(F41*F46)+(G41*G46)+(H41*H46)+(I41*I46)+(J41*J46)+(K41*K46)+(L41*L46)+(M41*M46)+(N41*N46)+(O41*O46)+(P41*P46)+(Q41*Q46)+(R41*R46)+(S41*S46)+(T41*T46)+(U41*U46)+(V41*V46)+(W41*W46)+(X41*X46)+(Y41*Y46)+(Z41*Z46)+(AA41*AA46)+(AB41*AB46) -> 0 | AD41: =10%*AC41 -> 0 | AE41: =AC41-AD41 -> 0 | AG41: =AE41/3 -> 0 | AH41: =AG41 -> 0 | AI41: =AH41 -> 0
B42: =B41+1 -> 31 | AC42: =(E42*E46)+(F42*F46)+(G42*G46)+(H42*H46)+(I42*I46)+(J42*J46)+(K42*K46)+(L42*L46)+(M42*M46)+(N42*N46)+(O42*O46)+(P42*P46)+(Q42*Q46)+(R42*R46)+(S42*S46)+(T42*T46)+(U42*U46)+(V42*V46)+(W42*W46)+(X42*X46)+(Y42*Y46)+(Z42*Z46)+(AA42*AA46)+(AB42*AB46) -> 0 | AD42: =10%*AC42 -> 0 | AE42: =AC42-AD42 -> 0 | AG42: =AE42/3 -> 0 | AH42: =AG42 -> 0 | AI42: =AH42 -> 0
B43: TOTAL | C43: =COUNTA(C12:C42) -> 15 | E43: =SUM(E12:E42) -> 12 | F43: =SUM(F12:F42) -> 4 | G43: =SUM(G12:G42) -> 36 | H43: =SUM(H12:H42) -> 1 | I43: =SUM(I12:I42) -> 0 | J43: =SUM(J12:J42) -> 0 | K43: =SUM(K12:K42) -> 0 | L43: =SUM(L12:L42) -> 0 | ... AE43: =SUM(AE12:AE42) -> 85597.2 | AG43: =SUM(AG12:AG42) -> 0 | AH43: =SUM(AH12:AH42) -> 0 | AI43: =SUM(AI12:AI42) -> 0 | AJ43: =SUM(AJ12:AJ42) -> 0 | AK43: =SUM(AK12:AK42) -> 0 | AL43: =SUM(AL12:AL42) -> 14505 | AM43: =SUM(AM12:AM42) -> 14505 | AN43: =SUM(AN12:AN42) -> 14505 | ... AP43: =SUM(AP12:AP42) -> 43515
C46: Price | E46: 204 | F46: =12*E46 -> 2448 | G46: 177 | H46: =G46*48 -> 8496 | I46: 204 | J46: =I46*12 -> 2448 | K46: 177 | L46: =K46*15 -> 2655 | M46: 34 | N46: =M46*6 -> 204 | O46: 272 | P46: =O46*4 -> 1088 | Q46: 1496 | R46: 204 | S46: =R46*4 -> 816 | T46: 6800 | U46: 75 | V46: =U46*12 -> 900 | W46: 13.6 | X46: 68 | Y46: =X46*12 -> 816 | Z46: 1904 | AA46: 122 | AB46: 340

Sheet 0
C2: NOTE:
C3: 1. Enter the quantity of agro inputs requested by the farmer either in pcs or boxes under each agro input
C4: 2. Do not change any thing in the excel sheet. The cells are linked
C6: REGION: | D6: ASHANTI
C7: DISTRICT: | D7: obuasi
C8: SOCIETY: | AE8: ONWE
B10: NO. | C10: FARMER NAME | D10: MOBILE NO. | E10: AcetaStar -Adama (1Lt) | G10: Galil | I10: AKATE BRAFO | K10: PHYTOGREEN | M10: BEGREEN | O10: Agyenkwa Liquid Fertilizer (5Lt) | Q10: Matabi (15Lt) | R10: PLANTFEED | T10: Solo Machine | U10: All Wedicides (Glyphosate) | W10: NODOX | X10: ALL GRAMO | Z10: STANDARD PRUNNER | AA10: WELLINGTON BOOT | AB10: OVERALL | AC10: TOTAL AMOUNT (GHc) | AD10: DEPOSIT PAID (GHc) | AE10: OUTS. BALANCE (GHc) | AF10: REPAYMENT PLAN(GHC)
E11: PCs | F11: Box (12pcs) | G11: PCs | H11: Box | I11: PCs | J11: Box | K11: 1LT | L11: BOX(15) | M11: 1GALLON | N11: BOX(6) | O11: PCs | P11: Box(4) | Q11: PCs | R11: 1 GALLON | S11: BOX(4) | T11: PCs | U11: PCS | V11: BOX(12) | W11: PCs | X11: PCS | Y11: BOX(12) | Z11: PC | AA11: PC | AB11: PC | AF11: NOV | AG11: DEC | AL11: OCT | AM11: NOV | AN11: DEC | AO11: TOTAL PAYMENT
B12: =B11+1 -> 1 | AC12: =(E12*E46)+(F12*F46)+(G12*G46)+(H12*H46)+(I12*I46)+(J12*J46)+(K12*K46)+(L12*L46)+(M12*M46)+(N12*N46)+(O12*O46)+(P12*P46)+(Q12*Q46)+(R12*R46)+(S12*S46)+(T12*T46)+(U12*U46)+(V12*V46)+(W12*W46)+(X12*X46)+(Y12*Y46)+(Z12*Z46)+(AA12*AA46)+(AB12*AB46) -> 0 | AD12: =10%*AC12 -> 0 | AE12: =AC12-AD12 -> 0 | AL12: =AE12/3 -> 0 | AM12: =AL12 -> 0 | AN12: =AM12 -> 0 | AO12: =AD12+AF12+AG12+AH12+AI12+AJ12+AK12 -> 0
B13: =B12+1 -> 2 | AC13: =(E13*E46)+(F13*F46)+(G13*G46)+(H13*H46)+(I13*I46)+(J13*J46)+(K13*K46)+(L13*L46)+(M13*M46)+(N13*N46)+(O13*O46)+(P13*P46)+(Q13*Q46)+(R13*R46)+(S13*S46)+(T13*T46)+(U13*U46)+(V13*V46)+(W13*W46)+(X13*X46)+(Y13*Y46)+(Z13*Z46)+(AA13*AA46)+(AB13*AB46) -> 0 | AD13: =10%*AC13 -> 0 | AE13: =AC13-AD13 -> 0 | AL13: =AE13/3 -> 0 | AM13: =AL13 -> 0 | AN13: =AM13 -> 0 | AO13: =AD13+AF13+AG13+AH13+AI13+AJ13+AK13 -> 0
B14: =B13+1 -> 3 | AC14: =(E14*E46)+(F14*F46)+(G14*G46)+(H14*H46)+(I14*I46)+(J14*J46)+(K14*K46)+(L14*L46)+(M14*M46)+(N14*N46)+(O14*O46)+(P14*P46)+(Q14*Q46)+(R14*R46)+(S14*S46)+(T14*T46)+(U14*U46)+(V14*V46)+(W14*W46)+(X14*X46)+(Y14*Y46)+(Z14*Z46)+(AA14*AA46)+(AB14*AB46) -> 0 | AE14: =AC14-AD14 -> 0 | AL14: =AE14/3 -> 0 | AM14: =AL14 -> 0 | AN14: =AM14 -> 0 | AO14: =AD14+AF14+AG14+AH14+AI14+AJ14+AK14 -> 0
B15: =B14+1 -> 4 | AC15: =(E15*E46)+(F15*F46)+(G15*G46)+(H15*H46)+(I15*I46)+(J15*J46)+(K15*K46)+(L15*L46)+(M15*M46)+(N15*N46)+(O15*O46)+(P15*P46)+(Q15*Q46)+(R15*R46)+(S15*S46)+(T15*T46)+(U15*U46)+(V15*V46)+(W15*W46)+(X15*X46)+(Y15*Y46)+(Z15*Z46)+(AA15*AA46)+(AB15*AB46) -> 0 | AD15: =10%*AC15 -> 0 | AE15: =AC15-AD15 -> 0 | AL15: =AE15/3 -> 0 | AM15: =AL15 -> 0 | AN15: =AM15 -> 0 | AO15: =AD15+AF15+AG15+AH15+AI15+AJ15+AK15 -> 0
B16: =B15+1 -> 5 | AC16: =(E16*E46)+(F16*F46)+(G16*G46)+(H16*H46)+(I16*I46)+(J16*J46)+(K16*K46)+(L16*L46)+(M16*M46)+(N16*N46)+(O16*O46)+(P16*P46)+(Q16*Q46)+(R16*R46)+(S16*S46)+(T16*T46)+(U16*U46)+(V16*V46)+(W16*W46)+(X16*X46)+(Y16*Y46)+(Z16*Z46)+(AA16*AA46)+(AB16*AB46) -> 0 | AD16: =10%*AC16 -> 0 | AE16: =AC16-AD16 -> 0 | AL16: =AE16/3 -> 0 | AM16: =AL16 -> 0 | AN16: =AM16 -> 0 | AO16: =AD16+AF16+AG16+AH16+AI16+AJ16+AK16 -> 0
B17: =B16+1 -> 6 | AC17: =(E17*E46)+(F17*F46)+(G17*G46)+(H17*H46)+(I17*I46)+(J17*J50)+(K17*K46)+(L17*L46)+(M17*M46)+(N17*N46)+(O17*O46)+(P17*P46)+(Q17*Q46)+(R17*R46)+(S17*S46)+(T17*T46)+(U17*U46)+(V17*V46)+(W17*W46)+(X17*X46)+(Y17*Y46)+(Z17*Z46)+(AA17*AA46)+(AB17*AB46) -> 0 | AD17: =10%*AC17 -> 0 | AE17: =AC17-AD17 -> 0 | AL17: =AE17/3 -> 0 | AM17: =AL17 -> 0 | AN17: =AM17 -> 0 | AO17: =AD17+AF17+AG17+AH17+AI17+AJ17+AK17 -> 0
B18: =B17+1 -> 7 | AC18: =(E18*E46)+(F18*F46)+(G18*G46)+(H18*H46)+(I18*I46)+(J18*J46)+(K18*K46)+(L18*L46)+(M18*M46)+(N18*N46)+(O18*O46)+(P18*P46)+(Q18*Q46)+(R18*R46)+(S18*S46)+(T18*T46)+(U18*U46)+(V18*V46)+(W18*W46)+(X18*X46)+(Y18*Y46)+(Z18*Z46)+(AA18*AA46)+(AB18*AB46) -> 0 | AD18: =10%*AC18 -> 0 | AE18: =AC18-AO18 -> 0 | AL18: =AE18/3 -> 0 | AM18: =AL18 -> 0 | AN18: =AM18 -> 0 | AO18: =AD18+AF18+AG18+AH18+AI18+AJ18+AK18 -> 0
B19: =B18+1 -> 8 | AC19: =(E19*E46)+(F19*F46)+(G19*G46)+(H19*H46)+(I19*I46)+(J19*J46)+(K19*K46)+(L19*L46)+(M19*M46)+(N19*N46)+(O19*O46)+(P19*P46)+(Q19*Q46)+(R19*R46)+(S19*S46)+(T19*T46)+(U19*U46)+(V19*V46)+(W19*W46)+(X19*X46)+(Y19*Y46)+(Z19*Z46)+(AA19*AA46)+(AB19*AB46) -> 0 | AD19: =10%*AC19 -> 0 | AE19: =AC19-AD19 -> 0 | AL19: =AE19/3 -> 0 | AM19: =AL19 -> 0 | AN19: =AM19 -> 0 | AO19: =AD19+AF19+AG19+AH19+AI19+AJ19+AK19 -> 0
B20: =B19+1 -> 9 | AC20: =(E20*E46)+(F20*F46)+(G20*G46)+(H20*H46)+(I20*I46)+(J20*J46)+(K20*K46)+(L20*L46)+(M20*M46)+(N20*N46)+(O20*O46)+(P20*P46)+(Q20*Q46)+(R20*R46)+(S20*S46)+(T20*T46)+(U20*U46)+(V20*V46)+(W20*W46)+(X20*X46)+(Y20*Y46)+(Z20*Z46)+(AA20*AA46)+(AB20*AB46) -> 0 | AD20: =10%*AC20 -> 0 | AE20: =AC20-AD20 -> 0 | AL20: =AE20/3 -> 0 | AM20: =AL20 -> 0 | AN20: =AM20 -> 0 | AO20: =AD20+AF20+AG20+AH20+AI20+AJ20+AK20 -> 0
B21: =B20+1 -> 10 | AC21: =(E21*E46)+(F21*F46)+(G21*G46)+(H21*H46)+(I21*I46)+(J21*J46)+(K21*K46)+(L21*L46)+(M21*M46)+(N21*N46)+(O21*O46)+(P21*P46)+(Q21*Q46)+(R21*R46)+(S21*S46)+(T21*T46)+(U21*U46)+(V21*V46)+(W21*W46)+(X21*X46)+(Y21*Y46)+(Z21*Z46)+(AA21*AA46)+(AB21*AB46) -> 0 | AD21: =10%*AC21 -> 0 | AE21: =AC21-AD21 -> 0 | AL21: =AE21/3 -> 0 | AM21: =AL21 -> 0 | AN21: =AM21 -> 0
B22: =B21+1 -> 11 | AC22: =(E22*E46)+(F22*F46)+(G22*G46)+(H22*H46)+(I22*I46)+(J22*J46)+(K22*K46)+(L22*L46)+(M22*M46)+(N22*N46)+(O22*O46)+(P22*P46)+(Q22*Q46)+(R22*R46)+(S22*S46)+(T22*T46)+(U22*U46)+(V22*V46)+(W22*W46)+(X22*X46)+(Y22*Y46)+(Z22*Z46)+(AA22*AA46)+(AB22*AB46) -> 0 | AD22: =10%*AC22 -> 0 | AE22: =AC22-AD22 -> 0 | AL22: =AE22/3 -> 0 | AM22: =AL22 -> 0 | AN22: =AM22 -> 0
B23: =B22+1 -> 12 | AC23: =(E23*E46)+(F23*F46)+(G23*G46)+(H23*H46)+(I23*I46)+(J23*J46)+(K23*K46)+(L23*L46)+(M23*M46)+(N23*N46)+(O23*O46)+(P23*P46)+(Q23*Q46)+(R23*R46)+(S23*S46)+(T23*T46)+(U23*U46)+(V23*V46)+(W23*W46)+(X23*X46)+(Y23*Y46)+(Z23*Z46)+(AA23*AA46)+(AB23*AB46) -> 0 | AD23: =10%*AC23 -> 0 | AE23: =AC23-AD23 -> 0 | AL23: =AE23/3 -> 0 | AM23: =AL23 -> 0 | AN23: =AM23 -> 0
B24: =B23+1 -> 13 | AC24: =(E24*E46)+(F24*F46)+(G24*G46)+(H24*H46)+(I24*I46)+(J24*J46)+(K24*K46)+(L24*L46)+(M24*M46)+(N24*N46)+(O24*O46)+(P24*P46)+(Q24*Q46)+(R24*R46)+(S24*S46)+(T24*T46)+(U24*U46)+(V24*V46)+(W24*W46)+(X24*X46)+(Y24*Y46)+(Z24*Z46)+(AA24*AA46)+(AB24*AB46) -> 0 | AD24: =10%*AC24 -> 0 | AE24: =AC24-AD24 -> 0 | AL24: =AE24/3 -> 0 | AM24: =AL24 -> 0 | AN24: =AM24 -> 0
B25: =B24+1 -> 14 | AC25: =(E25*E46)+(F25*F46)+(G25*G46)+(H25*H46)+(I25*I46)+(J25*J46)+(K25*J46)+(L25*L46)+(M25*M46)+(N25*N46)+(O25*O46)+(P25*P46)+(Q25*Q46)+(R25*R46)+(S25*S46)+(T25*T46)+(U25*U46)+(V25*V46)+(W25*W46)+(X25*X46)+(Y25*Y46)+(Z25*Z46)+(AA25*AA46)+(AB25*AB46) -> 0 | AD25: =10%*AC25 -> 0 | AE25: =AC25-AD25 -> 0 | AL25: =AE25/3 -> 0 | AM25: =AL25 -> 0 | AN25: =AM25 -> 0
B26: =B25+1 -> 15 | AC26: =(E26*E46)+(F26*F46)+(G26*G46)+(H26*H46)+(I26*I46)+(J26*J46)+(K26*K46)+(L26*L46)+(M26*M46)+(N26*N46)+(O26*O46)+(P26*P46)+(Q26*Q46)+(R26*R46)+(S26*S46)+(T26*T46)+(U26*U46)+(V26*V46)+(W26*W46)+(X26*X46)+(Y26*Y46)+(Z26*Z46)+(AA26*AA46)+(AB26*AB46) -> 0 | AD26: =10%*AC26 -> 0 | AE26: =AC26-AD26 -> 0 | AL26: =AE26/3 -> 0 | AM26: =AL26 -> 0 | AN26: =AM26 -> 0
B27: =B26+1 -> 16 | AC27: =(E27*E46)+(F27*F46)+(G27*G46)+(H27*H46)+(I27*I46)+(J27*J46)+(K27*K46)+(L27*L46)+(M27*M46)+(N27*N46)+(O27*O46)+(P27*P46)+(Q27*Q46)+(R27*R46)+(S27*S46)+(T27*T46)+(U27*U46)+(V27*V46)+(W27*W46)+(X27*X46)+(Y27*Y46)+(Z27*Z46)+(AA27*AA46)+(AB27*AB46) -> 0 | AD27: =10%*AC27 -> 0 | AE27: =AC27-AD27 -> 0 | AL27: =AE27/3 -> 0 | AM27: =AL27 -> 0 | AN27: =AM27 -> 0
B28: =B27+1 -> 17 | AC28: =(E28*E46)+(F28*F46)+(G28*G46)+(H28*H46)+(I28*I46)+(J28*J46)+(K28*J46)+(L28*L46)+(M28*M46)+(N28*N46)+(O28*O46)+(P28*P46)+(Q28*Q46)+(R28*R46)+(S28*S46)+(T28*T46)+(U28*U46)+(V28*V46)+(W28*W46)+(X28*X46)+(Y28*Y46)+(Z28*Z46)+(AA28*AA46)+(AB28*AB46) -> 0 | AD28: =10%*AC28 -> 0 | AE28: =AC28-AD28 -> 0 | AL28: =AE28/3 -> 0 | AM28: =AL28 -> 0 | AN28: =AM28 -> 0
B29: =B28+1 -> 18 | AC29: =(E29*E46)+(F29*F46)+(G29*G46)+(H29*H46)+(I29*I46)+(J29*J46)+(K29*K46)+(L29*L46)+(M29*M46)+(N29*N46)+(O29*O46)+(P29*P46)+(Q29*Q46)+(R29*R46)+(S29*S46)+(T29*T46)+(U29*U46)+(V29*V46)+(W29*W46)+(X29*X46)+(Y29*Y46)+(Z29*Z46)+(AA29*AA46)+(AB29*AB46) -> 0 | AD29: =10%*AC29 -> 0 | AE29: =AC29-AD29 -> 0 | AL29: =AE29/3 -> 0 | AM29: =AL29 -> 0 | AN29: =AM29 -> 0
B30: =B29+1 -> 19 | AC30: =(E30*E46)+(F30*F46)+(G30*G46)+(H30*H46)+(I30*I46)+(J30*J46)+(K30*K46)+(L30*L46)+(M30*M46)+(N30*N46)+(O30*O46)+(P30*P46)+(Q30*Q46)+(R30*R46)+(S30*S46)+(T30*T46)+(U30*U46)+(V30*V46)+(W30*W46)+(X30*X46)+(Y30*Y46)+(Z30*Z46)+(AA30*AA46)+(AB30*AB46) -> 0 | AD30: =10%*AC30 -> 0 | AE30: =AC30-AD30 -> 0 | AL30: =AE30/3 -> 0 | AM30: =AL30 -> 0 | AN30: =AM30 -> 0
B31: =B30+1 -> 20 | AC31: =(E31*E46)+(F31*F46)+(G31*G46)+(H31*H46)+(I31*I46)+(J31*J46)+(K31*J46)+(L31*L46)+(M31*M46)+(N31*N46)+(O31*O46)+(P31*P46)+(Q31*Q46)+(R31*R46)+(S31*S46)+(T31*T46)+(U31*U46)+(V31*V46)+(W31*W46)+(X31*X46)+(Y31*Y46)+(Z31*Z46)+(AA31*AA46)+(AB31*AB46) -> 0 | AD31: =10%*AC31 -> 0 | AE31: =AC31-AD31 -> 0 | AL31: =AE31/3 -> 0 | AM31: =AL31 -> 0 | AN31: =AM31 -> 0
B32: =B31+1 -> 21 | AC32: =(E32*E46)+(F32*F46)+(G32*G46)+(H32*H46)+(I32*I46)+(J32*J46)+(K32*K46)+(L32*L46)+(M32*M46)+(N32*N46)+(O32*O46)+(P32*P46)+(Q32*Q46)+(R32*R46)+(S32*S46)+(T32*T46)+(U32*U46)+(V32*V46)+(W32*W46)+(X32*X46)+(Y32*Y46)+(Z32*Z46)+(AA32*AA46)+(AB32*AB46) -> 0 | AD32: =10%*AC32 -> 0 | AE32: =AC32-AD32 -> 0 | AL32: =AE32/3 -> 0 | AM32: =AL32 -> 0 | AN32: =AM32 -> 0
B33: =B32+1 -> 22 | AC33: =(E33*E46)+(F33*F46)+(G33*G46)+(H33*H46)+(I33*I46)+(J33*J46)+(K33*K46)+(L33*L46)+(M33*M46)+(N33*N46)+(O33*O46)+(P33*P46)+(Q33*Q46)+(R33*R46)+(S33*S46)+(T33*T46)+(U33*U46)+(V33*V46)+(W33*W46)+(X33*X46)+(Y33*Y46)+(Z33*Z46)+(AA33*AA46)+(AB33*AB46) -> 0 | AD33: =10%*AC33 -> 0 | AE33: =AC33-AD33 -> 0 | AL33: =AE33/3 -> 0 | AM33: =AL33 -> 0 | AN33: =AM33 -> 0
B34: =B33+1 -> 23 | AC34: =(E34*E46)+(F34*F46)+(G34*G46)+(H34*H46)+(I34*I46)+(J34*J46)+(K34*J46)+(L34*L46)+(M34*M46)+(N34*N46)+(O34*O46)+(P34*P46)+(Q34*Q46)+(R34*R46)+(S34*S46)+(T34*T46)+(U34*U46)+(V34*V46)+(W34*W46)+(X34*X46)+(Y34*Y46)+(Z34*Z46)+(AA34*AA46)+(AB34*AB46) -> 0 | AD34: =10%*AC34 -> 0 | AE34: =AC34-AD34 -> 0 | AL34: =AE34/3 -> 0 | AM34: =AL34 -> 0 | AN34: =AM34 -> 0
B35: =B34+1 -> 24 | AC35: =(E35*E46)+(F35*F46)+(G35*G46)+(H35*H46)+(I35*I46)+(J35*J46)+(K35*K46)+(L35*L46)+(M35*M46)+(N35*N46)+(O35*O46)+(P35*P46)+(Q35*Q46)+(R35*R46)+(S35*S46)+(T35*T46)+(U35*U46)+(V35*V46)+(W35*W46)+(X35*X46)+(Y35*Y46)+(Z35*Z46)+(AA35*AA46)+(AB35*AB46) -> 0 | AD35: =10%*AC35 -> 0 | AE35: =AC35-AD35 -> 0 | AL35: =AE35/3 -> 0 | AM35: =AL35 -> 0 | AN35: =AM35 -> 0
B36: =B35+1 -> 25 | AC36: =(E36*E46)+(F36*F46)+(G36*G46)+(H36*H46)+(I36*I46)+(J36*J46)+(K36*K46)+(L36*L46)+(M36*M46)+(N36*N46)+(O36*O46)+(P36*P46)+(Q36*Q46)+(R36*R46)+(S36*S46)+(T36*T46)+(U36*U46)+(V36*V46)+(W36*W46)+(X36*X46)+(Y36*Y46)+(Z36*Z46)+(AA36*AA46)+(AB36*AB46) -> 0 | AD36: =10%*AC36 -> 0 | AE36: =AC36-AD36 -> 0 | AL36: =AE36/3 -> 0 | AM36: =AL36 -> 0 | AN36: =AM36 -> 0
B37: =B36+1 -> 26 | AC37: =(E37*E46)+(F37*F46)+(G37*G46)+(H37*H46)+(I37*I46)+(J37*J46)+(K37*J46)+(L37*L46)+(M37*M46)+(N37*N46)+(O37*O46)+(P37*P46)+(Q37*Q46)+(R37*R46)+(S37*S46)+(T37*T46)+(U37*U46)+(V37*V46)+(W37*W46)+(X37*X46)+(Y37*Y46)+(Z37*Z46)+(AA37*AA46)+(AB37*AB46) -> 0 | AD37: =10%*AC37 -> 0 | AE37: =AC37-AD37 -> 0 | AL37: =AE37/3 -> 0 | AM37: =AL37 -> 0 | AN37: =AM37 -> 0
B38: =B37+1 -> 27 | AC38: =(E38*E46)+(F38*F46)+(G38*G46)+(H38*H46)+(I38*I46)+(J38*J46)+(K38*K46)+(L38*L46)+(M38*M46)+(N38*N46)+(O38*O46)+(P38*P46)+(Q38*Q46)+(R38*R46)+(S38*S46)+(T38*T46)+(U38*U46)+(V38*V46)+(W38*W46)+(X38*X46)+(Y38*Y46)+(Z38*Z46)+(AA38*AA46)+(AB38*AB46) -> 0 | AD38: =10%*AC38 -> 0 | AE38: =AC38-AD38 -> 0 | AL38: =AE38/3 -> 0 | AM38: =AL38 -> 0 | AN38: =AM38 -> 0
B39: =B38+1 -> 28 | AC39: =(E39*E46)+(F39*F46)+(G39*G46)+(H39*H46)+(I39*I46)+(J39*J46)+(K39*K46)+(L39*L46)+(M39*M46)+(N39*N46)+(O39*O46)+(P39*P46)+(Q39*Q46)+(R39*R46)+(S39*S46)+(T39*T46)+(U39*U46)+(V39*V46)+(W39*W46)+(X39*X46)+(Y39*Y46)+(Z39*Z46)+(AA39*AA46)+(AB39*AB46) -> 0 | AD39: =10%*AC39 -> 0 | AE39: =AC39-AD39 -> 0 | AL39: =AE39/3 -> 0 | AM39: =AL39 -> 0 | AN39: =AM39 -> 0
B40: =B39+1 -> 29 | AC40: =(E40*E46)+(F40*F46)+(G40*G46)+(H40*H46)+(I40*I46)+(J40*J46)+(K40*J46)+(L40*L46)+(M40*M46)+(N40*N46)+(O40*O46)+(P40*P46)+(Q40*Q46)+(R40*R46)+(S40*S46)+(T40*T46)+(U40*U46)+(V40*V46)+(W40*W46)+(X40*X46)+(Y40*Y46)+(Z40*Z46)+(AA40*AA46)+(AB40*AB46) -> 0 | AD40: =10%*AC40 -> 0 | AE40: =AC40-AD40 -> 0 | AL40: =AE40/3 -> 0 | AM40: =AL40 -> 0 | AN40: =AM40 -> 0
B41: =B40+1 -> 30 | AC41: =(E41*E46)+(F41*F46)+(G41*G46)+(H41*H46)+(I41*I46)+(J41*J46)+(K41*K46)+(L41*L46)+(M41*M46)+(N41*N46)+(O41*O46)+(P41*P46)+(Q41*Q46)+(R41*R46)+(S41*S46)+(T41*T46)+(U41*U46)+(V41*V46)+(W41*W46)+(X41*X46)+(Y41*Y46)+(Z41*Z46)+(AA41*AA46)+(AB41*AB46) -> 0 | AD41: =10%*AC41 -> 0 | AE41: =AC41-AD41 -> 0 | AL41: =AE41/3 -> 0 | AM41: =AL41 -> 0 | AN41: =AM41 -> 0
B42: =B41+1 -> 31 | AC42: =(E42*E46)+(F42*F46)+(G42*G46)+(H42*H46)+(I42*I46)+(J42*J46)+(K42*K46)+(L42*L46)+(M42*M46)+(N42*N46)+(O42*O46)+(P42*P46)+(Q42*Q46)+(R42*R46)+(S42*S46)+(T42*T46)+(U42*U46)+(V42*V46)+(W42*W46)+(X42*X46)+(Y42*Y46)+(Z42*Z46)+(AA42*AA46)+(AB42*AB46) -> 0 | AD42: =10%*AC42 -> 0 | AE42: =AC42-AD42 -> 0 | AL42: =AE42/3 -> 0 | AM42: =AL42 -> 0 | AN42: =AM42 -> 0
B43: TOTAL | C43: =COUNTA(C12:C42) -> 0 | E43: =SUM(E12:E42) -> 0 | F43: =SUM(F12:F42) -> 0 | G43: =SUM(G12:G42) -> 0 | H43: =SUM(H12:H42) -> 0 | I43: =SUM(I12:I42) -> 0 | J43: =SUM(J12:J42) -> 0 | K43: =SUM(K12:K42) -> 0 | L43: =SUM(L12:L42) -> 0 | ... AE43: =SUM(AE12:AE42) -> 0 | AL43: =SUM(AL12:AL42) -> 0 | AM43: =SUM(AM12:AM42) -> 0 | AN43: =SUM(AN12:AN42) -> 0 | AO43: =SUM(AO12:AO42) -> 0
C46: Price | E46: 204 | F46: =12*E46 -> 2448 | G46: 177 | H46: =G46*48 -> 8496 | I46: 204 | J46: =I46*12 -> 2448 | K46: 177 | L46: =K46*15 -> 2655 | M46: 116 | N46: =M46*6 -> 696 | O46: 272 | P46: =O46*4 -> 1088 | Q46: 1496 | R46: 272 | S46: =R46*4 -> 1088 | T46: 6800 | U46: 75 | V46: =U46*12 -> 900 | W46: 20 | X46: 68 | Y46: =X46*12 -> 816 | Z46: 1904 | AA46: 122 | AB46: 340

Sheet YAWOWUSUKROM
C2: NOTE:
C3: 1. Enter the quantity of agro inputs requested by the farmer either in pcs or boxes under each agro input
C4: 2. Do not change any thing in the excel sheet. The cells are linked
K5: NEW PRICES
C6: REGION: | D6: ASHANTI
C7: DISTRICT: | D7: TEPA
C8: SOCIETY: | D8: ODO NA EFE,NYAME AKWAN,MPIRENKYE
B10: NO. | C10: FARMER NAME | D10: MOBILE NO. | E10: AcetaStar -Adama (1Lt) | G10: Galil | I10: AKATE BRAFO | K10: PHYTOGREEN | M10: BEGREEN | O10: Agyenkwa Liquid Fertilizer (5Lt) | Q10: Matabi (15Lt) | R10: PLANTFEED | T10: Solo Machine | U10: All Wedicides (Glyphosate) | W10: NODOX | X10: ALL GRAMO | Z10: STANDARD PRUNNER | AA10: WELLINGTON BOOT | AB10: OVERALL | AC10: TOTAL AMOUNT (GHc) | AD10: DEPOSIT PAID (GHc) | AE10: OUTS. BALANCE (GHc) | AF10: REPAYMENT PLAN(GHC)
E11: PCs | F11: Box (12pcs) | G11: PCs | H11: Box | I11: PCs | J11: Box | K11: 1LT | L11: BOX(15) | M11: 1GALLON | N11: BOX(6) | O11: PCs | P11: Box(4) | Q11: PCs | R11: 1 GALLON | S11: BOX(4) | T11: PCs | U11: PCS | V11: BOX(12) | W11: PCs | X11: PCS | Y11: BOX(12) | Z11: PC | AA11: PC | AB11: PC | AF11: OCT | AG11: NOV | AH11: NOV | AL11: OCT | AM11: NOV | AN11: DEC | AO11: TOTAL PAYMENT | AP11: REMN
B12: 1 | C12: AGYEI PRINCE | D12: 0533979381 | F12: 1 | AC12: =(E12*E42)+(F12*F42)+(G12*G42)+(H12*H42)+(I12*I42)+(J12*J42)+(K12*K42)+(L12*L42)+(M12*M42)+(N12*N42)+(O12*O42)+(P12*P42)+(Q12*Q42)+(R12*R42)+(S12*S42)+(T12*T42)+(U12*U42)+(V12*V42)+(W12*W42)+(X12*X42)+(Y12*Y42)+(Z12*Z42)+(AA12*AA42)+(AB12*AB42) -> 2448 | AD12: =10%*AC12 -> 244.8 | AE12: =AC12-AD12 -> 2203.2 | AF12: 1000 | AL12: =AE12/3 -> 734.4 | AM12: =AL12 -> 734.4 | AN12: =AM12 -> 734.4 | AO12: =AD12+AF12+AG12+AH12+AI12+AJ12+AK12 -> 1244.8 | AP12: =AC12-AO12 -> 1203.2
B13: =B12+1 -> 2 | C13: GANU KWEKU | D13: 0548871853 | E13: 2 | G13: 3 | P13: 2 | AC13: =(E13*E42)+(F13*F42)+(G13*G42)+(H13*H42)+(I13*I42)+(J13*J46)+(K13*K42)+(L13*L42)+(M13*M42)+(N13*N42)+(O13*O42)+(P13*P42)+(Q13*Q42)+(R13*R42)+(S13*S42)+(T13*T42)+(U13*U42)+(V13*V42)+(W13*W42)+(X13*X42)+(Y13*Y42)+(Z13*Z42)+(AA13*AA42)+(AB13*AB42) -> 3115 | AD13: =10%*AC13 -> 311.5 | AE13: =AC13-AD13 -> 2803.5 | AF13: 1000 | AL13: =AE13/3 -> 934.5 | AM13: =AL13 -> 934.5 | AN13: =AM13 -> 934.5 | AO13: =AD13+AF13+AG13+AH13+AI13+AJ13+AK13 -> 1311.5 | AP13: =AC13-AO13 -> 1803.5
B14: =B13+1 -> 3 | C14: BRUKU YAW | D14: 0544296626 | F14: 1 | AC14: =(E14*E42)+(F14*F42)+(G14*G42)+(H14*H42)+(I14*I42)+(J14*J42)+(K14*K42)+(L14*L42)+(M14*M42)+(N14*N42)+(O14*O42)+(P14*P42)+(Q14*Q42)+(R14*R42)+(S14*S42)+(T14*T42)+(U14*U42)+(V14*V42)+(W14*W42)+(X14*X42)+(Y14*Y42)+(Z14*Z42)+(AA14*AA42)+(AB14*AB42) -> 2448 | AD14: =10%*AC14 -> 244.8 | AE14: =AC14-AD14 -> 2203.2 | AF14: 1000 | AL14: =AE14/3 -> 734.4 | AM14: =AL14 -> 734.4 | AN14: =AM14 -> 734.4 | AO14: =AD14+AF14+AG14+AH14+AI14+AJ14+AK14 -> 1244.8 | AP14: =AC14-AO14 -> 1203.2
B15: =B14+1 -> 4 | C15: OPOKU NAOMI | D15: 0543346777 | G15: 2 | X15: 2 | AC15: =(E15*E42)+(F15*F42)+(G15*G42)+(H15*H42)+(I15*I42)+(J15*J42)+(K15*K42)+(L15*L42)+(M15*M42)+(N15*N42)+(O15*O42)+(P15*P42)+(Q15*Q42)+(R15*R42)+(S15*S42)+(T15*T42)+(U15*U42)+(V15*V42)+(W15*W42)+(X15*X42)+(Y15*Y42)+(Z15*Z42)+(AA15*AA42)+(AB15*AB42) -> 490 | AD15: =10%*AC15 -> 49 | AE15: =AC15-AD15 -> 441 | AL15: =AE15/3 -> 147 | AM15: =AL15 -> 147 | AN15: =AM15 -> 147 | AO15: =AD15+AF15+AG15+AH15+AI15+AJ15+AK15 -> 49 | AP15: =AC15-AO15 -> 441
B16: =B15+1 -> 5 | C16: ADDAI FRANCIS | D16: 0542995158 | E16: 2 | G16: 3 | T16: 1 | AC16: =(E16*E42)+(F16*F42)+(G16*G42)+(H16*H42)+(I16*I42)+(J16*J42)+(K16*K42)+(L16*L42)+(M16*M42)+(N16*N42)+(O16*O42)+(P16*P42)+(Q16*Q42)+(R16*R42)+(S16*S42)+(T16*T42)+(U16*U42)+(V16*V42)+(W16*W42)+(X16*X42)+(Y16*Y42)+(Z16*Z42)+(AA16*AA42)+(AB16*AB42) -> 7739 | AD16: =10%*AC16 -> 773.9 | AE16: =AC16-AD16 -> 6965.1 | AF16: 1000 | AL16: =AE16/3 -> 2321.7 | AM16: =AL16 -> 2321.7 | AN16: =AM16 -> 2321.7 | AO16: =AD16+AF16+AG16+AH16+AI16+AJ16+AK16 -> 1773.9
B17: =B16+1 -> 6 | C17: OPOKU BENJAMIN | T17: 1 | AC17: =(E17*E42)+(F17*F42)+(G17*G42)+(H17*H42)+(I17*I42)+(J17*J42)+(K17*K42)+(L17*L42)+(M17*M42)+(N17*N42)+(O17*O42)+(P17*P42)+(Q17*Q42)+(R17*R42)+(S17*S42)+(T17*T42)+(U17*U42)+(V17*V42)+(W17*W42)+(X17*X42)+(Y17*Y42)+(Z17*Z42)+(AA17*AA42)+(AB17*AB42) -> 6800 | AD17: =10%*AC17 -> 680 | AE17: =AC17-AD17 -> 6120 | AF17: 3000 | AL17: =AE17/3 -> 2040 | AM17: =AL17 -> 2040 | AN17: =AM17 -> 2040
B18: =B17+1 -> 7 | C18: AMANKWAANOR KWAME | D18: 0545774137 | T18: 1 | AC18: =(E18*E42)+(F18*F42)+(G18*G42)+(H18*H42)+(I18*I42)+(J18*J42)+(K18*K42)+(L18*L42)+(M18*M42)+(N18*N42)+(O18*O42)+(P18*P42)+(Q18*Q42)+(R18*R42)+(S18*S42)+(T18*T42)+(U18*U42)+(V18*V42)+(W18*W42)+(X18*X42)+(Y18*Y42)+(Z18*Z42)+(AA18*AA42)+(AB18*AB42) -> 6800 | AD18: =10%*AC18 -> 680 | AE18: =AC18-AD18 -> 6120 | AL18: =AE18/3 -> 2040 | AM18: =AL18 -> 2040 | AN18: =AM18 -> 2040
B19: =B18+1 -> 8 | C19: NKRUMAH GEORGE | D19: 0256718824 | T19: 1 | AC19: =(E19*E42)+(F19*F42)+(G19*G42)+(H19*H42)+(I19*I42)+(J19*J42)+(K19*K42)+(L19*L42)+(M19*M42)+(N19*N42)+(O19*O42)+(P19*P42)+(Q19*Q42)+(R19*R42)+(S19*S42)+(T19*T42)+(U19*U42)+(V19*V42)+(W19*W42)+(X19*X42)+(Y19*Y42)+(Z19*Z42)+(AA19*AA42)+(AB19*AB42) -> 6800 | AD19: =10%*AC19 -> 680 | AE19: =AC19-AD19 -> 6120 | AL19: =AE19/3 -> 2040 | AM19: =AL19 -> 2040 | AN19: =AM19 -> 2040
B20: =B19+1 -> 9 | C20: AKPABLA OLIVIA | D20: 0242747263 | T20: 1 | Z20: 1 | AC20: =(E20*E42)+(F20*F42)+(G20*G42)+(H20*H42)+(I20*I42)+(J20*J42)+(K20*K42)+(L20*L42)+(M20*M42)+(N20*N42)+(O20*O42)+(P20*P42)+(Q20*Q42)+(R20*R42)+(S20*S42)+(T20*T42)+(U20*U42)+(V20*V42)+(W20*W42)+(X20*X42)+(Y20*Y42)+(Z20*Z42)+(AA20*AA42)+(AB20*AB42) -> 8704 | AD20: =10%*AC20 -> 870.4 | AE20: =AC20-AD20 -> 7833.6 | AL20: =AE20/3 -> 2611.2 | AM20: =AL20 -> 2611.2 | AN20: =AM20 -> 2611.2
B21: =B20+1 -> 10 | C21: MANU ESTHER | T21: 1 | AC21: =(E21*E42)+(F21*F42)+(G21*G42)+(H21*H42)+(I21*I42)+(J21*J42)+(K21*J42)+(L21*L42)+(M21*M42)+(N21*N42)+(O21*O42)+(P21*P42)+(Q21*Q42)+(R21*R42)+(S21*S42)+(T21*T42)+(U21*U42)+(V21*V42)+(W21*W42)+(X21*X42)+(Y21*Y42)+(Z21*Z42)+(AA21*AA42)+(AB21*AB42) -> 6800 | AD21: =10%*AC21 -> 680 | AE21: =AC21-AD21 -> 6120 | AL21: =AE21/3 -> 2040 | AM21: =AL21 -> 2040 | AN21: =AM21 -> 2040
B22: =B21+1 -> 11 | C22: OFFEI RICHARD | D22: 0248525154 | T22: 1 | AC22: =(E22*E42)+(F22*F42)+(G22*G42)+(H22*H42)+(I22*I42)+(J22*J42)+(K22*K42)+(L22*L42)+(M22*M42)+(N22*N42)+(O22*O42)+(P22*P42)+(Q22*Q42)+(R22*R42)+(S22*S42)+(T22*T42)+(U22*U42)+(V22*V42)+(W22*W42)+(X22*X42)+(Y22*Y42)+(Z22*Z42)+(AA22*AA42)+(AB22*AB42) -> 6800 | AD22: =10%*AC22 -> 680 | AE22: =AC22-AD22 -> 6120 | AL22: =AE22/3 -> 2040 | AM22: =AL22 -> 2040 | AN22: =AM22 -> 2040
B23: =B22+1 -> 12 | C23: SEGBEFIA BRIGHT NANA YAW | D23: 0559019318 | T23: 1 | AC23: =(E23*E42)+(F23*F42)+(G23*G42)+(H23*H42)+(I23*I42)+(J23*J42)+(K23*K42)+(L23*L42)+(M23*M42)+(N23*N42)+(O23*O42)+(P23*P42)+(Q23*Q42)+(R23*R42)+(S23*S42)+(T23*T42)+(U23*U42)+(V23*V42)+(W23*W42)+(X23*X42)+(Y23*Y42)+(Z23*Z42)+(AA23*AA42)+(AB23*AB42) -> 6800 | AD23: =10%*AC23 -> 680 | AE23: =AC23-AD23 -> 6120 | AL23: =AE23/3 -> 2040 | AM23: =AL23 -> 2040 | AN23: =AM23 -> 2040
B24: =B23+1 -> 13 | C24: BOAKYE RICHMOND ADU | D24: 0240622624 | T24: 1 | AC24: =(E24*E42)+(F24*F42)+(G24*G42)+(H24*H42)+(I24*I42)+(J24*J42)+(K24*J42)+(L24*L42)+(M24*M42)+(N24*N42)+(O24*O42)+(P24*P42)+(Q24*Q42)+(R24*R42)+(S24*S42)+(T24*T42)+(U24*U42)+(V24*V42)+(W24*W42)+(X24*X42)+(Y24*Y42)+(Z24*Z42)+(AA24*AA42)+(AB24*AB42) -> 6800 | AD24: =10%*AC24 -> 680 | AE24: =AC24-AD24 -> 6120 | AL24: =AE24/3 -> 2040 | AM24: =AL24 -> 2040 | AN24: =AM24 -> 2040
B25: =B24+1 -> 14 | C25: TETTEH FREDRICK | D25: 0241587170 | T25: 1 | AC25: =(E25*E42)+(F25*F42)+(G25*G42)+(H25*H42)+(I25*I42)+(J25*J42)+(K25*K42)+(L25*L42)+(M25*M42)+(N25*N42)+(O25*O42)+(P25*P42)+(Q25*Q42)+(R25*R42)+(S25*S42)+(T25*T42)+(U25*U42)+(V25*V42)+(W25*W42)+(X25*X42)+(Y25*Y42)+(Z25*Z42)+(AA25*AA42)+(AB25*AB42) -> 6800 | AD25: =10%*AC25 -> 680 | AE25: =AC25-AD25 -> 6120 | AL25: =AE25/3 -> 2040 | AM25: =AL25 -> 2040 | AN25: =AM25 -> 2040
B26: =B25+1 -> 15 | C26: ATEMO SETH | D26: 0530392644 | T26: 1 | AC26: =(E26*E42)+(F26*F42)+(G26*G42)+(H26*H42)+(I26*I42)+(J26*J42)+(K26*K42)+(L26*L42)+(M26*M42)+(N26*N42)+(O26*O42)+(P26*P42)+(Q26*Q42)+(R26*R42)+(S26*S42)+(T26*T42)+(U26*U42)+(V26*V42)+(W26*W42)+(X26*X42)+(Y26*Y42)+(Z26*Z42)+(AA26*AA42)+(AB26*AB42) -> 6800 | AD26: =10%*AC26 -> 680 | AE26: =AC26-AD26 -> 6120 | AL26: =AE26/3 -> 2040 | AM26: =AL26 -> 2040 | AN26: =AM26 -> 2040
B27: =B26+1 -> 16 | AC27: =(E27*E42)+(F27*F42)+(G27*G42)+(H27*H42)+(I27*I42)+(J27*J42)+(K27*J42)+(L27*L42)+(M27*M42)+(N27*N42)+(O27*O42)+(P27*P42)+(Q27*Q42)+(R27*R42)+(S27*S42)+(T27*T42)+(U27*U42)+(V27*V42)+(W27*W42)+(X27*X42)+(Y27*Y42)+(Z27*Z42)+(AA27*AA42)+(AB27*AB42) -> 0 | AD27: =10%*AC27 -> 0 | AE27: =AC27-AD27 -> 0 | AL27: =AE27/3 -> 0 | AM27: =AL27 -> 0 | AN27: =AM27 -> 0
B28: =B27+1 -> 17 | AC28: =(E28*E42)+(F28*F42)+(G28*G42)+(H28*H42)+(I28*I42)+(J28*J42)+(K28*K42)+(L28*L42)+(M28*M42)+(N28*N42)+(O28*O42)+(P28*P42)+(Q28*Q42)+(R28*R42)+(S28*S42)+(T28*T42)+(U28*U42)+(V28*V42)+(W28*W42)+(X28*X42)+(Y28*Y42)+(Z28*Z42)+(AA28*AA42)+(AB28*AB42) -> 0 | AD28: =10%*AC28 -> 0 | AE28: =AC28-AD28 -> 0 | AL28: =AE28/3 -> 0 | AM28: =AL28 -> 0 | AN28: =AM28 -> 0
B29: =B28+1 -> 18 | AC29: =(E29*E42)+(F29*F42)+(G29*G42)+(H29*H42)+(I29*I42)+(J29*J42)+(K29*K42)+(L29*L42)+(M29*M42)+(N29*N42)+(O29*O42)+(P29*P42)+(Q29*Q42)+(R29*R42)+(S29*S42)+(T29*T42)+(U29*U42)+(V29*V42)+(W29*W42)+(X29*X42)+(Y29*Y42)+(Z29*Z42)+(AA29*AA42)+(AB29*AB42) -> 0 | AD29: =10%*AC29 -> 0 | AE29: =AC29-AD29 -> 0 | AL29: =AE29/3 -> 0 | AM29: =AL29 -> 0 | AN29: =AM29 -> 0
B30: =B29+1 -> 19 | AC30: =(E30*E42)+(F30*F42)+(G30*G42)+(H30*H42)+(I30*I42)+(J30*J42)+(K30*J42)+(L30*L42)+(M30*M42)+(N30*N42)+(O30*O42)+(P30*P42)+(Q30*Q42)+(R30*R42)+(S30*S42)+(T30*T42)+(U30*U42)+(V30*V42)+(W30*W42)+(X30*X42)+(Y30*Y42)+(Z30*Z42)+(AA30*AA42)+(AB30*AB42) -> 0 | AD30: =10%*AC30 -> 0 | AE30: =AC30-AD30 -> 0 | AL30: =AE30/3 -> 0 | AM30: =AL30 -> 0 | AN30: =AM30 -> 0
B31: =B30+1 -> 20 | AC31: =(E31*E42)+(F31*F42)+(G31*G42)+(H31*H42)+(I31*I42)+(J31*J42)+(K31*K42)+(L31*L42)+(M31*M42)+(N31*N42)+(O31*O42)+(P31*P42)+(Q31*Q42)+(R31*R42)+(S31*S42)+(T31*T42)+(U31*U42)+(V31*V42)+(W31*W42)+(X31*X42)+(Y31*Y42)+(Z31*Z42)+(AA31*AA42)+(AB31*AB42) -> 0 | AD31: =10%*AC31 -> 0 | AE31: =AC31-AD31 -> 0 | AL31: =AE31/3 -> 0 | AM31: =AL31 -> 0 | AN31: =AM31 -> 0
B32: =B31+1 -> 21 | AC32: =(E32*E42)+(F32*F42)+(G32*G42)+(H32*H42)+(I32*I42)+(J32*J42)+(K32*K42)+(L32*L42)+(M32*M42)+(N32*N42)+(O32*O42)+(P32*P42)+(Q32*Q42)+(R32*R42)+(S32*S42)+(T32*T42)+(U32*U42)+(V32*V42)+(W32*W42)+(X32*X42)+(Y32*Y42)+(Z32*Z42)+(AA32*AA42)+(AB32*AB42) -> 0 | AD32: =10%*AC32 -> 0 | AE32: =AC32-AD32 -> 0 | AL32: =AE32/3 -> 0 | AM32: =AL32 -> 0 | AN32: =AM32 -> 0
B33: =B32+1 -> 22 | AC33: =(E33*E42)+(F33*F42)+(G33*G42)+(H33*H42)+(I33*I42)+(J33*J42)+(K33*J42)+(L33*L42)+(M33*M42)+(N33*N42)+(O33*O42)+(P33*P42)+(Q33*Q42)+(R33*R42)+(S33*S42)+(T33*T42)+(U33*U42)+(V33*V42)+(W33*W42)+(X33*X42)+(Y33*Y42)+(Z33*Z42)+(AA33*AA42)+(AB33*AB42) -> 0 | AD33: =10%*AC33 -> 0 | AE33: =AC33-AD33 -> 0 | AL33: =AE33/3 -> 0 | AM33: =AL33 -> 0 | AN33: =AM33 -> 0
B34: =B33+1 -> 23 | AC34: =(E34*E42)+(F34*F42)+(G34*G42)+(H34*H42)+(I34*I42)+(J34*J42)+(K34*K42)+(L34*L42)+(M34*M42)+(N34*N42)+(O34*O42)+(P34*P42)+(Q34*Q42)+(R34*R42)+(S34*S42)+(T34*T42)+(U34*U42)+(V34*V42)+(W34*W42)+(X34*X42)+(Y34*Y42)+(Z34*Z42)+(AA34*AA42)+(AB34*AB42) -> 0 | AD34: =10%*AC34 -> 0 | AE34: =AC34-AD34 -> 0 | AL34: =AE34/3 -> 0 | AM34: =AL34 -> 0 | AN34: =AM34 -> 0
B35: =B34+1 -> 24 | AC35: =(E35*E42)+(F35*F42)+(G35*G42)+(H35*H42)+(I35*I42)+(J35*J42)+(K35*K42)+(L35*L42)+(M35*M42)+(N35*N42)+(O35*O42)+(P35*P42)+(Q35*Q42)+(R35*R42)+(S35*S42)+(T35*T42)+(U35*U42)+(V35*V42)+(W35*W42)+(X35*X42)+(Y35*Y42)+(Z35*Z42)+(AA35*AA42)+(AB35*AB42) -> 0 | AD35: =10%*AC35 -> 0 | AE35: =AC35-AD35 -> 0 | AL35: =AE35/3 -> 0 | AM35: =AL35 -> 0 | AN35: =AM35 -> 0
B36: =B35+1 -> 25 | AC36: =(E36*E42)+(F36*F42)+(G36*G42)+(H36*H42)+(I36*I42)+(J36*J42)+(K36*J42)+(L36*L42)+(M36*M42)+(N36*N42)+(O36*O42)+(P36*P42)+(Q36*Q42)+(R36*R42)+(S36*S42)+(T36*T42)+(U36*U42)+(V36*V42)+(W36*W42)+(X36*X42)+(Y36*Y42)+(Z36*Z42)+(AA36*AA42)+(AB36*AB42) -> 0 | AD36: =10%*AC36 -> 0 | AE36: =AC36-AD36 -> 0 | AL36: =AE36/3 -> 0 | AM36: =AL36 -> 0 | AN36: =AM36 -> 0
B37: =B36+1 -> 26 | AC37: =(E37*E42)+(F37*F42)+(G37*G42)+(H37*H42)+(I37*I42)+(J37*J42)+(K37*K42)+(L37*L42)+(M37*M42)+(N37*N42)+(O37*O42)+(P37*P42)+(Q37*Q42)+(R37*R42)+(S37*S42)+(T37*T42)+(U37*U42)+(V37*V42)+(W37*W42)+(X37*X42)+(Y37*Y42)+(Z37*Z42)+(AA37*AA42)+(AB37*AB42) -> 0 | AD37: =10%*AC37 -> 0 | AE37: =AC37-AD37 -> 0 | AL37: =AE37/3 -> 0 | AM37: =AL37 -> 0 | AN37: =AM37 -> 0
B38: =B37+1 -> 27 | AC38: =(E38*E42)+(F38*F42)+(G38*G42)+(H38*H42)+(I38*I42)+(J38*J42)+(K38*K42)+(L38*L42)+(M38*M42)+(N38*N42)+(O38*O42)+(P38*P42)+(Q38*Q42)+(R38*R42)+(S38*S42)+(T38*T42)+(U38*U42)+(V38*V42)+(W38*W42)+(X38*X42)+(Y38*Y42)+(Z38*Z42)+(AA38*AA42)+(AB38*AB42) -> 0 | AD38: =10%*AC38 -> 0 | AE38: =AC38-AD38 -> 0 | AL38: =AE38/3 -> 0 | AM38: =AL38 -> 0 | AN38: =AM38 -> 0
B39: TOTAL | C39: =COUNTA(C12:C38) -> 15 | E39: =SUM(E12:E38) -> 4 | F39: =SUM(F12:F38) -> 2 | G39: =SUM(G12:G38) -> 8 | H39: =SUM(H12:H38) -> 0 | I39: =SUM(I12:I38) -> 0 | J39: =SUM(J12:J38) -> 0 | K39: =SUM(K12:K38) -> 0 | L39: =SUM(L12:L38) -> 0 | ... AE39: =SUM(AE12:AE38) -> 77529.6 | AL39: =SUM(AL12:AL38) -> 25843.2 | AM39: =SUM(AM12:AM38) -> 25843.2 | AN39: =SUM(AN12:AN38) -> 25843.2 | AO39: =SUM(AO12:AO38) -> 5624 | AP39: =SUM(AP12:AP38) -> 4650.9
C42: Price | E42: 204 | F42: =12*E42 -> 2448 | G42: 177 | H42: =G42*48 -> 8496 | I42: 204 | J42: =I42*12 -> 2448 | K42: 177 | L42: =K42*15 -> 2655 | M42: 116 | N42: =M42*6 -> 696 | O42: 272 | P42: =O42*4 -> 1088 | Q42: 1496 | R42: 272 | S42: =R42*4 -> 1088 | T42: 6800 | U42: 75 | V42: =U42*12 -> 900 | W42: 20 | X42: 68 | Y42: =X42*12 -> 816 | Z42: 1904 | AA42: 122 | AB42: 340

Sheet kramokrom 1
C1: NOTE:
C2: 1. Enter the quantity of agro inputs requested by the farmer either in pcs or boxes under each agro input
C3: 2. Do not change any thing in the excel sheet. The cells are linked
K4: NEW PRICES
C5: REGION:
C6: DISTRICT: | D6: NKABOM MAN
C7: SOCIETY: | D7: kramokrom
B8: NO. | C8: FARMER NAME | D8: MOBILE NO. | E8: AcetaStar -Adama (1Lt) | G8: Galil | I8: AKATE BRAFO | K8: PHYTOGREEN | M8: BEGREEN | O8: Agyenkwa Liquid Fertilizer (5Lt) | Q8: Matabi (15Lt) | R8: PLANTFEED | T8: Solo Machine | U8: All Wedicides (Glyphosate) | W8: NODOX | X8: ALL GRAMO | Z8: STANDARD PRUNNER | AA8: WELLINGTON BOOT | AB8: OVERALL | AC8: TOTAL AMOUNT (GHc) | AD8: DEPOSIT PAID (GHc) | AE8: OUTS. BALANCE (GHc) | AF8: REPAYMENT PLAN(GHC)
E9: PCs | F9: Box (12pcs) | G9: PCs | H9: Box | I9: PCs | J9: Box | K9: 1LT | L9: BOX(15) | M9: 1GALLON | N9: BOX(6) | O9: PCs | P9: Box(4) | Q9: PCs | R9: 1 GALLON | S9: BOX(4) | T9: PCs | U9: PCS | V9: BOX(12) | W9: PCs | X9: PCS | Y9: BOX(12) | Z9: PC | AA9: PC | AB9: PC | AF9: OCT | AG9: NOV | AH9: NOV | AL9: OCT | AM9: NOV | AN9: DEC | AO9: TOTAL PAYMENT
B10: =B9+1 -> 1 | C10: TEYE JOSHUA | D10: 02421093512 | F10: 3 | T10: 1 | V10: 1 | AC10: =(E10*E46)+(F10*F46)+(G10*G46)+(H10*H46)+(I10*I46)+(J10*J46)+(K10*K46)+(L10*L46)+(M10*M46)+(N10*N46)+(O10*O46)+(P10*P46)+(Q10*Q46)+(R10*R46)+(S10*S46)+(T10*T46)+(U10*U46)+(V10*V46)+(W10*W46)+(X10*X46)+(Y10*Y46)+(Z10*Z46)+(AA10*AA46)+(AB10*AB46) -> 15044 | AD10: =10%*AC10 -> 1504.4 | AE10: =AC10-AD10 -> 13539.6 | AL10: =AE10/3 -> 4513.2 | AM10: =AL10 -> 4513.2 | AN10: =AM10 -> 4513.2 | AO10: =AD10+AF10+AG10+AH10+AI10+AJ10+AK10 -> 1504.4
B11: =B10+1 -> 2 | C11: YIADOMAA ELIZABETH | D11: 0542349614 | T11: 1 | AC11: =(E11*E46)+(F11*F46)+(G11*G46)+(H11*H46)+(I11*I46)+(J11*J46)+(K11*K46)+(L11*L46)+(M11*M46)+(N11*N46)+(O11*O46)+(P11*P46)+(Q11*Q46)+(R11*R46)+(S11*S46)+(T11*T46)+(U11*U46)+(V11*V46)+(W11*W46)+(X11*X46)+(Y11*Y46)+(Z11*Z46)+(AA11*AA46)+(AB11*AB46) -> 6800 | AD11: =10%*AC11 -> 680 | AE11: =AC11-AD11 -> 6120 | AL11: =AE11/3 -> 2040 | AM11: =AL11 -> 2040 | AN11: =AM11 -> 2040 | AO11: =AD11+AF11+AG11+AH11+AI11+AJ11+AK11 -> 680
B12: =B11+1 -> 3 | C12: NARH THEOPHILUS | D12: 0543421545 | T12: 1 | AA12: 1 | AC12: =(E12*E46)+(F12*F46)+(G12*G46)+(H12*H46)+(I12*I46)+(J12*J46)+(K12*K46)+(L12*L46)+(M12*M46)+(N12*N46)+(O12*O46)+(P12*P46)+(Q12*Q46)+(R12*R46)+(S12*S46)+(T12*T46)+(U12*U46)+(V12*V46)+(W12*W46)+(X12*X46)+(Y12*Y46)+(Z12*Z46)+(AA12*AA46)+(AB12*AB46) -> 6922 | AD12: =10%*AC12 -> 692.2 | AE12: =AC12-AD12 -> 6229.8 | AL12: =AE12/3 -> 2076.6 | AM12: =AL12 -> 2076.6 | AN12: =AM12 -> 2076.6 | AO12: =AD12+AF12+AG12+AH12+AI12+AJ12+AK12 -> 692.2
B13: =B12+1 -> 4 | C13: NYIMETEYE SAMUEL | H13: 1 | I13: 1 | AC13: =(E13*E46)+(F13*F46)+(G13*G46)+(H13*H46)+(I13*I46)+(J13*J46)+(K13*K46)+(L13*L46)+(M13*M46)+(N13*N46)+(O13*O46)+(P13*P46)+(Q13*Q46)+(R13*R46)+(S13*S46)+(T13*T46)+(U13*U46)+(V13*V46)+(W13*W46)+(X13*X46)+(Y13*Y46)+(Z13*Z46)+(AA13*AA46)+(AB13*AB46) -> 8700 | AD13: =10%*AC13 -> 870 | AE13: =AC13-AD13 -> 7830 | AL13: =AE13/3 -> 2610 | AM13: =AL13 -> 2610 | AN13: =AM13 -> 2610 | AO13: =AD13+AF13+AG13+AH13+AI13+AJ13+AK13 -> 870
B14: =B13+1 -> 5 | C14: OBENG LAWRENCE | D14: 0244198138 | F14: 2 | Q14: 1 | T14: 1 | AC14: =(E14*E46)+(F14*F46)+(G14*G46)+(H14*H46)+(I14*I46)+(J14*J46)+(K14*K46)+(L14*L46)+(M14*M46)+(N14*N46)+(O14*O46)+(P14*P46)+(Q14*Q46)+(R14*R46)+(S14*S46)+(T14*T46)+(U14*U46)+(V14*V46)+(W14*W46)+(X14*X46)+(Y14*Y46)+(Z14*Z46)+(AA14*AA46)+(AB14*AB46) -> 13192 | AD14: =10%*AC14 -> 1319.2 | AE14: =AC14-AD14 -> 11872.8 | AL14: =AE14/3 -> 3957.6 | AM14: =AL14 -> 3957.6 | AN14: =AM14 -> 3957.6 | AO14: =AD14+AF14+AG14+AH14+AI14+AJ14+AK14 -> 1319.2
B15: =B14+1 -> 6 | C15: TETTEH SAMUEL | D15: 0533072508 | F15: 1 | Q15: 1 | AC15: =(E15*E46)+(F15*F46)+(G15*G46)+(H15*H46)+(I15*I46)+(J15*J50)+(K15*K46)+(L15*L46)+(M15*M46)+(N15*N46)+(O15*O46)+(P15*P46)+(Q15*Q46)+(R15*R46)+(S15*S46)+(T15*T46)+(U15*U46)+(V15*V46)+(W15*W46)+(X15*X46)+(Y15*Y46)+(Z15*Z46)+(AA15*AA46)+(AB15*AB46) -> 3944 | AD15: =10%*AC15 -> 394.4 | AE15: =AC15-AD15 -> 3549.6 | AL15: =AE15/3 -> 1183.2 | AM15: =AL15 -> 1183.2 | AN15: =AM15 -> 1183.2 | AO15: =AD15+AF15+AG15+AH15+AI15+AJ15+AK15 -> 394.4
B16: =B15+1 -> 7 | C16: SERWAA GIFTY | D16: 0555055892 | F16: 2 | AC16: =(E16*E46)+(F16*F46)+(G16*G46)+(H16*H46)+(I16*I46)+(J16*J46)+(K16*K46)+(L16*L46)+(M16*M46)+(N16*N46)+(O16*O46)+(P16*P46)+(Q16*Q46)+(R16*R46)+(S16*S46)+(T16*T46)+(U16*U46)+(V16*V46)+(W16*W46)+(X16*X46)+(Y16*Y46)+(Z16*Z46)+(AA16*AA46)+(AB16*AB46) -> 4896 | AD16: =10%*AC16 -> 489.6 | AE16: =AC16-AD16 -> 4406.4 | AL16: =AE16/3 -> 1468.8 | AM16: =AL16 -> 1468.8 | AN16: =AM16 -> 1468.8 | AO16: =AD16+AF16+AG16+AH16+AI16+AJ16+AK16 -> 489.6
B17: =B16+1 -> 8 | C17: AYEREBI AGNES | D17: 0549322636 | F17: 1 | T17: 1 | AC17: =(E17*E46)+(F17*F46)+(G17*G46)+(H17*H46)+(I17*I46)+(J17*J46)+(K17*K46)+(L17*L46)+(M17*M46)+(N17*N46)+(O17*O46)+(P17*P46)+(Q17*Q46)+(R17*R46)+(S17*S46)+(T17*T46)+(U17*U46)+(V17*V46)+(W17*W46)+(X17*X46)+(Y17*Y46)+(Z17*Z46)+(AA17*AA46)+(AB17*AB46) -> 9248 | AD17: =10%*AC17 -> 924.8 | AE17: =AC17-AD17 -> 8323.2 | AL17: =AE17/3 -> 2774.4 | AM17: =AL17 -> 2774.4 | AN17: =AM17 -> 2774.4 | AO17: =AD17+AF17+AG17+AH17+AI17+AJ17+AK17 -> 924.8
B18: =B17+1 -> 9 | C18: SEKYI CHARITY | D18: 059558220 | E18: 6 | Y18: 1 | AC18: =(E18*E46)+(F18*F46)+(G18*G46)+(H18*H46)+(I18*I46)+(J18*J46)+(K18*K46)+(L18*L46)+(M18*M46)+(N18*N46)+(O18*O46)+(P18*P46)+(Q18*Q46)+(R18*R46)+(S18*S46)+(T18*T46)+(U18*U46)+(V18*V46)+(W18*W46)+(X18*X46)+(Y18*Y46)+(Z18*Z46)+(AA18*AA46)+(AB18*AB46) -> 1848 | AD18: =10%*AC18 -> 184.8 | AE18: =AC18-AD18 -> 1663.2 | AL18: =AE18/3 -> 554.4 | AM18: =AL18 -> 554.4 | AN18: =AM18 -> 554.4 | AO18: =AD18+AF18+AG18+AH18+AI18+AJ18+AK18 -> 184.8
B19: =B18+1 -> 10 | C19: TEKPERTRY RICHARD | D19: 0547111519 | T19: 1 | AC19: =(E19*E46)+(F19*F46)+(G19*G46)+(H19*H46)+(I19*I46)+(J19*J46)+(K19*K46)+(L19*L46)+(M19*M46)+(N19*N46)+(O19*O46)+(P19*P46)+(Q19*Q46)+(R19*R46)+(S19*S46)+(T19*T46)+(U19*U46)+(V19*V46)+(W19*W46)+(X19*X46)+(Y19*Y46)+(Z19*Z46)+(AA19*AA46)+(AB19*AB46) -> 6800 | AD19: =10%*AC19 -> 680 | AE19: =AC19-AD19 -> 6120 | AL19: =AE19/3 -> 2040 | AM19: =AL19 -> 2040 | AN19: =AM19 -> 2040 | AO19: =AD19+AF19+AG19+AH19+AI19+AJ19+AK19 -> 680
B20: =B19+1 -> 11 | C20: ACQUAH JOHN | D20: 0541041140 | T20: 1 | AC20: =(E20*E46)+(F20*F46)+(G20*G46)+(H20*H46)+(I20*I46)+(J20*J46)+(K20*K46)+(L20*L46)+(M20*M46)+(N20*N46)+(O20*O46)+(P20*P46)+(Q20*Q46)+(R20*R46)+(S20*S46)+(T20*T46)+(U20*U46)+(V20*V46)+(W20*W46)+(X20*X46)+(Y20*Y46)+(Z20*Z46)+(AA20*AA46)+(AB20*AB46) -> 6800 | AD20: =10%*AC20 -> 680 | AE20: =AC20-AD20 -> 6120 | AL20: =AE20/3 -> 2040 | AM20: =AL20 -> 2040 | AN20: =AM20 -> 2040 | AO20: =AD20+AF20+AG20+AH20+AI20+AJ20+AK20 -> 680
B21: =B20+1 -> 12 | C21: ADJEI PATRIC JUNIOR-NANA | D21: 0243960229 | E21: 6 | Y21: 1 | AC21: =(E21*E46)+(F21*F46)+(G21*G46)+(H21*H46)+(I21*I46)+(J21*J46)+(K21*K46)+(L21*L46)+(M21*M46)+(N21*N46)+(O21*O46)+(P21*P46)+(Q21*Q46)+(R21*R46)+(S21*S46)+(T21*T46)+(U21*U46)+(V21*V46)+(W21*W46)+(X21*X46)+(Y21*Y46)+(Z21*Z46)+(AA21*AA46)+(AB21*AB46) -> 1848 | AD21: =10%*AC21 -> 184.8 | AE21: =AC21-AD21 -> 1663.2 | AL21: =AE21/3 -> 554.4 | AM21: =AL21 -> 554.4 | AN21: =AM21 -> 554.4 | AO21: =AD21+AF21+AG21+AH21+AI21+AJ21+AK21 -> 184.8
B22: =B21+1 -> 13 | C22: FRIMPONG STEPHEN OFORI | D22: 0555607369 | P22: 1 | Q22: 1 | V22: 1 | AC22: =(E22*E46)+(F22*F46)+(G22*G46)+(H22*H46)+(I22*I46)+(J22*J46)+(K22*K46)+(L22*L46)+(M22*M46)+(N22*N46)+(O22*O46)+(P22*P46)+(Q22*Q46)+(R22*R46)+(S22*S46)+(T22*T46)+(U22*U46)+(V22*V46)+(W22*W46)+(X22*X46)+(Y22*Y46)+(Z22*Z46)+(AA22*AA46)+(AB22*AB46) -> 3484 | AD22: =10%*AC22 -> 348.4 | AE22: =AC22-AD22 -> 3135.6 | AL22: =AE22/3 -> 1045.2 | AM22: =AL22 -> 1045.2 | AN22: =AM22 -> 1045.2 | AO22: =AD22+AF22+AG22+AH22+AI22+AJ22+AK22 -> 348.4
B23: =B22+1 -> 14 | C23: BOATENG EBENEZER | D23: 0245960229 | F23: 1 | T23: 1 | AC23: =(E23*E46)+(F23*F46)+(G23*G46)+(H23*H46)+(I23*I46)+(J23*J46)+(K23*J46)+(L23*L46)+(M23*M46)+(N23*N46)+(O23*O46)+(P23*P46)+(Q23*Q46)+(R23*R46)+(S23*S46)+(T23*T46)+(U23*U46)+(V23*V46)+(W23*W46)+(X23*X46)+(Y23*Y46)+(Z23*Z46)+(AA23*AA46)+(AB23*AB46) -> 9248 | AD23: =10%*AC23 -> 924.8 | AE23: =AC23-AD23 -> 8323.2 | AL23: =AE23/3 -> 2774.4 | AM23: =AL23 -> 2774.4 | AN23: =AM23 -> 2774.4 | AO23: =AD23+AF23+AG23+AH23+AI23+AJ23+AK23 -> 924.8
B24: =B23+1 -> 15 | C24: OBENG ISAAC | D24: 0549301571 | T24: 1 | Y24: 1 | AC24: =(E24*E46)+(F24*F46)+(G24*G46)+(H24*H46)+(I24*I46)+(J24*J46)+(K24*K46)+(L24*L46)+(M24*M46)+(N24*N46)+(O24*O46)+(P24*P46)+(Q24*Q46)+(R24*R46)+(S24*S46)+(T24*T46)+(U24*U46)+(V24*V46)+(W24*W46)+(X24*X46)+(Y24*Y46)+(Z24*Z46)+(AA24*AA46)+(AB24*AB46) -> 7424 | AD24: =10%*AC24 -> 742.4 | AE24: =AC24-AD24 -> 6681.6 | AL24: =AE24/3 -> 2227.2 | AM24: =AL24 -> 2227.2 | AN24: =AM24 -> 2227.2 | AO24: =AD24+AF24+AG24+AH24+AI24+AJ24+AK24 -> 742.4
B25: =B24+1 -> 16 | C25: ASAMOAH COMFORT | D25: 0592954370 | H25: 1 | T25: 1 | AC25: =(E25*E46)+(F25*F46)+(G25*G46)+(H25*H46)+(I25*I46)+(J25*J46)+(K25*K46)+(L25*L46)+(M25*M46)+(N25*N46)+(O25*O46)+(P25*P46)+(Q25*Q46)+(R25*R46)+(S25*S46)+(T25*T46)+(U25*U46)+(V25*V46)+(W25*W46)+(X25*X46)+(Y25*Y46)+(Z25*Z46)+(AA25*AA46)+(AB25*AB46) -> 15296 | AD25: =10%*AC25 -> 1529.6 | AE25: =AC25-AD25 -> 13766.4 | AL25: =AE25/3 -> 4588.8 | AM25: =AL25 -> 4588.8 | AN25: =AM25 -> 4588.8 | AO25: =AD25+AF25+AG25+AH25+AI25+AJ25+AK25 -> 1529.6
B26: =B25+1 -> 17 | C26: ASARE AKWASI | D26: 0547375189 | E26: 4 | O26: 2 | U26: 4 | AC26: =(E26*E46)+(F26*F46)+(G26*G46)+(H26*H46)+(I26*I46)+(J26*J46)+(K26*J46)+(L26*L46)+(M26*M46)+(N26*N46)+(O26*O46)+(P26*P46)+(Q26*Q46)+(R26*R46)+(S26*S46)+(T26*T46)+(U26*U46)+(V26*V46)+(W26*W46)+(X26*X46)+(Y26*Y46)+(Z26*Z46)+(AA26*AA46)+(AB26*AB46) -> 1660 | AD26: =10%*AC26 -> 166 | AE26: =AC26-AD26 -> 1494 | AL26: =AE26/3 -> 498 | AM26: =AL26 -> 498 | AN26: =AM26 -> 498 | AO26: =AD26+AF26+AG26+AH26+AI26+AJ26+AK26 -> 166
B27: =B26+1 -> 18 | C27: LOMOTEY AGNES | D27: 0556098446 | T27: 1 | AC27: =(E27*E46)+(F27*F46)+(G27*G46)+(H27*H46)+(I27*I46)+(J27*J46)+(K27*K46)+(L27*L46)+(M27*M46)+(N27*N46)+(O27*O46)+(P27*P46)+(Q27*Q46)+(R27*R46)+(S27*S46)+(T27*T46)+(U27*U46)+(V27*V46)+(W27*W46)+(X27*X46)+(Y27*Y46)+(Z27*Z46)+(AA27*AA46)+(AB27*AB46) -> 6800 | AD27: =10%*AC27 -> 680 | AE27: =AC27-AD27 -> 6120 | AL27: =AE27/3 -> 2040 | AM27: =AL27 -> 2040 | AN27: =AM27 -> 2040 | AO27: =AD27+AF27+AG27+AH27+AI27+AJ27+AK27 -> 680
B28: =B27+1 -> 19 | C28: ATTA REBECCA | D28: 0247474621 | E28: 4 | T28: 1 | U28: 4 | AC28: =(E28*E46)+(F28*F46)+(G28*G46)+(H28*H46)+(I28*I46)+(J28*J46)+(K28*K46)+(L28*L46)+(M28*M46)+(N28*N46)+(O28*O46)+(P28*P46)+(Q28*Q46)+(R28*R46)+(S28*S46)+(T28*T46)+(U28*U46)+(V28*V46)+(W28*W46)+(X28*X46)+(Y28*Y46)+(Z28*Z46)+(AA28*AA46)+(AB28*AB46) -> 7916 | AD28: =10%*AC28 -> 791.6 | AE28: =AC28-AD28 -> 7124.4 | AL28: =AE28/3 -> 2374.8 | AM28: =AL28 -> 2374.8 | AN28: =AM28 -> 2374.8 | AO28: =AD28+AF28+AG28+AH28+AI28+AJ28+AK28 -> 791.6
B29: =B28+1 -> 20 | C29: MUSA MAKU | D29: 0542349614 | E29: 4 | T29: 1 | AC29: =(E29*E46)+(F29*F46)+(G29*G46)+(H29*H46)+(I29*I46)+(J29*J46)+(K29*J46)+(L29*L46)+(M29*M46)+(N29*N46)+(O29*O46)+(P29*P46)+(Q29*Q46)+(R29*R46)+(S29*S46)+(T29*T46)+(U29*U46)+(V29*V46)+(W29*W46)+(X29*X46)+(Y29*Y46)+(Z29*Z46)+(AA29*AA46)+(AB29*AB46) -> 7616 | AD29: =10%*AC29 -> 761.6 | AE29: =AC29-AD29 -> 6854.4 | AL29: =AE29/3 -> 2284.8 | AM29: =AL29 -> 2284.8 | AN29: =AM29 -> 2284.8 | AO29: =AD29+AF29+AG29+AH29+AI29+AJ29+AK29 -> 761.6
B30: =B29+1 -> 21 | C30: KORLEY KWASI MATIN | E30: 6 | K30: 6 | AC30: =(E30*E46)+(F30*F46)+(G30*G46)+(H30*H46)+(I30*I46)+(J30*J46)+(K30*K46)+(L30*L46)+(M30*M46)+(N30*N46)+(O30*O46)+(P30*P46)+(Q30*Q46)+(R30*R46)+(S30*S46)+(T30*T46)+(U30*U46)+(V30*V46)+(W30*W46)+(X30*X46)+(Y30*Y46)+(Z30*Z46)+(AA30*AA46)+(AB30*AB46) -> 2286 | AD30: =10%*AC30 -> 228.6 | AE30: =AC30-AD30 -> 2057.4 | AL30: =AE30/3 -> 685.8 | AM30: =AL30 -> 685.8 | AN30: =AM30 -> 685.8 | AO30: =AD30+AF30+AG30+AH30+AI30+AJ30+AK30 -> 228.6
B31: =B30+1 -> 22 | C31: TEYE GRACE | D31: 0551177951 | F31: 1 | T31: 1 | AC31: =(E31*E46)+(F31*F46)+(G31*G46)+(H31*H46)+(I31*I46)+(J31*J46)+(K31*K46)+(L31*L46)+(M31*M46)+(N31*N46)+(O31*O46)+(P31*P46)+(Q31*Q46)+(R31*R46)+(S31*S46)+(T31*T46)+(U31*U46)+(V31*V46)+(W31*W46)+(X31*X46)+(Y31*Y46)+(Z31*Z46)+(AA31*AA46)+(AB31*AB46) -> 9248 | AD31: =10%*AC31 -> 924.8 | AE31: =AC31-AD31 -> 8323.2 | AL31: =AE31/3 -> 2774.4 | AM31: =AL31 -> 2774.4 | AN31: =AM31 -> 2774.4 | AO31: =AD31+AF31+AG31+AH31+AI31+AJ31+AK31 -> 924.8
B32: =B31+1 -> 23 | C32: TEYE SAMUEL | D32: 0543062229 | T32: 1 | AC32: =(E32*E46)+(F32*F46)+(G32*G46)+(H32*H46)+(I32*I46)+(J32*J46)+(K32*J46)+(L32*L46)+(M32*M46)+(N32*N46)+(O32*O46)+(P32*P46)+(Q32*Q46)+(R32*R46)+(S32*S46)+(T32*T46)+(U32*U46)+(V32*V46)+(W32*W46)+(X32*X46)+(Y32*Y46)+(Z32*Z46)+(AA32*AA46)+(AB32*AB46) -> 6800 | AD32: =10%*AC32 -> 680 | AE32: =AC32-AD32 -> 6120 | AL32: =AE32/3 -> 2040 | AM32: =AL32 -> 2040 | AN32: =AM32 -> 2040 | AO32: =AD32+AF32+AG32+AH32+AI32+AJ32+AK32 -> 680
B33: =B32+1 -> 24 | C33: TEYE MONICA | Y33: 1 | AC33: =(E33*E46)+(F33*F46)+(G33*G46)+(H33*H46)+(I33*I46)+(J33*J46)+(K33*K46)+(L33*L46)+(M33*M46)+(N33*N46)+(O33*O46)+(P33*P46)+(Q33*Q46)+(R33*R46)+(S33*S46)+(T33*T46)+(U33*U46)+(V33*V46)+(W33*W46)+(X33*X46)+(Y33*Y46)+(Z33*Z46)+(AA33*AA46)+(AB33*AB46) -> 624 | AD33: =10%*AC33 -> 62.4 | AE33: =AC33-AD33 -> 561.6 | AL33: =AE33/3 -> 187.2 | AM33: =AL33 -> 187.2 | AN33: =AM33 -> 187.2 | AO33: =AD33+AF33+AG33+AH33+AI33+AJ33+AK33 -> 62.4
B34: =B33+1 -> 25 | C34: DANKYI PAUL | D34: 0246894120 | Z34: 1 | AC34: =(E34*E46)+(F34*F46)+(G34*G46)+(H34*H46)+(I34*I46)+(J34*J46)+(K34*K46)+(L34*L46)+(M34*M46)+(N34*N46)+(O34*O46)+(P34*P46)+(Q34*Q46)+(R34*R46)+(S34*S46)+(T34*T46)+(U34*U46)+(V34*V46)+(W34*W46)+(X34*X46)+(Y34*Y46)+(Z34*Z46)+(AA34*AA46)+(AB34*AB46) -> 1904 | AD34: =10%*AC34 -> 190.4 | AE34: =AC34-AD34 -> 1713.6 | AL34: =AE34/3 -> 571.2 | AM34: =AL34 -> 571.2 | AN34: =AM34 -> 571.2
B35: =B34+1 -> 26 | C35: KWABLA SOLOMON | D35: 0241985412 | F35: 1 | T35: 1 | AC35: =(E35*E46)+(F35*F46)+(G35*G46)+(H35*H46)+(I35*I46)+(J35*J46)+(K35*J46)+(L35*L46)+(M35*M46)+(N35*N46)+(O35*O46)+(P35*P46)+(Q35*Q46)+(R35*R46)+(S35*S46)+(T35*T46)+(U35*U46)+(V35*V46)+(W35*W46)+(X35*X46)+(Y35*Y46)+(Z35*Z46)+(AA35*AA46)+(AB35*AB46) -> 9248 | AD35: =10%*AC35 -> 924.8 | AE35: =AC35-AD35 -> 8323.2 | AL35: =AE35/3 -> 2774.4 | AM35: =AL35 -> 2774.4 | AN35: =AM35 -> 2774.4
B36: =B35+1 -> 27 | C36: ABDULRAMANI IBRAHIM | T36: 1 | AC36: =(E36*E46)+(F36*F46)+(G36*G46)+(H36*H46)+(I36*I46)+(J36*J46)+(K36*K46)+(L36*L46)+(M36*M46)+(N36*N46)+(O36*O46)+(P36*P46)+(Q36*Q46)+(R36*R46)+(S36*S46)+(T36*T46)+(U36*U46)+(V36*V46)+(W36*W46)+(X36*X46)+(Y36*Y46)+(Z36*Z46)+(AA36*AA46)+(AB36*AB46) -> 6800 | AD36: =10%*AC36 -> 680 | AE36: =AC36-AD36 -> 6120 | AL36: =AE36/3 -> 2040 | AM36: =AL36 -> 2040 | AN36: =AM36 -> 2040
B37: =B36+1 -> 28 | C37: KWAKYE CHARLES | V37: 1 | AC37: =(E37*E46)+(F37*F46)+(G37*G46)+(H37*H46)+(I37*I46)+(J37*J46)+(K37*K46)+(L37*L46)+(M37*M46)+(N37*N46)+(O37*O46)+(P37*P46)+(Q37*Q46)+(R37*R46)+(S37*S46)+(T37*T46)+(U37*U46)+(V37*V46)+(W37*W46)+(X37*X46)+(Y37*Y46)+(Z37*Z46)+(AA37*AA46)+(AB37*AB46) -> 900 | AD37: =10%*AC37 -> 90 | AE37: =AC37-AD37 -> 810 | AL37: =AE37/3 -> 270 | AM37: =AL37 -> 270 | AN37: =AM37 -> 270
C38: SOLOMON KWABENA | F38: 1 | T38: 1 | AC38: =(E38*E47)+(F38*F47)+(G38*G47)+(H38*H47)+(I38*I47)+(J38*J47)+(K38*K47)+(L38*L47)+(M38*M47)+(N38*N47)+(O38*O47)+(P38*P47)+(Q38*Q47)+(R38*R47)+(S38*S47)+(T38*T47)+(U38*U47)+(V38*V47)+(W38*W47)+(X38*X47)+(Y38*Y47)+(Z38*Z47)+(AA38*AA47)+(AB38*AB47) -> 0 | AD38: =10%*AC38 -> 0 | AE38: =AC38-AD38 -> 0
C39: EMMANUEL MARTEY
B40: =B37+1 -> 29 | C40: ARHIN KWAKU | F40: 2 | T40: 1 | V40: 1 | AC40: =(E40*E46)+(F40*F46)+(G40*G46)+(H40*H46)+(I40*I46)+(J40*J46)+(K40*J46)+(L40*L46)+(M40*M46)+(N40*N46)+(O40*O46)+(P40*P46)+(Q40*Q46)+(R40*R46)+(S40*S46)+(T40*T46)+(U40*U46)+(V40*V46)+(W40*W46)+(X40*X46)+(Y40*Y46)+(Z40*Z46)+(AA40*AA46)+(AB40*AB46) -> 12596 | AD40: =10%*AC40 -> 1259.6 | AE40: =AC40-AD40 -> 11336.4 | AL40: =AE40/3 -> 3778.8 | AM40: =AL40 -> 3778.8 | AN40: =AM40 -> 3778.8
B41: =B40+1 -> 30 | C41: MUSA MAKU | D41: 0532783503 | P41: 1 | T41: 1 | AC41: =(E41*E46)+(F41*F46)+(G41*G46)+(H41*H46)+(I41*I46)+(J41*J46)+(K41*K46)+(L41*L46)+(M41*M46)+(N41*N46)+(O41*O46)+(P41*P46)+(Q41*Q46)+(R41*R46)+(S41*S46)+(T41*T46)+(U41*U46)+(V41*V46)+(W41*W46)+(X41*X46)+(Y41*Y46)+(Z41*Z46)+(AA41*AA46)+(AB41*AB46) -> 7888 | AD41: =10%*AC41 -> 788.8 | AE41: =AC41-AD41 -> 7099.2 | AL41: =AE41/3 -> 2366.4 | AM41: =AL41 -> 2366.4 | AN41: =AM41 -> 2366.4
B42: =B41+1 -> 31 | C42: SEIDU ABUBAKAR | F42: 1 | AC42: =(E42*E46)+(F42*F46)+(G42*G46)+(H42*H46)+(I42*I46)+(J42*J46)+(K42*K46)+(L42*L46)+(M42*M46)+(N42*N46)+(O42*O46)+(P42*P46)+(Q42*Q46)+(R42*R46)+(S42*S46)+(T42*T46)+(U42*U46)+(V42*V46)+(W42*W46)+(X42*X46)+(Y42*Y46)+(Z42*Z46)+(AA42*AA46)+(AB42*AB46) -> 2448 | AD42: =10%*AC42 -> 244.8 | AE42: =AC42-AD42 -> 2203.2 | AL42: =AE42/3 -> 734.4 | AM42: =AL42 -> 734.4 | AN42: =AM42 -> 734.4
B43: TOTAL | C43: =COUNTA(C10:C42) -> 33 | E43: =SUM(E10:E42) -> 30 | F43: =SUM(F10:F42) -> 16 | G43: =SUM(G10:G42) -> 0 | H43: =SUM(H10:H42) -> 2 | I43: =SUM(I10:I42) -> 1 | J43: =SUM(J10:J42) -> 0 | K43: =SUM(K10:K42) -> 6 | L43: =SUM(L10:L42) -> 0 | ... AE43: =SUM(AE10:AE42) -> 185605.2 | AL43: =SUM(AL10:AL42) -> 61868.4 | AM43: =SUM(AM10:AM42) -> 61868.4 | AN43: =SUM(AN10:AN42) -> 61868.4 | AO43: =SUM(AO10:AO42) -> 16444.4
C46: Price | E46: 204 | F46: =12*E46 -> 2448 | G46: 177 | H46: =G46*48 -> 8496 | I46: 204 | J46: =I46*12 -> 2448 | K46: 177 | L46: =K46*15 -> 2655 | M46: 116 | N46: =M46*6 -> 696 | O46: 272 | P46: =O46*4 -> 1088 | Q46: 1496 | R46: 272 | S46: =R46*4 -> 1088 | T46: 6800 | U46: 75 | V46: =U46*12 -> 900 | W46: 20 | X46: 52 | Y46: =X46*12 -> 624 | Z46: 1904 | AA46: 122 | AB46: 340

Sheet SH1
C1: NOTE:
C2: 1. Enter the quantity of agro inputs requested by the farmer either in pcs or boxes under each agro input
C3: 2. Do not change any thing in the excel sheet. The cells are linked
D4: ATAYA BASE | K4: NEW PRICES
C5: REGION: | D5: ASHANTI
C6: DISTRICT: | D6: TEPA
C7: SOCIETY: | D7: ATAYA BASE
B8: NO. | C8: FARMER NAME | D8: MOBILE NO. | E8: AcetaStar -Adama (1Lt) | G8: Galil | I8: AKATE BRAFO | K8: PHYTOGREEN | M8: BEGREEN | O8: Agyenkwa Liquid Fertilizer (5Lt) | Q8: Matabi (15Lt) | R8: PLANTFEED | T8: Solo Machine | U8: All Wedicides (Glyphosate) | W8: NODOX | X8: ALL GRAMO | Z8: STANDARD PRUNNER | AA8: WELLINGTON BOOT | AB8: OVERALL | AC8: TOTAL AMOUNT (GHc) | AD8: DEPOSIT PAID (GHc) | AE8: OUTS. BALANCE (GHc) | AF8: REPAYMENT PLAN(GHC)
E9: PCs | F9: Box (12pcs) | G9: PCs | H9: Box | I9: PCs | J9: Box | K9: 1LT | L9: BOX(15) | M9: 1GALLON | N9: BOX(6) | O9: PCs | P9: Box(4) | Q9: PCs | R9: 1 GALLON | S9: BOX(4) | T9: PCs | U9: PCS | V9: BOX(12) | W9: PCs | X9: PCS | Y9: BOX(12) | Z9: PC | AA9: PC | AB9: PC | AF9: OCT | AG9: NOV | AH9: NOV | AI9: DEC | AL9: OCT | AM9: NOV | AN9: DEC | AO9: TOTAL PAYMENT
B10: =B9+1 -> 1 | AC10: =(E10*E40)+(F10*F40)+(G10*G40)+(H10*H40)+(I10*I40)+(J10*J40)+(K10*K40)+(L10*L40)+(M10*M40)+(N10*N40)+(O10*O40)+(P10*P40)+(Q10*Q40)+(R10*R40)+(S10*S40)+(T10*T40)+(U10*U40)+(V10*V40)+(W10*W40)+(X10*X40)+(Y10*Y40)+(Z10*Z40)+(AA10*AA40)+(AB10*AB40) -> 0 | AD10: =10%*AC10 -> 0 | AE10: =AC10-AD10 -> 0 | AL10: =AE10/3 -> 0 | AM10: =AL10 -> 0 | AN10: =AM10 -> 0 | AO10: =AD10+AF10+AG10+AH10+AI10+AJ10+AK10 -> 0
B11: =B10+1 -> 2 | AC11: =(E11*E41)+(F11*F41)+(G11*G41)+(H11*H41)+(I11*I41)+(J11*J41)+(K11*K41)+(L11*L41)+(M11*M41)+(N11*N41)+(O11*O41)+(P11*P41)+(Q11*Q41)+(R11*R41)+(S11*S41)+(T11*T41)+(U11*U41)+(V11*V41)+(W11*W41)+(X11*X41)+(Y11*Y41)+(Z11*Z41)+(AA11*AA41)+(AB11*AB41) -> 0 | AD11: =10%*AC11 -> 0 | AE11: =AC11-AD11 -> 0 | AL11: =AE11/3 -> 0 | AM11: =AL11 -> 0 | AN11: =AM11 -> 0 | AO11: =AD11+AF11+AG11+AH11+AI11+AJ11+AK11 -> 0
B12: =B11+1 -> 3 | AC12: =(E12*E42)+(F12*F42)+(G12*G42)+(H12*H42)+(I12*I42)+(J12*J42)+(K12*K42)+(L12*L42)+(M12*M42)+(N12*N42)+(O12*O42)+(P12*P42)+(Q12*Q42)+(R12*R42)+(S12*S42)+(T12*T42)+(U12*U42)+(V12*V42)+(W12*W42)+(X12*X42)+(Y12*Y42)+(Z12*Z42)+(AA12*AA42)+(AB12*AB42) -> 0 | AD12: =10%*AC12 -> 0 | AE12: =AC12-AD12 -> 0 | AL12: =AE12/3 -> 0 | AM12: =AL12 -> 0 | AN12: =AM12 -> 0 | AO12: =AD12+AF12+AG12+AH12+AI12+AJ12+AK12 -> 0
B13: =B12+1 -> 4 | AC13: =(E13*E43)+(F13*F43)+(G13*G43)+(H13*H43)+(I13*I43)+(J13*J43)+(K13*K43)+(L13*L43)+(M13*M43)+(N13*N43)+(O13*O43)+(P13*P43)+(Q13*Q43)+(R13*R43)+(S13*S43)+(T13*T43)+(U13*U43)+(V13*V43)+(W13*W43)+(X13*X43)+(Y13*Y43)+(Z13*Z43)+(AA13*AA43)+(AB13*AB43) -> 0 | AD13: =10%*AC13 -> 0 | AE13: =AC13-AD13 -> 0 | AL13: =AE13/3 -> 0 | AM13: =AL13 -> 0 | AN13: =AM13 -> 0 | AO13: =AD13+AF13+AG13+AH13+AI13+AJ13+AK13 -> 0
B14: =B13+1 -> 5 | AC14: =(E14*E44)+(F14*F44)+(G14*G44)+(H14*H44)+(I14*I44)+(J14*J44)+(K14*K44)+(L14*L44)+(M14*M44)+(N14*N44)+(O14*O44)+(P14*P44)+(Q14*Q44)+(R14*R44)+(S14*S44)+(T14*T44)+(U14*U44)+(V14*V44)+(W14*W44)+(X14*X44)+(Y14*Y44)+(Z14*Z44)+(AA14*AA44)+(AB14*AB44) -> 0 | AD14: =10%*AC14 -> 0 | AE14: =AC14-AD14 -> 0 | AL14: =AE14/3 -> 0 | AM14: =AL14 -> 0 | AN14: =AM14 -> 0 | AO14: =AD14+AF14+AG14+AH14+AI14+AJ14+AK14 -> 0
B15: =B14+1 -> 6 | AC15: =(E15*E45)+(F15*F45)+(G15*G45)+(H15*H45)+(I15*I45)+(J15*J45)+(K15*K45)+(L15*L45)+(M15*M45)+(N15*N45)+(O15*O45)+(P15*P45)+(Q15*Q45)+(R15*R45)+(S15*S45)+(T15*T45)+(U15*U45)+(V15*V45)+(W15*W45)+(X15*X45)+(Y15*Y45)+(Z15*Z45)+(AA15*AA45)+(AB15*AB45) -> 0 | AD15: =10%*AC15 -> 0 | AE15: =AC15-AD15 -> 0 | AL15: =AE15/3 -> 0 | AM15: =AL15 -> 0 | AN15: =AM15 -> 0 | AO15: =AD15+AF15+AG15+AH15+AI15+AJ15+AK15 -> 0
B16: =B15+1 -> 7 | AC16: =(E16*E43)+(F16*F43)+(G16*G43)+(H16*H43)+(I16*I43)+(J16*J43)+(K16*K43)+(L16*L43)+(M16*M43)+(N16*N43)+(O16*O43)+(P16*P43)+(Q16*Q43)+(R16*R43)+(S16*S43)+(T16*T43)+(U16*U43)+(V16*V43)+(W16*W43)+(X16*X43)+(Y16*Y43)+(Z16*Z43)+(AA16*AA43)+(AB16*AB43) -> 0 | AD16: =10%*AC16 -> 0 | AE16: =AC16-AO16 -> 0 | AL16: =AE16/3 -> 0 | AM16: =AL16 -> 0 | AN16: =AM16 -> 0 | AO16: =AD16+AF16+AG16+AH16+AI16+AJ16+AK16 -> 0
B17: =B16+1 -> 8 | AC17: =(E17*E43)+(F17*F43)+(G17*G43)+(H17*H43)+(I17*I43)+(J17*J43)+(K17*K43)+(L17*L43)+(M17*M43)+(N17*N43)+(O17*O43)+(P17*P43)+(Q17*Q43)+(R17*R43)+(S17*S43)+(T17*T43)+(U17*U43)+(V17*V43)+(W17*W43)+(X17*X43)+(Y17*Y43)+(Z17*Z43)+(AA17*AA43)+(AB17*AB43) -> 0 | AD17: =10%*AC17 -> 0 | AE17: =AC17-AD17 -> 0 | AL17: =AE17/3 -> 0 | AM17: =AL17 -> 0 | AN17: =AM17 -> 0 | AO17: =AD17+AF17+AG17+AH17+AI17+AJ17+AK17 -> 0
B18: =B17+1 -> 9 | AC18: =(E18*E44)+(F18*F44)+(G18*G44)+(H18*H44)+(I18*I44)+(J18*J44)+(K18*K44)+(L18*L44)+(M18*M44)+(N18*N44)+(O18*O44)+(P18*P44)+(Q18*Q44)+(R18*R44)+(S18*S44)+(T18*T44)+(U18*U44)+(V18*V44)+(W18*W44)+(X18*X44)+(Y18*Y44)+(Z18*Z44)+(AA18*AA44)+(AB18*AB44) -> 0 | AD18: =10%*AC18 -> 0 | AE18: =AC18-AD18 -> 0 | AL18: =AE18/3 -> 0 | AM18: =AL18 -> 0 | AN18: =AM18 -> 0 | AO18: =AD18+AF18+AG18+AH18+AI18+AJ18+AK18 -> 0
B19: =B18+1 -> 10 | AC19: =(E19*E45)+(F19*F45)+(G19*G45)+(H19*H45)+(I19*I45)+(J19*J45)+(K19*K45)+(L19*L45)+(M19*M45)+(N19*N45)+(O19*O45)+(P19*P45)+(Q19*Q45)+(R19*R45)+(S19*S45)+(T19*T45)+(U19*U45)+(V19*V45)+(W19*W45)+(X19*X45)+(Y19*Y45)+(Z19*Z45)+(AA19*AA45)+(AB19*AB45) -> 0 | AD19: =10%*AC19 -> 0 | AE19: =AC19-AD19 -> 0 | AL19: =AE19/3 -> 0 | AM19: =AL19 -> 0 | AN19: =AM19 -> 0 | AO19: =AD19+AF19+AG19+AH19+AI19+AJ19+AK19 -> 0
B20: =B19+1 -> 11 | AC20: =(E20*E46)+(F20*F46)+(G20*G46)+(H20*H46)+(I20*I46)+(J20*J46)+(K20*K46)+(L20*L46)+(M20*M46)+(N20*N46)+(O20*O46)+(P20*P46)+(Q20*Q46)+(R20*R46)+(S20*S46)+(T20*T46)+(U20*U46)+(V20*V46)+(W20*W46)+(X20*X46)+(Y20*Y46)+(Z20*Z46)+(AA20*AA46)+(AB20*AB46) -> 0 | AD20: =10%*AC20 -> 0 | AE20: =AC20-AD20 -> 0 | AL20: =AE20/3 -> 0 | AM20: =AL20 -> 0 | AN20: =AM20 -> 0 | AO20: =AD20+AF20+AG20+AH20+AI20+AJ20+AK20 -> 0
B21: =B20+1 -> 12 | AC21: =(E21*E47)+(F21*F47)+(G21*G47)+(H21*H47)+(I21*I47)+(J21*J47)+(K21*K47)+(L21*L47)+(M21*M47)+(N21*N47)+(O21*O47)+(P21*P47)+(Q21*Q47)+(R21*R47)+(S21*S47)+(T21*T47)+(U21*U47)+(V21*V47)+(W21*W47)+(X21*X47)+(Y21*Y47)+(Z21*Z47)+(AA21*AA47)+(AB21*AB47) -> 0 | AD21: =10%*AC21 -> 0 | AE21: =AC21-AD21 -> 0 | AL21: =AE21/3 -> 0 | AM21: =AL21 -> 0 | AN21: =AM21 -> 0 | AO21: =AD21+AF21+AG21+AH21+AI21+AJ21+AK21 -> 0
B22: =B21+1 -> 13 | AC22: =(E22*E48)+(F22*F48)+(G22*G48)+(H22*H48)+(I22*I48)+(J22*J48)+(K22*K48)+(L22*L48)+(M22*M48)+(N22*N48)+(O22*O48)+(P22*P48)+(Q22*Q48)+(R22*R48)+(S22*S48)+(T22*T48)+(U22*U48)+(V22*V48)+(W22*W48)+(X22*X48)+(Y22*Y48)+(Z22*Z48)+(AA22*AA48)+(AB22*AB48) -> 0 | AD22: =10%*AC22 -> 0 | AE22: =AC22-AD22 -> 0 | AL22: =AE22/3 -> 0 | AM22: =AL22 -> 0 | AN22: =AM22 -> 0 | AO22: =AD22+AF22+AG22+AH22+AI22+AJ22+AK22 -> 0
B23: =B22+1 -> 14 | AC23: =(E23*E49)+(F23*F49)+(G23*G49)+(H23*H49)+(I23*I49)+(J23*J49)+(K23*K49)+(L23*L49)+(M23*M49)+(N23*N49)+(O23*O49)+(P23*P49)+(Q23*Q49)+(R23*R49)+(S23*S49)+(T23*T49)+(U23*U49)+(V23*V49)+(W23*W49)+(X23*X49)+(Y23*Y49)+(Z23*Z49)+(AA23*AA49)+(AB23*AB49) -> 0 | AD23: =10%*AC23 -> 0 | AE23: =AC23-AD23 -> 0 | AL23: =AE23/3 -> 0 | AM23: =AL23 -> 0 | AN23: =AM23 -> 0 | AO23: =AD23+AF23+AG23+AH23+AI23+AJ23+AK23 -> 0
B24: =B23+1 -> 15 | AC24: =(E24*E50)+(F24*F50)+(G24*G50)+(H24*H50)+(I24*I50)+(J24*J50)+(K24*K50)+(L24*L50)+(M24*M50)+(N24*N50)+(O24*O50)+(P24*P50)+(Q24*Q50)+(R24*R50)+(S24*S50)+(T24*T50)+(U24*U50)+(V24*V50)+(W24*W50)+(X24*X50)+(Y24*Y50)+(Z24*Z50)+(AA24*AA50)+(AB24*AB50) -> 0 | AD24: =10%*AC24 -> 0 | AE24: =AC24-AD24 -> 0 | AL24: =AE24/3 -> 0 | AM24: =AL24 -> 0 | AN24: =AM24 -> 0 | AO24: =AD24+AF24+AG24+AH24+AI24+AJ24+AK24 -> 0
B25: =B24+1 -> 16 | AC25: =(E25*E51)+(F25*F51)+(G25*G51)+(H25*H51)+(I25*I51)+(J25*J51)+(K25*K51)+(L25*L51)+(M25*M51)+(N25*N51)+(O25*O51)+(P25*P51)+(Q25*Q51)+(R25*R51)+(S25*S51)+(T25*T51)+(U25*U51)+(V25*V51)+(W25*W51)+(X25*X51)+(Y25*Y51)+(Z25*Z51)+(AA25*AA51)+(AB25*AB51) -> 0 | AD25: =10%*AC25 -> 0 | AE25: =AC25-AD25 -> 0 | AL25: =AE25/3 -> 0 | AM25: =AL25 -> 0 | AN25: =AM25 -> 0 | AO25: =AD25+AF25+AG25+AH25+AI25+AJ25+AK25 -> 0
B26: =B25+1 -> 17 | AC26: =(E26*E52)+(F26*F52)+(G26*G52)+(H26*H52)+(I26*I52)+(J26*J52)+(K26*K52)+(L26*L52)+(M26*M52)+(N26*N52)+(O26*O52)+(P26*P52)+(Q26*Q52)+(R26*R52)+(S26*S52)+(T26*T52)+(U26*U52)+(V26*V52)+(W26*W52)+(X26*X52)+(Y26*Y52)+(Z26*Z52)+(AA26*AA52)+(AB26*AB52) -> 0 | AD26: =10%*AC26 -> 0 | AE26: =AC26-AD26 -> 0 | AL26: =AE26/3 -> 0 | AM26: =AL26 -> 0 | AN26: =AM26 -> 0
B27: =B26+1 -> 18 | AC27: =(E27*E53)+(F27*F53)+(G27*G53)+(H27*H53)+(I27*I53)+(J27*J53)+(K27*K53)+(L27*L53)+(M27*M53)+(N27*N53)+(O27*O53)+(P27*P53)+(Q27*Q53)+(R27*R53)+(S27*S53)+(T27*T53)+(U27*U53)+(V27*V53)+(W27*W53)+(X27*X53)+(Y27*Y53)+(Z27*Z53)+(AA27*AA53)+(AB27*AB53) -> 0 | AD27: =10%*AC27 -> 0 | AE27: =AC27-AD27 -> 0 | AL27: =AE27/3 -> 0 | AM27: =AL27 -> 0 | AN27: =AM27 -> 0
B28: =B27+1 -> 19 | AC28: =(E28*E43)+(F28*F43)+(G28*G43)+(H28*H43)+(I28*I43)+(J28*J43)+(K28*K43)+(L28*L43)+(M28*M43)+(N28*N43)+(O28*O43)+(P28*P43)+(Q28*Q43)+(R28*R43)+(S28*S43)+(T28*T43)+(U28*U43)+(V28*V43)+(W28*W43)+(X28*X43)+(Y28*Y43)+(Z28*Z43)+(AA28*AA43)+(AB28*AB43) -> 0 | AD28: =10%*AC28 -> 0 | AE28: =AC28-AD28 -> 0 | AL28: =AE28/3 -> 0 | AM28: =AL28 -> 0 | AN28: =AM28 -> 0
B29: =B28+1 -> 20 | AC29: =(E29*E43)+(F29*F43)+(G29*G43)+(H29*H43)+(I29*I43)+(J29*J43)+(K29*J43)+(L29*L43)+(M29*M43)+(N29*N43)+(O29*O43)+(P29*P43)+(Q29*Q43)+(R29*R43)+(S29*S43)+(T29*T43)+(U29*U43)+(V29*V43)+(W29*W43)+(X29*X43)+(Y29*Y43)+(Z29*Z43)+(AA29*AA43)+(AB29*AB43) -> 0 | AD29: =10%*AC29 -> 0 | AE29: =AC29-AD29 -> 0 | AL29: =AE29/3 -> 0 | AM29: =AL29 -> 0 | AN29: =AM29 -> 0
B30: =B29+1 -> 21 | AC30: =(E30*E43)+(F30*F43)+(G30*G43)+(H30*H43)+(I30*I43)+(J30*J43)+(K30*K43)+(L30*L43)+(M30*M43)+(N30*N43)+(O30*O43)+(P30*P43)+(Q30*Q43)+(R30*R43)+(S30*S43)+(T30*T43)+(U30*U43)+(V30*V43)+(W30*W43)+(X30*X43)+(Y30*Y43)+(Z30*Z43)+(AA30*AA43)+(AB30*AB43) -> 0 | AD30: =10%*AC30 -> 0 | AE30: =AC30-AD30 -> 0 | AL30: =AE30/3 -> 0 | AM30: =AL30 -> 0 | AN30: =AM30 -> 0
B31: =B30+1 -> 22 | AC31: =(E31*E43)+(F31*F43)+(G31*G43)+(H31*H43)+(I31*I43)+(J31*J43)+(K31*K43)+(L31*L43)+(M31*M43)+(N31*N43)+(O31*O43)+(P31*P43)+(Q31*Q43)+(R31*R43)+(S31*S43)+(T31*T43)+(U31*U43)+(V31*V43)+(W31*W43)+(X31*X43)+(Y31*Y43)+(Z31*Z43)+(AA31*AA43)+(AB31*AB43) -> 0 | AD31: =10%*AC31 -> 0 | AE31: =AC31-AD31 -> 0 | AL31: =AE31/3 -> 0 | AM31: =AL31 -> 0 | AN31: =AM31 -> 0
B32: =B31+1 -> 23 | AC32: =(E32*E43)+(F32*F43)+(G32*G43)+(H32*H43)+(I32*I43)+(J32*J43)+(K32*J43)+(L32*L43)+(M32*M43)+(N32*N43)+(O32*O43)+(P32*P43)+(Q32*Q43)+(R32*R43)+(S32*S43)+(T32*T43)+(U32*U43)+(V32*V43)+(W32*W43)+(X32*X43)+(Y32*Y43)+(Z32*Z43)+(AA32*AA43)+(AB32*AB43) -> 0 | AD32: =10%*AC32 -> 0 | AE32: =AC32-AD32 -> 0 | AL32: =AE32/3 -> 0 | AM32: =AL32 -> 0 | AN32: =AM32 -> 0
B33: =B32+1 -> 24 | AC33: =(E33*E43)+(F33*F43)+(G33*G43)+(H33*H43)+(I33*I43)+(J33*J43)+(K33*K43)+(L33*L43)+(M33*M43)+(N33*N43)+(O33*O43)+(P33*P43)+(Q33*Q43)+(R33*R43)+(S33*S43)+(T33*T43)+(U33*U43)+(V33*V43)+(W33*W43)+(X33*X43)+(Y33*Y43)+(Z33*Z43)+(AA33*AA43)+(AB33*AB43) -> 0 | AD33: =10%*AC33 -> 0 | AE33: =AC33-AD33 -> 0 | AL33: =AE33/3 -> 0 | AM33: =AL33 -> 0 | AN33: =AM33 -> 0
B34: =B33+1 -> 25 | AC34: =(E34*E43)+(F34*F43)+(G34*G43)+(H34*H43)+(I34*I43)+(J34*J43)+(K34*K43)+(L34*L43)+(M34*M43)+(N34*N43)+(O34*O43)+(P34*P43)+(Q34*Q43)+(R34*R43)+(S34*S43)+(T34*T43)+(U34*U43)+(V34*V43)+(W34*W43)+(X34*X43)+(Y34*Y43)+(Z34*Z43)+(AA34*AA43)+(AB34*AB43) -> 0 | AD34: =10%*AC34 -> 0 | AE34: =AC34-AD34 -> 0 | AL34: =AE34/3 -> 0 | AM34: =AL34 -> 0 | AN34: =AM34 -> 0
B35: =B34+1 -> 26 | AC35: =(E35*E43)+(F35*F43)+(G35*G43)+(H35*H43)+(I35*I43)+(J35*J43)+(K35*K43)+(L35*L43)+(M35*M43)+(N35*N43)+(O35*O43)+(P35*P43)+(Q35*Q43)+(R35*R43)+(S35*S43)+(T35*T43)+(U35*U43)+(V35*V43)+(W35*W43)+(X35*X43)+(Y35*Y43)+(Z35*Z43)+(AA35*AA43)+(AB35*AB43) -> 0 | AD35: =10%*AC35 -> 0 | AE35: =AC35-AD35 -> 0 | AL35: =AE35/3 -> 0 | AM35: =AL35 -> 0 | AN35: =AM35 -> 0
B36: =B35+1 -> 27 | AC36: =(E36*E43)+(F36*F43)+(G36*G43)+(H36*H43)+(I36*I43)+(J36*J43)+(K36*K43)+(L36*L43)+(M36*M43)+(N36*N43)+(O36*O43)+(P36*P43)+(Q36*Q43)+(R36*R43)+(S36*S43)+(T36*T43)+(U36*U43)+(V36*V43)+(W36*W43)+(X36*X43)+(Y36*Y43)+(Z36*Z43)+(AA36*AA43)+(AB36*AB43) -> 0 | AD36: =10%*AC36 -> 0 | AE36: =AC36-AD36 -> 0 | AL36: =AE36/3 -> 0 | AM36: =AL36 -> 0 | AN36: =AM36 -> 0
B37: =B36+1 -> 28 | AC37: =(E37*E43)+(F37*F43)+(G37*G43)+(H37*H43)+(I37*I43)+(J37*J43)+(K37*J43)+(L37*L43)+(M37*M43)+(N37*N43)+(O37*O43)+(P37*P43)+(Q37*Q43)+(R37*R43)+(S37*S43)+(T37*T43)+(U37*U43)+(V37*V43)+(W37*W43)+(X37*X43)+(Y37*Y43)+(Z37*Z43)+(AA37*AA43)+(AB37*AB43) -> 0 | AD37: =10%*AC37 -> 0 | AE37: =AC37-AD37 -> 0 | AL37: =AE37/3 -> 0 | AM37: =AL37 -> 0 | AN37: =AM37 -> 0
B38: =B37+1 -> 29 | AC38: =(E38*E43)+(F38*F43)+(G38*G43)+(H38*H43)+(I38*I43)+(J38*J43)+(K38*K43)+(L38*L43)+(M38*M43)+(N38*N43)+(O38*O43)+(P38*P43)+(Q38*Q43)+(R38*R43)+(S38*S43)+(T38*T43)+(U38*U43)+(V38*V43)+(W38*W43)+(X38*X43)+(Y38*Y43)+(Z38*Z43)+(AA38*AA43)+(AB38*AB43) -> 0 | AD38: =10%*AC38 -> 0 | AE38: =AC38-AD38 -> 0 | AL38: =AE38/3 -> 0 | AM38: =AL38 -> 0 | AN38: =AM38 -> 0
B39: =B38+1 -> 30 | AC39: =(E39*E43)+(F39*F43)+(G39*G43)+(H39*H43)+(I39*I43)+(J39*J43)+(K39*K43)+(L39*L43)+(M39*M43)+(N39*N43)+(O39*O43)+(P39*P43)+(Q39*Q43)+(R39*R43)+(S39*S43)+(T39*T43)+(U39*U43)+(V39*V43)+(W39*W43)+(X39*X43)+(Y39*Y43)+(Z39*Z43)+(AA39*AA43)+(AB39*AB43) -> 0 | AD39: =10%*AC39 -> 0 | AE39: =AC39-AD39 -> 0 | AL39: =AE39/3 -> 0 | AM39: =AL39 -> 0 | AN39: =AM39 -> 0
B40: TOTAL | C40: =COUNTA(C10:C39) -> 0 | E40: =SUM(E10:E39) -> 0 | F40: =SUM(F10:F39) -> 0 | G40: =SUM(G10:G39) -> 0 | H40: =SUM(H10:H39) -> 0 | I40: =SUM(I10:I39) -> 0 | J40: =SUM(J10:J39) -> 0 | K40: =SUM(K10:K39) -> 0 | L40: =SUM(L10:L39) -> 0 | ... AE40: =SUM(AE10:AE39) -> 0 | AL40: =SUM(AL10:AL39) -> 0 | AM40: =SUM(AM10:AM39) -> 0 | AN40: =SUM(AN10:AN39) -> 0 | AO40: =SUM(AO10:AO39) -> 0
C43: Price | E43: 204 | F43: =12*E43 -> 2448 | G43: 177 | H43: =G43*48 -> 8496 | I43: 204 | J43: =I43*12 -> 2448 | K43: 116 | L43: =K43*15 -> 1740 | M43: 116 | N43: =M43*6 -> 696 | O43: 272 | P43: =O43*4 -> 1088 | Q43: 1496 | R43: 272 | S43: =R43*4 -> 1088 | T43: 6800 | U43: 75 | V43: =U43*12 -> 900 | W43: 20 | X43: 68 | Y43: =X43*12 -> 816 | Z43: 1904 | AA43: 122 | AB43: 340

Sheet ADAMSO.
C2: NOTE:
C3: 1. Enter the quantity of agro inputs requested by the farmer either in pcs or boxes under each agro input
C4: 2. Do not change any thing in the excel sheet. The cells are linked
K5: NEW PRICES
C6: REGION: | D6: ASHANTI
C7: DISTRICT: | D7: OBUASI
C8: SOCIETY: | D8: ADAMSO NKABOMKUO
B10: NO. | C10: FARMER NAME | D10: MOBILE NO. | E10: AcetaStar -Adama (1Lt) | G10: Galil | I10: AKATE BRAFO | K10: PHYTOGREEN | M10: BEGREEN | O10: Agyenkwa Liquid Fertilizer (5Lt) | Q10: Matabi (15Lt) | R10: PLANTFEED | T10: Solo Machine | U10: All Wedicides (Glyphosate) | W10: NODOX | X10: ALL GRAMO | Z10: STANDARD PRUNNER | AA10: WELLINGTON BOOT | AB10: OVERALL | AC10: TOTAL AMOUNT (GHc) | AD10: DEPOSIT PAID (GHc) | AE10: OUTS. BALANCE (GHc) | AF10: REPAYMENT PLAN(GHC)
E11: PCs | F11: Box (12pcs) | G11: PCs | H11: Box | I11: PCs | J11: Box | K11: 1LT | L11: BOX(15) | M11: 1GALLON | N11: BOX(6) | O11: PCs | P11: Box(4) | Q11: PCs | R11: 1 GALLON | S11: BOX(4) | T11: PCs | U11: PCS | V11: BOX(12) | W11: PCs | X11: PCS | Y11: BOX(12) | Z11: PC | AA11: PC | AB11: PC | AF11: OCT | AG11: NOV | AH11: DEC | AL11: OCT | AM11: NOV | AN11: DEC | AO11: TOTAL PAYMENT
B12: 1 | C12: MUHAMADU HARUNA | D12: 0597386565 | T12: 1 | AC12: =(E12*E45)+(F12*F45)+(G12*G45)+(H12*H45)+(I12*I45)+(J12*J45)+(K12*K45)+(L12*L45)+(M12*M45)+(N12*N45)+(O12*O45)+(P12*P45)+(Q12*Q45)+(R12*R45)+(S12*S45)+(T12*T45)+(U12*U45)+(V12*V45)+(W12*W45)+(X12*X45)+(Y12*Y45)+(Z12*Z45)+(AA12*AA45)+(AB12*AB45) -> 6800 | AD12: =10%*AC12 -> 680 | AE12: =AC12-AD12 -> 6120 | AL12: =AE12/3 -> 2040 | AM12: =AL12 -> 2040 | AN12: =AM12 -> 2040 | AO12: =AD12+AF12+AG12+AH12+AI12+AJ12+AK12 -> 680
B13: =B12+1 -> 2 | C13: ASARE DEDE | F13: 4 | L13: 4 | AC13: =(E13*E45)+(F13*F45)+(G13*G45)+(H13*H45)+(I13*I45)+(J13*J45)+(K13*K45)+(L13*L45)+(M13*M45)+(N13*N45)+(O13*O45)+(P13*P45)+(Q13*Q45)+(R13*R45)+(S13*S45)+(T13*T45)+(U13*U45)+(V13*V45)+(W13*W45)+(X13*X45)+(Y13*Y45)+(Z13*Z45)+(AA13*AA45)+(AB13*AB45) -> 20412 | AD13: =10%*AC13 -> 2041.2 | AE13: =AC13-AD13 -> 18370.8 | AL13: =AE13/3 -> 6123.6 | AM13: =AL13 -> 6123.6 | AN13: =AM13 -> 6123.6 | AO13: =AD13+AF13+AG13+AH13+AI13+AJ13+AK13 -> 2041.2
B14: =B13+1 -> 3 | C14: ODURO MANSA | E14: 6 | I14: 6 | T14: 1 | AC14: =(E14*E45)+(F14*F45)+(G14*G45)+(H14*H45)+(I14*I45)+(J14*J45)+(K14*K45)+(L14*L45)+(M14*M45)+(N14*N45)+(O14*O45)+(P14*P45)+(Q14*Q45)+(R14*R45)+(S14*S45)+(T14*T45)+(U14*U45)+(V14*V45)+(W14*W45)+(X14*X45)+(Y14*Y45)+(Z14*Z45)+(AA14*AA45)+(AB14*AB45) -> 9248 | AD14: =10%*AC14 -> 924.8 | AE14: =AC14-AD14 -> 8323.2 | AL14: =AE14/3 -> 2774.4 | AM14: =AL14 -> 2774.4 | AN14: =AM14 -> 2774.4 | AO14: =AD14+AF14+AG14+AH14+AI14+AJ14+AK14 -> 924.8
B15: =B14+1 -> 4 | C15: AMOAH WIREDU AKWASI | D15: 0242950282 | E15: 6 | I15: 6 | Y15: 1 | AC15: =(E15*E45)+(F15*F45)+(G15*G45)+(H15*H45)+(I15*I45)+(J15*J45)+(K15*K45)+(L15*L45)+(M15*M45)+(N15*N45)+(O15*O45)+(P15*P45)+(Q15*Q45)+(R15*R45)+(S15*S45)+(T15*T45)+(U15*U45)+(V15*V45)+(W15*W45)+(X15*X45)+(Y15*Y45)+(Z15*Z45)+(AA15*AA45)+(AB15*AB45) -> 3264 | AD15: =10%*AC15 -> 326.4 | AE15: =AC15-AD15 -> 2937.6 | AL15: =AE15/3 -> 979.2 | AM15: =AL15 -> 979.2 | AN15: =AM15 -> 979.2 | AO15: =AD15+AF15+AG15+AH15+AI15+AJ15+AK15 -> 326.4
B16: =B15+1 -> 5 | C16: OSMANU SULE | D16: 0531955660 | V16: 2 | AC16: =(E16*E45)+(F16*F45)+(G16*G45)+(H16*H45)+(I16*I45)+(J16*J49)+(K16*K45)+(L16*L45)+(M16*M45)+(N16*N45)+(O16*O45)+(P16*P45)+(Q16*Q45)+(R16*R45)+(S16*S45)+(T16*T45)+(U16*U45)+(V16*V45)+(W16*W45)+(X16*X45)+(Y16*Y45)+(Z16*Z45)+(AA16*AA45)+(AB16*AB45) -> 1800 | AD16: =10%*AC16 -> 180 | AE16: =AC16-AD16 -> 1620 | AL16: =AE16/3 -> 540 | AM16: =AL16 -> 540 | AN16: =AM16 -> 540 | AO16: =AD16+AF16+AG16+AH16+AI16+AJ16+AK16 -> 180
B17: =B16+1 -> 6 | C17: KWAKYE PHILIMON SANDYS | E17: 6 | I17: 6 | AC17: =(E17*E45)+(F17*F45)+(G17*G45)+(H17*H45)+(I17*I45)+(J17*J45)+(K17*K45)+(L17*L45)+(M17*M45)+(N17*N45)+(O17*O45)+(P17*P45)+(Q17*Q45)+(R17*R45)+(S17*S45)+(T17*T45)+(U17*U45)+(V17*V45)+(W17*W45)+(X17*X45)+(Y17*Y45)+(Z17*Z45)+(AA17*AA45)+(AB17*AB45) -> 2448 | AD17: =10%*AC17 -> 244.8 | AE17: =AC17-AD17 -> 2203.2 | AL17: =AE17/3 -> 734.4 | AM17: =AL17 -> 734.4 | AN17: =AM17 -> 734.4 | AO17: =AD17+AF17+AG17+AH17+AI17+AJ17+AK17 -> 244.8
B18: =B17+1 -> 7 | C18: NIMO JOSEPH BRUCE | U18: 6 | AC18: =(E18*E45)+(F18*F45)+(G18*G45)+(H18*H45)+(I18*I45)+(J18*J45)+(K18*K45)+(L18*L45)+(M18*M45)+(N18*N45)+(O18*O45)+(P18*P45)+(Q18*Q45)+(R18*R45)+(S18*S45)+(T18*T45)+(U18*U45)+(V18*V45)+(W18*W45)+(X18*X45)+(Y18*Y45)+(Z18*Z45)+(AA18*AA45)+(AB18*AB45) -> 450 | AD18: =10%*AC18 -> 45 | AE18: =AC18-AD18 -> 405 | AL18: =AE18/3 -> 135 | AM18: =AL18 -> 135 | AN18: =AM18 -> 135 | AO18: =AD18+AF18+AG18+AH18+AI18+AJ18+AK18 -> 45
B19: =B18+1 -> 8 | C19: ASAMOAH GEORGINA | D19: 0592837722 | E19: 4 | AC19: =(E19*E45)+(F19*F45)+(G19*G45)+(H19*H45)+(I19*I45)+(J19*J45)+(K19*K45)+(L19*L45)+(M19*M45)+(N19*N45)+(O19*O45)+(P19*P45)+(Q19*Q45)+(R19*R45)+(S19*S45)+(T19*T45)+(U19*U45)+(V19*V45)+(W19*W45)+(X19*X45)+(Y19*Y45)+(Z19*Z45)+(AA19*AA45)+(AB19*AB45) -> 816 | AD19: =10%*AC19 -> 81.6 | AE19: =AC19-AD19 -> 734.4 | AL19: =AE19/3 -> 244.8 | AM19: =AL19 -> 244.8 | AN19: =AM19 -> 244.8 | AO19: =AD19+AF19+AG19+AH19+AI19+AJ19+AK19 -> 81.6
B20: =B19+1 -> 9 | C20: OPPPONG EDWARD | D20: 0559505845 | F20: 1 | J20: 1 | V20: 1 | AC20: =(E20*E45)+(F20*F45)+(G20*G45)+(H20*H45)+(I20*I45)+(J20*J45)+(K20*K45)+(L20*L45)+(M20*M45)+(N20*N45)+(O20*O45)+(P20*P45)+(Q20*Q45)+(R20*R45)+(S20*S45)+(T20*T45)+(U20*U45)+(V20*V45)+(W20*W45)+(X20*X45)+(Y20*Y45)+(Z20*Z45)+(AA20*AA45)+(AB20*AB45) -> 3688 | AD20: =10%*AC20 -> 368.8 | AE20: =AC20-AD20 -> 3319.2 | AL20: =AE20/3 -> 1106.4 | AM20: =AL20 -> 1106.4 | AN20: =AM20 -> 1106.4 | AO20: =AD20+AF20+AG20+AH20+AI20+AJ20+AK20 -> 368.8
B21: =B20+1 -> 10 | C21: AMANKWAH ERNEST | T21: 1 | AC21: =(E21*E45)+(F21*F45)+(G21*G45)+(H21*H45)+(I21*I45)+(J21*J45)+(K21*K45)+(L21*L45)+(M21*M45)+(N21*N45)+(O21*O45)+(P21*P45)+(Q21*Q45)+(R21*R45)+(S21*S45)+(T21*T45)+(U21*U45)+(V21*V45)+(W21*W45)+(X21*X45)+(Y21*Y45)+(Z21*Z45)+(AA21*AA45)+(AB21*AB45) -> 6800 | AD21: =10%*AC21 -> 680 | AE21: =AC21-AD21 -> 6120 | AL21: =AE21/3 -> 2040 | AM21: =AL21 -> 2040 | AN21: =AM21 -> 2040 | AO21: =AD21+AF21+AG21+AH21+AI21+AJ21+AK21 -> 680
B22: =B21+1 -> 11 | C22: CUDJOE EMMANUEL | T22: 1 | AC22: =(E22*E45)+(F22*F45)+(G22*G45)+(H22*H45)+(I22*I45)+(J22*J45)+(K22*K45)+(L22*L45)+(M22*M45)+(N22*N45)+(O22*O45)+(P22*P45)+(Q22*Q45)+(R22*R45)+(S22*S45)+(T22*T45)+(U22*U45)+(V22*V45)+(W22*W45)+(X22*X45)+(Y22*Y45)+(Z22*Z45)+(AA22*AA45)+(AB22*AB45) -> 6800 | AD22: =10%*AC22 -> 680 | AE22: =AC22-AD22 -> 6120 | AL22: =AE22/3 -> 2040 | AM22: =AL22 -> 2040 | AN22: =AM22 -> 2040 | AO22: =AD22+AF22+AG22+AH22+AI22+AJ22+AK22 -> 680
B23: =B22+1 -> 12 | C23: BENFO KWASI | T23: 1 | AC23: =(E23*E45)+(F23*F45)+(G23*G45)+(H23*H45)+(I23*I45)+(J23*J45)+(K23*K45)+(L23*L45)+(M23*M45)+(N23*N45)+(O23*O45)+(P23*P45)+(Q23*Q45)+(R23*R45)+(S23*S45)+(T23*T45)+(U23*U45)+(V23*V45)+(W23*W45)+(X23*X45)+(Y23*Y45)+(Z23*Z45)+(AA23*AA45)+(AB23*AB45) -> 6800 | AD23: =10%*AC23 -> 680 | AE23: =AC23-AD23 -> 6120 | AL23: =AE23/3 -> 2040 | AM23: =AL23 -> 2040 | AN23: =AM23 -> 2040 | AO23: =AD23+AF23+AG23+AH23+AI23+AJ23+AK23 -> 680
B24: =B23+1 -> 13 | AC24: =(E24*E45)+(F24*F45)+(G24*G45)+(H24*H45)+(I24*I45)+(J24*J45)+(K24*J45)+(L24*L45)+(M24*M45)+(N24*N45)+(O24*O45)+(P24*P45)+(Q24*Q45)+(R24*R45)+(S24*S45)+(T24*T45)+(U24*U45)+(V24*V45)+(W24*W45)+(X24*X45)+(Y24*Y45)+(Z24*Z45)+(AA24*AA45)+(AB24*AB45) -> 0 | AD24: =10%*AC24 -> 0 | AE24: =AC24-AD24 -> 0 | AL24: =AE24/3 -> 0 | AM24: =AL24 -> 0 | AN24: =AM24 -> 0 | AO24: =AD24+AF24+AG24+AH24+AI24+AJ24+AK24 -> 0
B25: =B24+1 -> 14 | AC25: =(E25*E45)+(F25*F45)+(G25*G45)+(H25*H45)+(I25*I45)+(J25*J45)+(K25*K45)+(L25*L45)+(M25*M45)+(N25*N45)+(O25*O45)+(P25*P45)+(Q25*Q45)+(R25*R45)+(S25*S45)+(T25*T45)+(U25*U45)+(V25*V45)+(W25*W45)+(X25*X45)+(Y25*Y45)+(Z25*Z45)+(AA25*AA45)+(AB25*AB45) -> 0 | AD25: =10%*AC25 -> 0 | AE25: =AC25-AD25 -> 0 | AL25: =AE25/3 -> 0 | AM25: =AL25 -> 0 | AN25: =AM25 -> 0 | AO25: =AD25+AF25+AG25+AH25+AI25+AJ25+AK25 -> 0
B26: =B25+1 -> 15 | AC26: =(E26*E45)+(F26*F45)+(G26*G45)+(H26*H45)+(I26*I45)+(J26*J45)+(K26*K45)+(L26*L45)+(M26*M45)+(N26*N45)+(O26*O45)+(P26*P45)+(Q26*Q45)+(R26*R45)+(S26*S45)+(T26*T45)+(U26*U45)+(V26*V45)+(W26*W45)+(X26*X45)+(Y26*Y45)+(Z26*Z45)+(AA26*AA45)+(AB26*AB45) -> 0 | AD26: =10%*AC26 -> 0 | AE26: =AC26-AD26 -> 0 | AL26: =AE26/3 -> 0 | AM26: =AL26 -> 0 | AN26: =AM26 -> 0 | AO26: =AD26+AF26+AG26+AH26+AI26+AJ26+AK26 -> 0
B27: =B26+1 -> 16 | AC27: =(E27*E45)+(F27*F45)+(G27*G45)+(H27*H45)+(I27*I45)+(J27*J45)+(K27*J45)+(L27*L45)+(M27*M45)+(N27*N45)+(O27*O45)+(P27*P45)+(Q27*Q45)+(R27*R45)+(S27*S45)+(T27*T45)+(U27*U45)+(V27*V45)+(W27*W45)+(X27*X45)+(Y27*Y45)+(Z27*Z45)+(AA27*AA45)+(AB27*AB45) -> 0 | AD27: =10%*AC27 -> 0 | AE27: =AC27-AD27 -> 0 | AL27: =AE27/3 -> 0 | AM27: =AL27 -> 0 | AN27: =AM27 -> 0 | AO27: =AD27+AF27+AG27+AH27+AI27+AJ27+AK27 -> 0
B28: =B27+1 -> 17 | AC28: =(E28*E45)+(F28*F45)+(G28*G45)+(H28*H45)+(I28*I45)+(J28*J45)+(K28*K45)+(L28*L45)+(M28*M45)+(N28*N45)+(O28*O45)+(P28*P45)+(Q28*Q45)+(R28*R45)+(S28*S45)+(T28*T45)+(U28*U45)+(V28*V45)+(W28*W45)+(X28*X45)+(Y28*Y45)+(Z28*Z45)+(AA28*AA45)+(AB28*AB45) -> 0 | AD28: =10%*AC28 -> 0 | AE28: =AC28-AD28 -> 0 | AL28: =AE28/3 -> 0 | AM28: =AL28 -> 0 | AN28: =AM28 -> 0 | AO28: =AD28+AF28+AG28+AH28+AI28+AJ28+AK28 -> 0
B29: =B28+1 -> 18 | AC29: =(E29*E45)+(F29*F45)+(G29*G45)+(H29*H45)+(I29*I45)+(J29*J45)+(K29*K45)+(L29*L45)+(M29*M45)+(N29*N45)+(O29*O45)+(P29*P45)+(Q29*Q45)+(R29*R45)+(S29*S45)+(T29*T45)+(U29*U45)+(V29*V45)+(W29*W45)+(X29*X45)+(Y29*Y45)+(Z29*Z45)+(AA29*AA45)+(AB29*AB45) -> 0 | AD29: =10%*AC29 -> 0 | AE29: =AC29-AD29 -> 0 | AL29: =AE29/3 -> 0 | AM29: =AL29 -> 0 | AN29: =AM29 -> 0 | AO29: =AD29+AF29+AG29+AH29+AI29+AJ29+AK29 -> 0
B30: =B29+1 -> 19 | AC30: =(E30*E45)+(F30*F45)+(G30*G45)+(H30*H45)+(I30*I45)+(J30*J45)+(K30*J45)+(L30*L45)+(M30*M45)+(N30*N45)+(O30*O45)+(P30*P45)+(Q30*Q45)+(R30*R45)+(S30*S45)+(T30*T45)+(U30*U45)+(V30*V45)+(W30*W45)+(X30*X45)+(Y30*Y45)+(Z30*Z45)+(AA30*AA45)+(AB30*AB45) -> 0 | AD30: =10%*AC30 -> 0 | AE30: =AC30-AD30 -> 0 | AL30: =AE30/3 -> 0 | AM30: =AL30 -> 0 | AN30: =AM30 -> 0 | AO30: =AD30+AF30+AG30+AH30+AI30+AJ30+AK30 -> 0
B31: =B30+1 -> 20 | AC31: =(E31*E45)+(F31*F45)+(G31*G45)+(H31*H45)+(I31*I45)+(J31*J45)+(K31*K45)+(L31*L45)+(M31*M45)+(N31*N45)+(O31*O45)+(P31*P45)+(Q31*Q45)+(R31*R45)+(S31*S45)+(T31*T45)+(U31*U45)+(V31*V45)+(W31*W45)+(X31*X45)+(Y31*Y45)+(Z31*Z45)+(AA31*AA45)+(AB31*AB45) -> 0 | AD31: =10%*AC31 -> 0 | AE31: =AC31-AD31 -> 0 | AL31: =AE31/3 -> 0 | AM31: =AL31 -> 0 | AN31: =AM31 -> 0 | AO31: =AD31+AF31+AG31+AH31+AI31+AJ31+AK31 -> 0
B32: =B31+1 -> 21 | AC32: =(E32*E45)+(F32*F45)+(G32*G45)+(H32*H45)+(I32*I45)+(J32*J45)+(K32*K45)+(L32*L45)+(M32*M45)+(N32*N45)+(O32*O45)+(P32*P45)+(Q32*Q45)+(R32*R45)+(S32*S45)+(T32*T45)+(U32*U45)+(V32*V45)+(W32*W45)+(X32*X45)+(Y32*Y45)+(Z32*Z45)+(AA32*AA45)+(AB32*AB45) -> 0 | AD32: =10%*AC32 -> 0 | AE32: =AC32-AD32 -> 0 | AL32: =AE32/3 -> 0 | AM32: =AL32 -> 0 | AN32: =AM32 -> 0 | AO32: =AD32+AF32+AG32+AH32+AI32+AJ32+AK32 -> 0
B33: =B32+1 -> 22 | AC33: =(E33*E46)+(F33*F46)+(G33*G46)+(H33*H46)+(I33*I46)+(J33*J46)+(K33*K46)+(L33*L46)+(M33*M46)+(N33*N46)+(O33*O46)+(P33*P46)+(Q33*Q46)+(R33*R46)+(S33*S46)+(T33*T46)+(U33*U46)+(V33*V46)+(W33*W46)+(X33*X46)+(Y33*Y46)+(Z33*Z46)+(AA33*AA46)+(AB33*AB46) -> 0 | AD33: =10%*AC33 -> 0 | AE33: =AC33-AD33 -> 0 | AL33: =AE33/3 -> 0 | AM33: =AL33 -> 0 | AN33: =AM33 -> 0 | AO33: =AD33+AF33+AG33+AH33+AI33+AJ33+AK33 -> 0
B34: =B33+1 -> 23 | AC34: =(E34*E47)+(F34*F47)+(G34*G47)+(H34*H47)+(I34*I47)+(J34*J47)+(K34*K47)+(L34*L47)+(M34*M47)+(N34*N47)+(O34*O47)+(P34*P47)+(Q34*Q47)+(R34*R47)+(S34*S47)+(T34*T47)+(U34*U47)+(V34*V47)+(W34*W47)+(X34*X47)+(Y34*Y47)+(Z34*Z47)+(AA34*AA47)+(AB34*AB47) -> 0 | AD34: =10%*AC34 -> 0 | AE34: =AC34-AD34 -> 0 | AL34: =AE34/3 -> 0 | AM34: =AL34 -> 0 | AN34: =AM34 -> 0 | AO34: =AD34+AF34+AG34+AH34+AI34+AJ34+AK34 -> 0
B35: =B34+1 -> 24 | AC35: =(E35*E48)+(F35*F48)+(G35*G48)+(H35*H48)+(I35*I48)+(J35*J48)+(K35*K48)+(L35*L48)+(M35*M48)+(N35*N48)+(O35*O48)+(P35*P48)+(Q35*Q48)+(R35*R48)+(S35*S48)+(T35*T48)+(U35*U48)+(V35*V48)+(W35*W48)+(X35*X48)+(Y35*Y48)+(Z35*Z48)+(AA35*AA48)+(AB35*AB48) -> 0 | AD35: =10%*AC35 -> 0 | AE35: =AC35-AD35 -> 0 | AL35: =AE35/3 -> 0 | AM35: =AL35 -> 0 | AN35: =AM35 -> 0 | AO35: =AD35+AF35+AG35+AH35+AI35+AJ35+AK35 -> 0
B36: =B35+1 -> 25 | AC36: =(E36*E49)+(F36*F49)+(G36*G49)+(H36*H49)+(I36*I49)+(J36*J49)+(K36*K49)+(L36*L49)+(M36*M49)+(N36*N49)+(O36*O49)+(P36*P49)+(Q36*Q49)+(R36*R49)+(S36*S49)+(T36*T49)+(U36*U49)+(V36*V49)+(W36*W49)+(X36*X49)+(Y36*Y49)+(Z36*Z49)+(AA36*AA49)+(AB36*AB49) -> 0 | AD36: =10%*AC36 -> 0 | AE36: =AC36-AD36 -> 0 | AL36: =AE36/3 -> 0 | AM36: =AL36 -> 0 | AN36: =AM36 -> 0
B37: =B36+1 -> 26 | AC37: =(E37*E50)+(F37*F50)+(G37*G50)+(H37*H50)+(I37*I50)+(J37*J50)+(K37*K50)+(L37*L50)+(M37*M50)+(N37*N50)+(O37*O50)+(P37*P50)+(Q37*Q50)+(R37*R50)+(S37*S50)+(T37*T50)+(U37*U50)+(V37*V50)+(W37*W50)+(X37*X50)+(Y37*Y50)+(Z37*Z50)+(AA37*AA50)+(AB37*AB50) -> 0 | AD37: =10%*AC37 -> 0 | AE37: =AC37-AD37 -> 0 | AL37: =AE37/3 -> 0 | AM37: =AL37 -> 0 | AN37: =AM37 -> 0
B38: =B37+1 -> 27 | AC38: =(E38*E51)+(F38*F51)+(G38*G51)+(H38*H51)+(I38*I51)+(J38*J51)+(K38*K51)+(L38*L51)+(M38*M51)+(N38*N51)+(O38*O51)+(P38*P51)+(Q38*Q51)+(R38*R51)+(S38*S51)+(T38*T51)+(U38*U51)+(V38*V51)+(W38*W51)+(X38*X51)+(Y38*Y51)+(Z38*Z51)+(AA38*AA51)+(AB38*AB51) -> 0 | AD38: =10%*AC38 -> 0 | AE38: =AC38-AD38 -> 0 | AL38: =AE38/3 -> 0 | AM38: =AL38 -> 0 | AN38: =AM38 -> 0
B39: =B38+1 -> 28 | AC39: =(E39*E52)+(F39*F52)+(G39*G52)+(H39*H52)+(I39*I52)+(J39*J52)+(K39*K52)+(L39*L52)+(M39*M52)+(N39*N52)+(O39*O52)+(P39*P52)+(Q39*Q52)+(R39*R52)+(S39*S52)+(T39*T52)+(U39*U52)+(V39*V52)+(W39*W52)+(X39*X52)+(Y39*Y52)+(Z39*Z52)+(AA39*AA52)+(AB39*AB52) -> 0 | AD39: =10%*AC39 -> 0 | AE39: =AC39-AD39 -> 0 | AL39: =AE39/3 -> 0 | AM39: =AL39 -> 0 | AN39: =AM39 -> 0
B40: =B39+1 -> 29 | AC40: =(E40*E53)+(F40*F53)+(G40*G53)+(H40*H53)+(I40*I53)+(J40*J53)+(K40*K53)+(L40*L53)+(M40*M53)+(N40*N53)+(O40*O53)+(P40*P53)+(Q40*Q53)+(R40*R53)+(S40*S53)+(T40*T53)+(U40*U53)+(V40*V53)+(W40*W53)+(X40*X53)+(Y40*Y53)+(Z40*Z53)+(AA40*AA53)+(AB40*AB53) -> 0 | AD40: =10%*AC40 -> 0 | AE40: =AC40-AD40 -> 0 | AL40: =AE40/3 -> 0 | AM40: =AL40 -> 0 | AN40: =AM40 -> 0
B41: =B40+1 -> 30 | AC41: =(E41*E54)+(F41*F54)+(G41*G54)+(H41*H54)+(I41*I54)+(J41*J54)+(K41*K54)+(L41*L54)+(M41*M54)+(N41*N54)+(O41*O54)+(P41*P54)+(Q41*Q54)+(R41*R54)+(S41*S54)+(T41*T54)+(U41*U54)+(V41*V54)+(W41*W54)+(X41*X54)+(Y41*Y54)+(Z41*Z54)+(AA41*AA54)+(AB41*AB54) -> 0 | AD41: =10%*AC41 -> 0 | AE41: =AC41-AD41 -> 0 | AL41: =AE41/3 -> 0 | AM41: =AL41 -> 0 | AN41: =AM41 -> 0
B42: TOTAL | C42: =COUNTA(C12:C41) -> 12 | E42: =SUM(E12:E41) -> 22 | F42: =SUM(F12:F41) -> 5 | G42: =SUM(G12:G41) -> 0 | H42: =SUM(H12:H41) -> 0 | I42: =SUM(I12:I41) -> 18 | J42: =SUM(J12:J41) -> 1 | K42: =SUM(K12:K41) -> 0 | L42: =SUM(L12:L41) -> 4 | ... AJ42: =SUM(AJ12:AJ41) -> 0 | AL42: =SUM(AL12:AL41) -> 20797.8 | AM42: =SUM(AM12:AM41) -> 20797.8 | AN42: =SUM(AN12:AN41) -> 20797.8 | AO42: =SUM(AO12:AO41) -> 6932.6
C45: Price | E45: 204 | F45: =12*E45 -> 2448 | G45: 177 | H45: =G45*48 -> 8496 | I45: 204 | J45: 340 | K45: 177 | L45: =K45*15 -> 2655 | M45: 116 | N45: =M45*6 -> 696 | O45: 272 | P45: =O45*4 -> 1088 | Q45: 1496 | R45: 272 | S45: =R45*4 -> 1088 | T45: 6800 | U45: 75 | V45: =U45*12 -> 900 | W45: 20 | X45: 68 | Y45: =X45*12 -> 816 | Z45: 1904 | AA45: 122 | AB45: 340

Sheet 13
C2: NOTE:
C3: 1. Enter the quantity of agro inputs requested by the farmer either in pcs or boxes under each agro input
C4: 2. Do not change any thing in the excel sheet. The cells are linked
K5: NEW PRICES
C6: REGION: | D6: ASHANTI
C7: DISTRICT: | D7: TEPA
C8: SOCIETY: | D8: KRAMOKROM
B9: NO. | C9: FARMER NAME | D9: MOBILE NO. | E9: AcetaStar -Adama (1Lt) | G9: Galil | I9: AKATE BRAFO | K9: PHYTOGREEN | M9: BEGREEN | O9: Agyenkwa Liquid Fertilizer (5Lt) | Q9: Matabi (15Lt) | R9: PLANTFEED | T9: Solo Machine | U9: All Wedicides (Glyphosate) | W9: NODOX | X9: ALL GRAMO | Z9: STANDARD PRUNNER | AA9: WELLINGTON BOOT | AB9: OVERALL | AC9: TOTAL AMOUNT (GHc) | AD9: DEPOSIT PAID (GHc) | AE9: OUTS. BALANCE (GHc) | AF9: REPAYMENT PLAN(GHC)
E10: PCs | F10: Box (12pcs) | G10: PCs | H10: Box | I10: PCs | J10: Box | K10: 1LT | L10: BOX(15) | M10: 1GALLON | N10: BOX(6) | O10: PCs | P10: Box(4) | Q10: PCs | R10: 1 GALLON | S10: BOX(4) | T10: PCs | U10: PCS | V10: BOX(12) | W10: PCs | X10: PCS | Y10: BOX(12) | Z10: PC | AA10: PC | AB10: PC | AF10: OCT | AG10: NOV | AH10: DEC | AL10: OCT | AM10: NOV | AN10: DEC | AO10: TOTAL PAYMENT
B11: =B10+1 -> 1 | AC11: =(E11*E45)+(F11*F45)+(G11*G45)+(H11*H45)+(I11*I45)+(J11*J45)+(K11*K45)+(L11*L45)+(M11*M45)+(N11*N45)+(O11*O45)+(P11*P45)+(Q11*Q45)+(R11*R45)+(S11*S45)+(T11*T45)+(U11*U45)+(V11*V45)+(W11*W45)+(X11*X45)+(Y11*Y45)+(Z11*Z45)+(AA11*AA45)+(AB11*AB45) -> 0 | AD11: =10%*AC11 -> 0 | AE11: =AC11-AD11 -> 0 | AL11: =AE11/3 -> 0 | AM11: =AL11 -> 0 | AN11: =AM11 -> 0 | AO11: =AD11+AF11+AG11+AH11+AI11+AJ11+AK11 -> 0
B12: =B11+1 -> 2 | AC12: =(E12*E45)+(F12*F45)+(G12*G45)+(H12*H45)+(I12*I45)+(J12*J45)+(K12*K45)+(L12*L45)+(M12*M45)+(N12*N45)+(O12*O45)+(P12*P45)+(Q12*Q45)+(R12*R45)+(S12*S45)+(T12*T45)+(U12*U45)+(V12*V45)+(W12*W45)+(X12*X45)+(Y12*Y45)+(Z12*Z45)+(AA12*AA45)+(AB12*AB45) -> 0 | AD12: =10%*AC12 -> 0 | AE12: =AC12-AD12 -> 0 | AL12: =AE12/3 -> 0 | AM12: =AL12 -> 0 | AN12: =AM12 -> 0 | AO12: =AD12+AF12+AG12+AH12+AI12+AJ12+AK12 -> 0
B13: =B12+1 -> 3 | AC13: =(E13*E45)+(F13*F45)+(G13*G45)+(H13*H45)+(I13*I45)+(J13*J45)+(K13*K45)+(L13*L45)+(M13*M45)+(N13*N45)+(O13*O45)+(P13*P45)+(Q13*Q45)+(R13*R45)+(S13*S45)+(T13*T45)+(U13*U45)+(V13*V45)+(W13*W45)+(X13*X45)+(Y13*Y45)+(Z13*Z45)+(AA13*AA45)+(AB13*AB45) -> 0 | AD13: =10%*AC13 -> 0 | AE13: =AC13-AD13 -> 0 | AL13: =AE13/3 -> 0 | AM13: =AL13 -> 0 | AN13: =AM13 -> 0 | AO13: =AD13+AF13+AG13+AH13+AI13+AJ13+AK13 -> 0
B14: =B13+1 -> 4 | AC14: =(E14*E45)+(F14*F45)+(G14*G45)+(H14*H45)+(I14*I45)+(J14*J45)+(K14*K45)+(L14*L45)+(M14*M45)+(N14*N45)+(O14*O45)+(P14*P45)+(Q14*Q45)+(R14*R45)+(S14*S45)+(T14*T45)+(U14*U45)+(V14*V45)+(W14*W45)+(X14*X45)+(Y14*Y45)+(Z14*Z45)+(AA14*AA45)+(AB14*AB45) -> 0 | AD14: =10%*AC14 -> 0 | AE14: =AC14-AD14 -> 0 | AL14: =AE14/3 -> 0 | AM14: =AL14 -> 0 | AN14: =AM14 -> 0 | AO14: =AD14+AF14+AG14+AH14+AI14+AJ14+AK14 -> 0
B15: =B14+1 -> 5 | AC15: =(E15*E45)+(F15*F45)+(G15*G45)+(H15*H45)+(I15*I45)+(J15*J45)+(K15*K45)+(L15*L45)+(M15*M45)+(N15*N45)+(O15*O45)+(P15*P45)+(Q15*Q45)+(R15*R45)+(S15*S45)+(T15*T45)+(U15*U45)+(V15*V45)+(W15*W45)+(X15*X45)+(Y15*Y45)+(Z15*Z45)+(AA15*AA45)+(AB15*AB45) -> 0 | AD15: =10%*AC15 -> 0 | AE15: =AC15-AD15 -> 0 | AL15: =AE15/3 -> 0 | AM15: =AL15 -> 0 | AN15: =AM15 -> 0 | AO15: =AD15+AF15+AG15+AH15+AI15+AJ15+AK15 -> 0
B16: =B15+1 -> 6 | AC16: =(E16*E45)+(F16*F45)+(G16*G45)+(H16*H45)+(I16*I45)+(J16*J49)+(K16*K45)+(L16*L45)+(M16*M45)+(N16*N45)+(O16*O45)+(P16*P45)+(Q16*Q45)+(R16*R45)+(S16*S45)+(T16*T45)+(U16*U45)+(V16*V45)+(W16*W45)+(X16*X45)+(Y16*Y45)+(Z16*Z45)+(AA16*AA45)+(AB16*AB45) -> 0 | AD16: =10%*AC16 -> 0 | AE16: =AC16-AD16 -> 0 | AL16: =AE16/3 -> 0 | AM16: =AL16 -> 0 | AN16: =AM16 -> 0 | AO16: =AD16+AF16+AG16+AH16+AI16+AJ16+AK16 -> 0
B17: =B16+1 -> 7 | AC17: =(E17*E45)+(F17*F45)+(G17*G45)+(H17*H45)+(I17*I45)+(J17*J45)+(K17*K45)+(L17*L45)+(M17*M45)+(N17*N45)+(O17*O45)+(P17*P45)+(Q17*Q45)+(R17*R45)+(S17*S45)+(T17*T45)+(U17*U45)+(V17*V45)+(W17*W45)+(X17*X45)+(Y17*Y45)+(Z17*Z45)+(AA17*AA45)+(AB17*AB45) -> 0 | AD17: =10%*AC17 -> 0 | AE17: =AC17-AO17 -> 0 | AL17: =AE17/3 -> 0 | AM17: =AL17 -> 0 | AN17: =AM17 -> 0 | AO17: =AD17+AF17+AG17+AH17+AI17+AJ17+AK17 -> 0
B18: =B17+1 -> 8 | AC18: =(E18*E45)+(F18*F45)+(G18*G45)+(H18*H45)+(I18*I45)+(J18*J45)+(K18*K45)+(L18*L45)+(M18*M45)+(N18*N45)+(O18*O45)+(P18*P45)+(Q18*Q45)+(R18*R45)+(S18*S45)+(T18*T45)+(U18*U45)+(V18*V45)+(W18*W45)+(X18*X45)+(Y18*Y45)+(Z18*Z45)+(AA18*AA45)+(AB18*AB45) -> 0 | AD18: =10%*AC18 -> 0 | AE18: =AC18-AD18 -> 0 | AL18: =AE18/3 -> 0 | AM18: =AL18 -> 0 | AN18: =AM18 -> 0 | AO18: =AD18+AF18+AG18+AH18+AI18+AJ18+AK18 -> 0
B19: =B18+1 -> 9 | AC19: =(E19*E45)+(F19*F45)+(G19*G45)+(H19*H45)+(I19*I45)+(J19*J45)+(K19*K45)+(L19*L45)+(M19*M45)+(N19*N45)+(O19*O45)+(P19*P45)+(Q19*Q45)+(R19*R45)+(S19*S45)+(T19*T45)+(U19*U45)+(V19*V45)+(W19*W45)+(X19*X45)+(Y19*Y45)+(Z19*Z45)+(AA19*AA45)+(AB19*AB45) -> 0 | AD19: =10%*AC19 -> 0 | AE19: =AC19-AD19 -> 0 | AL19: =AE19/3 -> 0 | AM19: =AL19 -> 0 | AN19: =AM19 -> 0 | AO19: =AD19+AF19+AG19+AH19+AI19+AJ19+AK19 -> 0
B20: =B19+1 -> 10 | AC20: =(E20*E45)+(F20*F45)+(G20*G45)+(H20*H45)+(I20*I45)+(J20*J45)+(K20*K45)+(L20*L45)+(M20*M45)+(N20*N45)+(O20*O45)+(P20*P45)+(Q20*Q45)+(R20*R45)+(S20*S45)+(T20*T45)+(U20*U45)+(V20*V45)+(W20*W45)+(X20*X45)+(Y20*Y45)+(Z20*Z45)+(AA20*AA45)+(AB20*AB45) -> 0 | AD20: =10%*AC20 -> 0 | AE20: =AC20-AD20 -> 0 | AL20: =AE20/3 -> 0 | AM20: =AL20 -> 0 | AN20: =AM20 -> 0 | AO20: =AD20+AF20+AG20+AH20+AI20+AJ20+AK20 -> 0
B21: =B20+1 -> 11 | AC21: =(E21*E45)+(F21*F45)+(G21*G45)+(H21*H45)+(I21*I45)+(J21*J45)+(K21*K45)+(L21*L45)+(M21*M45)+(N21*N45)+(O21*O45)+(P21*P45)+(Q21*Q45)+(R21*R45)+(S21*S45)+(T21*T45)+(U21*U45)+(V21*V45)+(W21*W45)+(X21*X45)+(Y21*Y45)+(Z21*Z45)+(AA21*AA45)+(AB21*AB45) -> 0 | AD21: =10%*AC21 -> 0 | AE21: =AC21-AD21 -> 0 | AL21: =AE21/3 -> 0 | AM21: =AL21 -> 0 | AN21: =AM21 -> 0
B22: =B21+1 -> 12 | AC22: =(E22*E45)+(F22*F45)+(G22*G45)+(H22*H45)+(I22*I45)+(J22*J45)+(K22*K45)+(L22*L45)+(M22*M45)+(N22*N45)+(O22*O45)+(P22*P45)+(Q22*Q45)+(R22*R45)+(S22*S45)+(T22*T45)+(U22*U45)+(V22*V45)+(W22*W45)+(X22*X45)+(Y22*Y45)+(Z22*Z45)+(AA22*AA45)+(AB22*AB45) -> 0 | AD22: =10%*AC22 -> 0 | AE22: =AC22-AD22 -> 0 | AL22: =AE22/3 -> 0 | AM22: =AL22 -> 0 | AN22: =AM22 -> 0
B23: =B22+1 -> 13 | AC23: =(E23*E45)+(F23*F45)+(G23*G45)+(H23*H45)+(I23*I45)+(J23*J45)+(K23*K45)+(L23*L45)+(M23*M45)+(N23*N45)+(O23*O45)+(P23*P45)+(Q23*Q45)+(R23*R45)+(S23*S45)+(T23*T45)+(U23*U45)+(V23*V45)+(W23*W45)+(X23*X45)+(Y23*Y45)+(Z23*Z45)+(AA23*AA45)+(AB23*AB45) -> 0 | AD23: =10%*AC23 -> 0 | AE23: =AC23-AD23 -> 0 | AL23: =AE23/3 -> 0 | AM23: =AL23 -> 0 | AN23: =AM23 -> 0
B24: =B23+1 -> 14 | AC24: =(E24*E45)+(F24*F45)+(G24*G45)+(H24*H45)+(I24*I45)+(J24*J45)+(K24*J45)+(L24*L45)+(M24*M45)+(N24*N45)+(O24*O45)+(P24*P45)+(Q24*Q45)+(R24*R45)+(S24*S45)+(T24*T45)+(U24*U45)+(V24*V45)+(W24*W45)+(X24*X45)+(Y24*Y45)+(Z24*Z45)+(AA24*AA45)+(AB24*AB45) -> 0 | AD24: =10%*AC24 -> 0 | AE24: =AC24-AD24 -> 0 | AL24: =AE24/3 -> 0 | AM24: =AL24 -> 0 | AN24: =AM24 -> 0
B25: =B24+1 -> 15 | AC25: =(E25*E45)+(F25*F45)+(G25*G45)+(H25*H45)+(I25*I45)+(J25*J45)+(K25*K45)+(L25*L45)+(M25*M45)+(N25*N45)+(O25*O45)+(P25*P45)+(Q25*Q45)+(R25*R45)+(S25*S45)+(T25*T45)+(U25*U45)+(V25*V45)+(W25*W45)+(X25*X45)+(Y25*Y45)+(Z25*Z45)+(AA25*AA45)+(AB25*AB45) -> 0 | AD25: =10%*AC25 -> 0 | AE25: =AC25-AD25 -> 0 | AL25: =AE25/3 -> 0 | AM25: =AL25 -> 0 | AN25: =AM25 -> 0
B26: =B25+1 -> 16 | AC26: =(E26*E45)+(F26*F45)+(G26*G45)+(H26*H45)+(I26*I45)+(J26*J45)+(K26*K45)+(L26*L45)+(M26*M45)+(N26*N45)+(O26*O45)+(P26*P45)+(Q26*Q45)+(R26*R45)+(S26*S45)+(T26*T45)+(U26*U45)+(V26*V45)+(W26*W45)+(X26*X45)+(Y26*Y45)+(Z26*Z45)+(AA26*AA45)+(AB26*AB45) -> 0 | AD26: =10%*AC26 -> 0 | AE26: =AC26-AD26 -> 0 | AL26: =AE26/3 -> 0 | AM26: =AL26 -> 0 | AN26: =AM26 -> 0
B27: =B26+1 -> 17 | AC27: =(E27*E45)+(F27*F45)+(G27*G45)+(H27*H45)+(I27*I45)+(J27*J45)+(K27*J45)+(L27*L45)+(M27*M45)+(N27*N45)+(O27*O45)+(P27*P45)+(Q27*Q45)+(R27*R45)+(S27*S45)+(T27*T45)+(U27*U45)+(V27*V45)+(W27*W45)+(X27*X45)+(Y27*Y45)+(Z27*Z45)+(AA27*AA45)+(AB27*AB45) -> 0 | AD27: =10%*AC27 -> 0 | AE27: =AC27-AD27 -> 0 | AL27: =AE27/3 -> 0 | AM27: =AL27 -> 0 | AN27: =AM27 -> 0
B28: =B27+1 -> 18 | AC28: =(E28*E45)+(F28*F45)+(G28*G45)+(H28*H45)+(I28*I45)+(J28*J45)+(K28*K45)+(L28*L45)+(M28*M45)+(N28*N45)+(O28*O45)+(P28*P45)+(Q28*Q45)+(R28*R45)+(S28*S45)+(T28*T45)+(U28*U45)+(V28*V45)+(W28*W45)+(X28*X45)+(Y28*Y45)+(Z28*Z45)+(AA28*AA45)+(AB28*AB45) -> 0 | AD28: =10%*AC28 -> 0 | AE28: =AC28-AD28 -> 0 | AL28: =AE28/3 -> 0 | AM28: =AL28 -> 0 | AN28: =AM28 -> 0
B29: =B28+1 -> 19 | AC29: =(E29*E45)+(F29*F45)+(G29*G45)+(H29*H45)+(I29*I45)+(J29*J45)+(K29*K45)+(L29*L45)+(M29*M45)+(N29*N45)+(O29*O45)+(P29*P45)+(Q29*Q45)+(R29*R45)+(S29*S45)+(T29*T45)+(U29*U45)+(V29*V45)+(W29*W45)+(X29*X45)+(Y29*Y45)+(Z29*Z45)+(AA29*AA45)+(AB29*AB45) -> 0 | AD29: =10%*AC29 -> 0 | AE29: =AC29-AD29 -> 0 | AL29: =AE29/3 -> 0 | AM29: =AL29 -> 0 | AN29: =AM29 -> 0
B30: =B29+1 -> 20 | AC30: =(E30*E45)+(F30*F45)+(G30*G45)+(H30*H45)+(I30*I45)+(J30*J45)+(K30*J45)+(L30*L45)+(M30*M45)+(N30*N45)+(O30*O45)+(P30*P45)+(Q30*Q45)+(R30*R45)+(S30*S45)+(T30*T45)+(U30*U45)+(V30*V45)+(W30*W45)+(X30*X45)+(Y30*Y45)+(Z30*Z45)+(AA30*AA45)+(AB30*AB45) -> 0 | AD30: =10%*AC30 -> 0 | AE30: =AC30-AD30 -> 0 | AL30: =AE30/3 -> 0 | AM30: =AL30 -> 0 | AN30: =AM30 -> 0
B31: =B30+1 -> 21 | AC31: =(E31*E45)+(F31*F45)+(G31*G45)+(H31*H45)+(I31*I45)+(J31*J45)+(K31*K45)+(L31*L45)+(M31*M45)+(N31*N45)+(O31*O45)+(P31*P45)+(Q31*Q45)+(R31*R45)+(S31*S45)+(T31*T45)+(U31*U45)+(V31*V45)+(W31*W45)+(X31*X45)+(Y31*Y45)+(Z31*Z45)+(AA31*AA45)+(AB31*AB45) -> 0 | AD31: =10%*AC31 -> 0 | AE31: =AC31-AD31 -> 0 | AL31: =AE31/3 -> 0 | AM31: =AL31 -> 0 | AN31: =AM31 -> 0
B32: =B31+1 -> 22 | AC32: =(E32*E45)+(F32*F45)+(G32*G45)+(H32*H45)+(I32*I45)+(J32*J45)+(K32*K45)+(L32*L45)+(M32*M45)+(N32*N45)+(O32*O45)+(P32*P45)+(Q32*Q45)+(R32*R45)+(S32*S45)+(T32*T45)+(U32*U45)+(V32*V45)+(W32*W45)+(X32*X45)+(Y32*Y45)+(Z32*Z45)+(AA32*AA45)+(AB32*AB45) -> 0 | AD32: =10%*AC32 -> 0 | AE32: =AC32-AD32 -> 0 | AL32: =AE32/3 -> 0 | AM32: =AL32 -> 0 | AN32: =AM32 -> 0
B33: =B32+1 -> 23 | AC33: =(E33*E45)+(F33*F45)+(G33*G45)+(H33*H45)+(I33*I45)+(J33*J45)+(K33*J45)+(L33*L45)+(M33*M45)+(N33*N45)+(O33*O45)+(P33*P45)+(Q33*Q45)+(R33*R45)+(S33*S45)+(T33*T45)+(U33*U45)+(V33*V45)+(W33*W45)+(X33*X45)+(Y33*Y45)+(Z33*Z45)+(AA33*AA45)+(AB33*AB45) -> 0 | AD33: =10%*AC33 -> 0 | AE33: =AC33-AD33 -> 0 | AL33: =AE33/3 -> 0 | AM33: =AL33 -> 0 | AN33: =AM33 -> 0
B34: =B33+1 -> 24 | AC34: =(E34*E45)+(F34*F45)+(G34*G45)+(H34*H45)+(I34*I45)+(J34*J45)+(K34*K45)+(L34*L45)+(M34*M45)+(N34*N45)+(O34*O45)+(P34*P45)+(Q34*Q45)+(R34*R45)+(S34*S45)+(T34*T45)+(U34*U45)+(V34*V45)+(W34*W45)+(X34*X45)+(Y34*Y45)+(Z34*Z45)+(AA34*AA45)+(AB34*AB45) -> 0 | AD34: =10%*AC34 -> 0 | AE34: =AC34-AD34 -> 0 | AL34: =AE34/3 -> 0 | AM34: =AL34 -> 0 | AN34: =AM34 -> 0
B35: =B34+1 -> 25 | AC35: =(E35*E45)+(F35*F45)+(G35*G45)+(H35*H45)+(I35*I45)+(J35*J45)+(K35*K45)+(L35*L45)+(M35*M45)+(N35*N45)+(O35*O45)+(P35*P45)+(Q35*Q45)+(R35*R45)+(S35*S45)+(T35*T45)+(U35*U45)+(V35*V45)+(W35*W45)+(X35*X45)+(Y35*Y45)+(Z35*Z45)+(AA35*AA45)+(AB35*AB45) -> 0 | AD35: =10%*AC35 -> 0 | AE35: =AC35-AD35 -> 0 | AL35: =AE35/3 -> 0 | AM35: =AL35 -> 0 | AN35: =AM35 -> 0
B36: =B35+1 -> 26 | AC36: =(E36*E45)+(F36*F45)+(G36*G45)+(H36*H45)+(I36*I45)+(J36*J45)+(K36*J45)+(L36*L45)+(M36*M45)+(N36*N45)+(O36*O45)+(P36*P45)+(Q36*Q45)+(R36*R45)+(S36*S45)+(T36*T45)+(U36*U45)+(V36*V45)+(W36*W45)+(X36*X45)+(Y36*Y45)+(Z36*Z45)+(AA36*AA45)+(AB36*AB45) -> 0 | AD36: =10%*AC36 -> 0 | AE36: =AC36-AD36 -> 0 | AL36: =AE36/3 -> 0 | AM36: =AL36 -> 0 | AN36: =AM36 -> 0
B37: =B36+1 -> 27 | AC37: =(E37*E45)+(F37*F45)+(G37*G45)+(H37*H45)+(I37*I45)+(J37*J45)+(K37*K45)+(L37*L45)+(M37*M45)+(N37*N45)+(O37*O45)+(P37*P45)+(Q37*Q45)+(R37*R45)+(S37*S45)+(T37*T45)+(U37*U45)+(V37*V45)+(W37*W45)+(X37*X45)+(Y37*Y45)+(Z37*Z45)+(AA37*AA45)+(AB37*AB45) -> 0 | AD37: =10%*AC37 -> 0 | AE37: =AC37-AD37 -> 0 | AL37: =AE37/3 -> 0 | AM37: =AL37 -> 0 | AN37: =AM37 -> 0
B38: =B37+1 -> 28 | AC38: =(E38*E45)+(F38*F45)+(G38*G45)+(H38*H45)+(I38*I45)+(J38*J45)+(K38*K45)+(L38*L45)+(M38*M45)+(N38*N45)+(O38*O45)+(P38*P45)+(Q38*Q45)+(R38*R45)+(S38*S45)+(T38*T45)+(U38*U45)+(V38*V45)+(W38*W45)+(X38*X45)+(Y38*Y45)+(Z38*Z45)+(AA38*AA45)+(AB38*AB45) -> 0 | AD38: =10%*AC38 -> 0 | AE38: =AC38-AD38 -> 0 | AL38: =AE38/3 -> 0 | AM38: =AL38 -> 0 | AN38: =AM38 -> 0
B39: =B38+1 -> 29 | AC39: =(E39*E45)+(F39*F45)+(G39*G45)+(H39*H45)+(I39*I45)+(J39*J45)+(K39*J45)+(L39*L45)+(M39*M45)+(N39*N45)+(O39*O45)+(P39*P45)+(Q39*Q45)+(R39*R45)+(S39*S45)+(T39*T45)+(U39*U45)+(V39*V45)+(W39*W45)+(X39*X45)+(Y39*Y45)+(Z39*Z45)+(AA39*AA45)+(AB39*AB45) -> 0 | AD39: =10%*AC39 -> 0 | AE39: =AC39-AD39 -> 0 | AL39: =AE39/3 -> 0 | AM39: =AL39 -> 0 | AN39: =AM39 -> 0
B40: =B39+1 -> 30 | AC40: =(E40*E45)+(F40*F45)+(G40*G45)+(H40*H45)+(I40*I45)+(J40*J45)+(K40*K45)+(L40*L45)+(M40*M45)+(N40*N45)+(O40*O45)+(P40*P45)+(Q40*Q45)+(R40*R45)+(S40*S45)+(T40*T45)+(U40*U45)+(V40*V45)+(W40*W45)+(X40*X45)+(Y40*Y45)+(Z40*Z45)+(AA40*AA45)+(AB40*AB45) -> 0 | AD40: =10%*AC40 -> 0 | AE40: =AC40-AD40 -> 0 | AL40: =AE40/3 -> 0 | AM40: =AL40 -> 0 | AN40: =AM40 -> 0
B41: =B40+1 -> 31 | AC41: =(E41*E45)+(F41*F45)+(G41*G45)+(H41*H45)+(I41*I45)+(J41*J45)+(K41*K45)+(L41*L45)+(M41*M45)+(N41*N45)+(O41*O45)+(P41*P45)+(Q41*Q45)+(R41*R45)+(S41*S45)+(T41*T45)+(U41*U45)+(V41*V45)+(W41*W45)+(X41*X45)+(Y41*Y45)+(Z41*Z45)+(AA41*AA45)+(AB41*AB45) -> 0 | AD41: =10%*AC41 -> 0 | AE41: =AC41-AD41 -> 0 | AL41: =AE41/3 -> 0 | AM41: =AL41 -> 0 | AN41: =AM41 -> 0
B42: TOTAL | C42: =COUNTA(C11:C41) -> 0 | E42: =SUM(E11:E41) -> 0 | F42: =SUM(F11:F41) -> 0 | G42: =SUM(G11:G41) -> 0 | H42: =SUM(H11:H41) -> 0 | I42: =SUM(I11:I41) -> 0 | J42: =SUM(J11:J41) -> 0 | K42: =SUM(K11:K41) -> 0 | L42: =SUM(L11:L41) -> 0 | ... AE42: =SUM(AE11:AE41) -> 0 | AL42: =SUM(AL11:AL41) -> 0 | AM42: =SUM(AM11:AM41) -> 0 | AN42: =SUM(AN11:AN41) -> 0 | AO42: =SUM(AO11:AO41) -> 0
C45: Price | E45: 144 | F45: =12*E45 -> 1728 | G45: 116 | H45: =G45*48 -> 5568 | I45: 144 | J45: =I45*12 -> 1728 | K45: 116 | L45: =K45*15 -> 1740 | M45: 116 | N45: =M45*6 -> 696 | O45: 272 | P45: =O45*4 -> 1088 | Q45: 1088 | R45: 272 | S45: =R45*4 -> 1088 | T45: 4964 | U45: 68 | V45: =U45*12 -> 816 | W45: 20 | X45: 52 | Y45: =X45*12 -> 624 | Z45: 1224 | AA45: 102 | AB45: 340

Sheet 12
C2: NOTE:
C3: 1. Enter the quantity of agro inputs requested by the farmer either in pcs or boxes under each agro input
C4: 2. Do not change any thing in the excel sheet. The cells are linked
K5: NEW PRICES
C6: REGION: | D6: ASHANTI
C7: DISTRICT: | D7: TEPA
C8: SOCIETY: | D8: ASEMPANAYE
B10: NO. | C10: FARMER NAME | D10: MOBILE NO. | E10: AcetaStar -Adama (1Lt) | G10: Galil | I10: AKATE BRAFO | K10: PHYTOGREEN | M10: BEGREEN | O10: Agyenkwa Liquid Fertilizer (5Lt) | Q10: Matabi (15Lt) | R10: PLANTFEED | T10: Solo Machine | U10: All Wedicides (Glyphosate) | W10: NODOX | X10: ALL GRAMO | Z10: STANDARD PRUNNER | AA10: WELLINGTON BOOT | AB10: OVERALL | AC10: TOTAL AMOUNT (GHc) | AD10: DEPOSIT PAID (GHc) | AE10: OUTS. BALANCE (GHc) | AF10: REPAYMENT PLAN(GHC)
E11: PCs | F11: Box (12pcs) | G11: PCs | H11: Box | I11: PCs | J11: Box | K11: 1LT | L11: BOX(15) | M11: 1GALLON | N11: BOX(6) | O11: PCs | P11: Box(4) | Q11: PCs | R11: 1 GALLON | S11: BOX(4) | T11: PCs | U11: PCS | V11: BOX(12) | W11: PCs | X11: PCS | Y11: BOX(12) | Z11: PC | AA11: PC | AB11: PC | AF11: OCT | AG11: NOV | AL11: OCT | AM11: NOV | AN11: DEC | AO11: TOTAL PAYMENT
B12: =B11+1 -> 1 | D12: 0599043061 | AC12: =(E12*E46)+(F12*F46)+(G12*G46)+(H12*H46)+(I12*I46)+(J12*J46)+(K12*K46)+(L12*L46)+(M12*M46)+(N12*N46)+(O12*O46)+(P12*P46)+(Q12*Q46)+(R12*R46)+(S12*S46)+(T12*T46)+(U12*U46)+(V12*V46)+(W12*W46)+(X12*X46)+(Y12*Y46)+(Z12*Z46)+(AA12*AA46)+(AB12*AB46) -> 0 | AD12: =10%*AC12 -> 0 | AE12: =AC12-AD12 -> 0 | AL12: =AE12/3 -> 0 | AM12: =AL12 -> 0 | AN12: =AM12 -> 0 | AO12: =AD12+AF12+AG12+AH12+AI12+AJ12+AK12 -> 0
B13: =B12+1 -> 2 | D13: 0545577756 | AC13: =(E13*E46)+(F13*F46)+(G13*G46)+(H13*H46)+(I13*I46)+(J13*J46)+(K13*K46)+(L13*L46)+(M13*M46)+(N13*N46)+(O13*O46)+(P13*P46)+(Q13*Q46)+(R13*R46)+(S13*S46)+(T13*T46)+(U13*U46)+(V13*V46)+(W13*W46)+(X13*X46)+(Y13*Y46)+(Z13*Z46)+(AA13*AA46)+(AB13*AB46) -> 0 | AD13: =10%*AC13 -> 0 | AE13: =AC13-AD13 -> 0 | AL13: =AE13/3 -> 0 | AM13: =AL13 -> 0 | AN13: =AM13 -> 0 | AO13: =AD13+AF13+AG13+AH13+AI13+AJ13+AK13 -> 0
B14: =B13+1 -> 3 | D14: 0247086080 | AC14: =(E14*E46)+(F14*F46)+(G14*G46)+(H14*H46)+(I14*I46)+(J14*J46)+(K14*K46)+(L14*L46)+(M14*M46)+(N14*N46)+(O14*O46)+(P14*P46)+(Q14*Q46)+(R14*R46)+(S14*S46)+(T14*T46)+(U14*U46)+(V14*V46)+(W14*W46)+(X14*X46)+(Y14*Y46)+(Z14*Z46)+(AA14*AA46)+(AB14*AB46) -> 0 | AD14: =10%*AC14 -> 0 | AE14: =AC14-AD14 -> 0 | AL14: =AE14/3 -> 0 | AM14: =AL14 -> 0 | AN14: =AM14 -> 0 | AO14: =AD14+AF14+AG14+AH14+AI14+AJ14+AK14 -> 0
B15: =B14+1 -> 4 | D15: 0554325958 | AC15: =(E15*E46)+(F15*F46)+(G15*G46)+(H15*H46)+(I15*I46)+(J15*J46)+(K15*K46)+(L15*L46)+(M15*M46)+(N15*N46)+(O15*O46)+(P15*P46)+(Q15*Q46)+(R15*R46)+(S15*S46)+(T15*T46)+(U15*U46)+(V15*V46)+(W15*W46)+(X15*X46)+(Y15*Y46)+(Z15*Z46)+(AA15*AA46)+(AB15*AB46) -> 0 | AD15: =10%*AC15 -> 0 | AE15: =AC15-AD15 -> 0 | AL15: =AE15/3 -> 0 | AM15: =AL15 -> 0 | AN15: =AM15 -> 0 | AO15: =AD15+AF15+AG15+AH15+AI15+AJ15+AK15 -> 0
B16: =B15+1 -> 5 | D16: 0240981003 | AC16: =(E16*E46)+(F16*F46)+(G16*G46)+(H16*H46)+(I16*I46)+(J16*J46)+(K16*K46)+(L16*L46)+(M16*M46)+(N16*N46)+(O16*O46)+(P16*P46)+(Q16*Q46)+(R16*R46)+(S16*S46)+(T16*T46)+(U16*U46)+(V16*V46)+(W16*W46)+(X16*X46)+(Y16*Y46)+(Z16*Z46)+(AA16*AA46)+(AB16*AB46) -> 0 | AD16: =10%*AC16 -> 0 | AE16: =AC16-AD16 -> 0 | AL16: =AE16/3 -> 0 | AM16: =AL16 -> 0 | AN16: =AM16 -> 0 | AO16: =AD16+AF16+AG16+AH16+AI16+AJ16+AK16 -> 0
B17: =B16+1 -> 6 | D17: 0597732554 | AC17: =(E17*E46)+(F17*F46)+(G17*G46)+(H17*H46)+(I17*I46)+(J17*J50)+(K17*K46)+(L17*L46)+(M17*M46)+(N17*N46)+(O17*O46)+(P17*P46)+(Q17*Q46)+(R17*R46)+(S17*S46)+(T17*T46)+(U17*U46)+(V17*V46)+(W17*W46)+(X17*X46)+(Y17*Y46)+(Z17*Z46)+(AA17*AA46)+(AB17*AB46) -> 0 | AD17: =10%*AC17 -> 0 | AE17: =AC17-AD17 -> 0 | AL17: =AE17/3 -> 0 | AM17: =AL17 -> 0 | AN17: =AM17 -> 0 | AO17: =AD17+AF17+AG17+AH17+AI17+AJ17+AK17 -> 0
B18: =B17+1 -> 7 | D18: 0592466141 | AC18: =(E18*E46)+(F18*F46)+(G18*G46)+(H18*H46)+(I18*I46)+(J18*J46)+(K18*K46)+(L18*L46)+(M18*M46)+(N18*N46)+(O18*O46)+(P18*P46)+(Q18*Q46)+(R18*R46)+(S18*S46)+(T18*T46)+(U18*U46)+(V18*V46)+(W18*W46)+(X18*X46)+(Y18*Y46)+(Z18*Z46)+(AA18*AA46)+(AB18*AB46) -> 0 | AD18: =10%*AC18 -> 0 | AE18: =AC18-AD18 -> 0 | AL18: =AE18/3 -> 0 | AM18: =AL18 -> 0 | AN18: =AM18 -> 0 | AO18: =AD18+AF18+AG18+AH18+AI18+AJ18+AK18 -> 0
B19: =B18+1 -> 8 | AC19: =(E19*E46)+(F19*F46)+(G19*G46)+(H19*H46)+(I19*I46)+(J19*J46)+(K19*K46)+(L19*L46)+(M19*M46)+(N19*N46)+(O19*O46)+(P19*P46)+(Q19*Q46)+(R19*R46)+(S19*S46)+(T19*T46)+(U19*U46)+(V19*V46)+(W19*W46)+(X19*X46)+(Y19*Y46)+(Z19*Z46)+(AA19*AA46)+(AB19*AB46) -> 0 | AD19: =10%*AC19 -> 0 | AE19: =AC19-AD19 -> 0 | AL19: =AE19/3 -> 0 | AM19: =AL19 -> 0 | AN19: =AM19 -> 0 | AO19: =AD19+AF19+AG19+AH19+AI19+AJ19+AK19 -> 0
B20: =B19+1 -> 9 | AC20: =(E20*E46)+(F20*F46)+(G20*G46)+(H20*H46)+(I20*I46)+(J20*J46)+(K20*K46)+(L20*L46)+(M20*M46)+(N20*N46)+(O20*O46)+(P20*P46)+(Q20*Q46)+(R20*R46)+(S20*S46)+(T20*T46)+(U20*U46)+(V20*V46)+(W20*W46)+(X20*X46)+(Y20*Y46)+(Z20*Z46)+(AA20*AA46)+(AB20*AB46) -> 0 | AD20: =10%*AC20 -> 0 | AE20: =AC20-AD20 -> 0 | AL20: =AE20/3 -> 0 | AM20: =AL20 -> 0 | AN20: =AM20 -> 0 | AO20: =AD20+AF20+AG20+AH20+AI20+AJ20+AK20 -> 0
B21: =B20+1 -> 10 | AC21: =(E21*E46)+(F21*F46)+(G21*G46)+(H21*H46)+(I21*I46)+(J21*J46)+(K21*K46)+(L21*L46)+(M21*M46)+(N21*N46)+(O21*O46)+(P21*P46)+(Q21*Q46)+(R21*R46)+(S21*S46)+(T21*T46)+(U21*U46)+(V21*V46)+(W21*W46)+(X21*X46)+(Y21*Y46)+(Z21*Z46)+(AA21*AA46)+(AB21*AB46) -> 0 | AD21: =10%*AC21 -> 0 | AE21: =AC21-AD21 -> 0 | AL21: =AE21/3 -> 0 | AM21: =AL21 -> 0 | AN21: =AM21 -> 0
B22: =B21+1 -> 11 | AC22: =(E22*E46)+(F22*F46)+(G22*G46)+(H22*H46)+(I22*I46)+(J22*J46)+(K22*K46)+(L22*L46)+(M22*M46)+(N22*N46)+(O22*O46)+(P22*P46)+(Q22*Q46)+(R22*R46)+(S22*S46)+(T22*T46)+(U22*U46)+(V22*V46)+(W22*W46)+(X22*X46)+(Y22*Y46)+(Z22*Z46)+(AA22*AA46)+(AB22*AB46) -> 0 | AD22: =10%*AC22 -> 0 | AE22: =AC22-AD22 -> 0 | AL22: =AE22/3 -> 0 | AM22: =AL22 -> 0 | AN22: =AM22 -> 0
B23: =B22+1 -> 12 | AC23: =(E23*E46)+(F23*F46)+(G23*G46)+(H23*H46)+(I23*I46)+(J23*J46)+(K23*K46)+(L23*L46)+(M23*M46)+(N23*N46)+(O23*O46)+(P23*P46)+(Q23*Q46)+(R23*R46)+(S23*S46)+(T23*T46)+(U23*U46)+(V23*V46)+(W23*W46)+(X23*X46)+(Y23*Y46)+(Z23*Z46)+(AA23*AA46)+(AB23*AB46) -> 0 | AD23: =10%*AC23 -> 0 | AE23: =AC23-AD23 -> 0 | AL23: =AE23/3 -> 0 | AM23: =AL23 -> 0 | AN23: =AM23 -> 0
B24: =B23+1 -> 13 | AC24: =(E24*E46)+(F24*F46)+(G24*G46)+(H24*H46)+(I24*I46)+(J24*J46)+(K24*K46)+(L24*L46)+(M24*M46)+(N24*N46)+(O24*O46)+(P24*P46)+(Q24*Q46)+(R24*R46)+(S24*S46)+(T24*T46)+(U24*U46)+(V24*V46)+(W24*W46)+(X24*X46)+(Y24*Y46)+(Z24*Z46)+(AA24*AA46)+(AB24*AB46) -> 0 | AD24: =10%*AC24 -> 0 | AE24: =AC24-AD24 -> 0 | AL24: =AE24/3 -> 0 | AM24: =AL24 -> 0 | AN24: =AM24 -> 0
B25: =B24+1 -> 14 | AC25: =(E25*E46)+(F25*F46)+(G25*G46)+(H25*H46)+(I25*I46)+(J25*J46)+(K25*J46)+(L25*L46)+(M25*M46)+(N25*N46)+(O25*O46)+(P25*P46)+(Q25*Q46)+(R25*R46)+(S25*S46)+(T25*T46)+(U25*U46)+(V25*V46)+(W25*W46)+(X25*X46)+(Y25*Y46)+(Z25*Z46)+(AA25*AA46)+(AB25*AB46) -> 0 | AD25: =10%*AC25 -> 0 | AE25: =AC25-AD25 -> 0 | AL25: =AE25/3 -> 0 | AM25: =AL25 -> 0 | AN25: =AM25 -> 0
B26: =B25+1 -> 15 | AC26: =(E26*E46)+(F26*F46)+(G26*G46)+(H26*H46)+(I26*I46)+(J26*J46)+(K26*K46)+(L26*L46)+(M26*M46)+(N26*N46)+(O26*O46)+(P26*P46)+(Q26*Q46)+(R26*R46)+(S26*S46)+(T26*T46)+(U26*U46)+(V26*V46)+(W26*W46)+(X26*X46)+(Y26*Y46)+(Z26*Z46)+(AA26*AA46)+(AB26*AB46) -> 0 | AD26: =10%*AC26 -> 0 | AE26: =AC26-AD26 -> 0 | AL26: =AE26/3 -> 0 | AM26: =AL26 -> 0 | AN26: =AM26 -> 0
B27: =B26+1 -> 16 | AC27: =(E27*E46)+(F27*F46)+(G27*G46)+(H27*H46)+(I27*I46)+(J27*J46)+(K27*K46)+(L27*L46)+(M27*M46)+(N27*N46)+(O27*O46)+(P27*P46)+(Q27*Q46)+(R27*R46)+(S27*S46)+(T27*T46)+(U27*U46)+(V27*V46)+(W27*W46)+(X27*X46)+(Y27*Y46)+(Z27*Z46)+(AA27*AA46)+(AB27*AB46) -> 0 | AD27: =10%*AC27 -> 0 | AE27: =AC27-AD27 -> 0 | AL27: =AE27/3 -> 0 | AM27: =AL27 -> 0 | AN27: =AM27 -> 0
B28: =B27+1 -> 17 | AC28: =(E28*E46)+(F28*F46)+(G28*G46)+(H28*H46)+(I28*I46)+(J28*J46)+(K28*J46)+(L28*L46)+(M28*M46)+(N28*N46)+(O28*O46)+(P28*P46)+(Q28*Q46)+(R28*R46)+(S28*S46)+(T28*T46)+(U28*U46)+(V28*V46)+(W28*W46)+(X28*X46)+(Y28*Y46)+(Z28*Z46)+(AA28*AA46)+(AB28*AB46) -> 0 | AD28: =10%*AC28 -> 0 | AE28: =AC28-AD28 -> 0 | AL28: =AE28/3 -> 0 | AM28: =AL28 -> 0 | AN28: =AM28 -> 0
B29: =B28+1 -> 18 | AC29: =(E29*E46)+(F29*F46)+(G29*G46)+(H29*H46)+(I29*I46)+(J29*J46)+(K29*K46)+(L29*L46)+(M29*M46)+(N29*N46)+(O29*O46)+(P29*P46)+(Q29*Q46)+(R29*R46)+(S29*S46)+(T29*T46)+(U29*U46)+(V29*V46)+(W29*W46)+(X29*X46)+(Y29*Y46)+(Z29*Z46)+(AA29*AA46)+(AB29*AB46) -> 0 | AD29: =10%*AC29 -> 0 | AE29: =AC29-AD29 -> 0 | AL29: =AE29/3 -> 0 | AM29: =AL29 -> 0 | AN29: =AM29 -> 0
B30: =B29+1 -> 19 | AC30: =(E30*E46)+(F30*F46)+(G30*G46)+(H30*H46)+(I30*I46)+(J30*J46)+(K30*K46)+(L30*L46)+(M30*M46)+(N30*N46)+(O30*O46)+(P30*P46)+(Q30*Q46)+(R30*R46)+(S30*S46)+(T30*T46)+(U30*U46)+(V30*V46)+(W30*W46)+(X30*X46)+(Y30*Y46)+(Z30*Z46)+(AA30*AA46)+(AB30*AB46) -> 0 | AD30: =10%*AC30 -> 0 | AE30: =AC30-AD30 -> 0 | AL30: =AE30/3 -> 0 | AM30: =AL30 -> 0 | AN30: =AM30 -> 0
B31: =B30+1 -> 20 | AC31: =(E31*E46)+(F31*F46)+(G31*G46)+(H31*H46)+(I31*I46)+(J31*J46)+(K31*J46)+(L31*L46)+(M31*M46)+(N31*N46)+(O31*O46)+(P31*P46)+(Q31*Q46)+(R31*R46)+(S31*S46)+(T31*T46)+(U31*U46)+(V31*V46)+(W31*W46)+(X31*X46)+(Y31*Y46)+(Z31*Z46)+(AA31*AA46)+(AB31*AB46) -> 0 | AD31: =10%*AC31 -> 0 | AE31: =AC31-AD31 -> 0 | AL31: =AE31/3 -> 0 | AM31: =AL31 -> 0 | AN31: =AM31 -> 0
B32: =B31+1 -> 21 | AC32: =(E32*E46)+(F32*F46)+(G32*G46)+(H32*H46)+(I32*I46)+(J32*J46)+(K32*K46)+(L32*L46)+(M32*M46)+(N32*N46)+(O32*O46)+(P32*P46)+(Q32*Q46)+(R32*R46)+(S32*S46)+(T32*T46)+(U32*U46)+(V32*V46)+(W32*W46)+(X32*X46)+(Y32*Y46)+(Z32*Z46)+(AA32*AA46)+(AB32*AB46) -> 0 | AD32: =10%*AC32 -> 0 | AE32: =AC32-AD32 -> 0 | AL32: =AE32/3 -> 0 | AM32: =AL32 -> 0 | AN32: =AM32 -> 0
B33: =B32+1 -> 22 | AC33: =(E33*E46)+(F33*F46)+(G33*G46)+(H33*H46)+(I33*I46)+(J33*J46)+(K33*K46)+(L33*L46)+(M33*M46)+(N33*N46)+(O33*O46)+(P33*P46)+(Q33*Q46)+(R33*R46)+(S33*S46)+(T33*T46)+(U33*U46)+(V33*V46)+(W33*W46)+(X33*X46)+(Y33*Y46)+(Z33*Z46)+(AA33*AA46)+(AB33*AB46) -> 0 | AD33: =10%*AC33 -> 0 | AE33: =AC33-AD33 -> 0 | AL33: =AE33/3 -> 0 | AM33: =AL33 -> 0 | AN33: =AM33 -> 0
B34: =B33+1 -> 23 | AC34: =(E34*E46)+(F34*F46)+(G34*G46)+(H34*H46)+(I34*I46)+(J34*J46)+(K34*J46)+(L34*L46)+(M34*M46)+(N34*N46)+(O34*O46)+(P34*P46)+(Q34*Q46)+(R34*R46)+(S34*S46)+(T34*T46)+(U34*U46)+(V34*V46)+(W34*W46)+(X34*X46)+(Y34*Y46)+(Z34*Z46)+(AA34*AA46)+(AB34*AB46) -> 0 | AD34: =10%*AC34 -> 0 | AE34: =AC34-AD34 -> 0 | AL34: =AE34/3 -> 0 | AM34: =AL34 -> 0 | AN34: =AM34 -> 0
B35: =B34+1 -> 24 | AC35: =(E35*E46)+(F35*F46)+(G35*G46)+(H35*H46)+(I35*I46)+(J35*J46)+(K35*K46)+(L35*L46)+(M35*M46)+(N35*N46)+(O35*O46)+(P35*P46)+(Q35*Q46)+(R35*R46)+(S35*S46)+(T35*T46)+(U35*U46)+(V35*V46)+(W35*W46)+(X35*X46)+(Y35*Y46)+(Z35*Z46)+(AA35*AA46)+(AB35*AB46) -> 0 | AD35: =10%*AC35 -> 0 | AE35: =AC35-AD35 -> 0 | AL35: =AE35/3 -> 0 | AM35: =AL35 -> 0 | AN35: =AM35 -> 0
B36: =B35+1 -> 25 | AC36: =(E36*E46)+(F36*F46)+(G36*G46)+(H36*H46)+(I36*I46)+(J36*J46)+(K36*K46)+(L36*L46)+(M36*M46)+(N36*N46)+(O36*O46)+(P36*P46)+(Q36*Q46)+(R36*R46)+(S36*S46)+(T36*T46)+(U36*U46)+(V36*V46)+(W36*W46)+(X36*X46)+(Y36*Y46)+(Z36*Z46)+(AA36*AA46)+(AB36*AB46) -> 0 | AD36: =10%*AC36 -> 0 | AE36: =AC36-AD36 -> 0 | AL36: =AE36/3 -> 0 | AM36: =AL36 -> 0 | AN36: =AM36 -> 0
B37: =B36+1 -> 26 | AC37: =(E37*E46)+(F37*F46)+(G37*G46)+(H37*H46)+(I37*I46)+(J37*J46)+(K37*J46)+(L37*L46)+(M37*M46)+(N37*N46)+(O37*O46)+(P37*P46)+(Q37*Q46)+(R37*R46)+(S37*S46)+(T37*T46)+(U37*U46)+(V37*V46)+(W37*W46)+(X37*X46)+(Y37*Y46)+(Z37*Z46)+(AA37*AA46)+(AB37*AB46) -> 0 | AD37: =10%*AC37 -> 0 | AE37: =AC37-AD37 -> 0 | AL37: =AE37/3 -> 0 | AM37: =AL37 -> 0 | AN37: =AM37 -> 0
B38: =B37+1 -> 27 | AC38: =(E38*E46)+(F38*F46)+(G38*G46)+(H38*H46)+(I38*I46)+(J38*J46)+(K38*K46)+(L38*L46)+(M38*M46)+(N38*N46)+(O38*O46)+(P38*P46)+(Q38*Q46)+(R38*R46)+(S38*S46)+(T38*T46)+(U38*U46)+(V38*V46)+(W38*W46)+(X38*X46)+(Y38*Y46)+(Z38*Z46)+(AA38*AA46)+(AB38*AB46) -> 0 | AD38: =10%*AC38 -> 0 | AE38: =AC38-AD38 -> 0 | AL38: =AE38/3 -> 0 | AM38: =AL38 -> 0 | AN38: =AM38 -> 0
B39: =B38+1 -> 28 | AC39: =(E39*E46)+(F39*F46)+(G39*G46)+(H39*H46)+(I39*I46)+(J39*J46)+(K39*K46)+(L39*L46)+(M39*M46)+(N39*N46)+(O39*O46)+(P39*P46)+(Q39*Q46)+(R39*R46)+(S39*S46)+(T39*T46)+(U39*U46)+(V39*V46)+(W39*W46)+(X39*X46)+(Y39*Y46)+(Z39*Z46)+(AA39*AA46)+(AB39*AB46) -> 0 | AD39: =10%*AC39 -> 0 | AE39: =AC39-AD39 -> 0 | AL39: =AE39/3 -> 0 | AM39: =AL39 -> 0 | AN39: =AM39 -> 0
B40: =B39+1 -> 29 | AC40: =(E40*E46)+(F40*F46)+(G40*G46)+(H40*H46)+(I40*I46)+(J40*J46)+(K40*J46)+(L40*L46)+(M40*M46)+(N40*N46)+(O40*O46)+(P40*P46)+(Q40*Q46)+(R40*R46)+(S40*S46)+(T40*T46)+(U40*U46)+(V40*V46)+(W40*W46)+(X40*X46)+(Y40*Y46)+(Z40*Z46)+(AA40*AA46)+(AB40*AB46) -> 0 | AD40: =10%*AC40 -> 0 | AE40: =AC40-AD40 -> 0 | AL40: =AE40/3 -> 0 | AM40: =AL40 -> 0 | AN40: =AM40 -> 0
B41: =B40+1 -> 30 | AC41: =(E41*E46)+(F41*F46)+(G41*G46)+(H41*H46)+(I41*I46)+(J41*J46)+(K41*K46)+(L41*L46)+(M41*M46)+(N41*N46)+(O41*O46)+(P41*P46)+(Q41*Q46)+(R41*R46)+(S41*S46)+(T41*T46)+(U41*U46)+(V41*V46)+(W41*W46)+(X41*X46)+(Y41*Y46)+(Z41*Z46)+(AA41*AA46)+(AB41*AB46) -> 0 | AD41: =10%*AC41 -> 0 | AE41: =AC41-AD41 -> 0 | AL41: =AE41/3 -> 0 | AM41: =AL41 -> 0 | AN41: =AM41 -> 0
B42: =B41+1 -> 31 | AC42: =(E42*E46)+(F42*F46)+(G42*G46)+(H42*H46)+(I42*I46)+(J42*J46)+(K42*K46)+(L42*L46)+(M42*M46)+(N42*N46)+(O42*O46)+(P42*P46)+(Q42*Q46)+(R42*R46)+(S42*S46)+(T42*T46)+(U42*U46)+(V42*V46)+(W42*W46)+(X42*X46)+(Y42*Y46)+(Z42*Z46)+(AA42*AA46)+(AB42*AB46) -> 0 | AD42: =10%*AC42 -> 0 | AE42: =AC42-AD42 -> 0 | AL42: =AE42/3 -> 0 | AM42: =AL42 -> 0 | AN42: =AM42 -> 0
B43: TOTAL | C43: =COUNTA(C12:C42) -> 0 | E43: =SUM(E12:E42) -> 0 | F43: =SUM(F12:F42) -> 0 | G43: =SUM(G12:G42) -> 0 | H43: =SUM(H12:H42) -> 0 | I43: =SUM(I12:I42) -> 0 | J43: =SUM(J12:J42) -> 0 | K43: =SUM(K12:K42) -> 0 | L43: =SUM(L12:L42) -> 0 | ... AE43: =SUM(AE12:AE42) -> 0 | AL43: =SUM(AL12:AL42) -> 0 | AM43: =SUM(AM12:AM42) -> 0 | AN43: =SUM(AN12:AN42) -> 0 | AO43: =SUM(AO12:AO42) -> 0
C46: Price | E46: 144 | F46: =12*E46 -> 1728 | G46: 116 | H46: =G46*48 -> 5568 | I46: 144 | J46: =I46*12 -> 1728 | K46: 116 | L46: =K46*15 -> 1740 | M46: 116 | N46: =M46*6 -> 696 | O46: 272 | P46: =O46*4 -> 1088 | Q46: 1088 | R46: 272 | S46: =R46*4 -> 1088 | T46: 4964 | U46: 68 | V46: =U46*12 -> 816 | W46: 20 | X46: 52 | Y46: =X46*12 -> 624 | Z46: 1224 | AA46: 102 | AB46: 340

Sheet 5
C2: NOTE:
C3: 1. Enter the quantity of agro inputs requested by the farmer either in pcs or boxes under each agro input
C4: 2. Do not change any thing in the excel sheet. The cells are linked
K5: NEW PRICES
C6: REGION: | D6: ASHANTI
C7: DISTRICT: | D7: TEPA
C8: SOCIETY:
B10: NO. | C10: FARMER NAME | D10: MOBILE NO. | E10: AcetaStar -Adama (1Lt) | G10: Galil | I10: AKATE BRAFO | K10: PHYTOGREEN | M10: BEGREEN | O10: Agyenkwa Liquid Fertilizer (5Lt) | Q10: Matabi (15Lt) | R10: PLANTFEED | T10: Solo Machine | U10: All Wedicides (Glyphosate) | W10: NODOX | X10: ALL GRAMO | Z10: STANDARD PRUNNER | AA10: WELLINGTON BOOT | AB10: OVERALL | AC10: TOTAL AMOUNT (GHc) | AD10: DEPOSIT PAID (GHc) | AE10: OUTS. BALANCE (GHc) | AF10: REPAYMENT PLAN(GHC)
E11: PCs | F11: Box (12pcs) | G11: PCs | H11: Box | I11: PCs | J11: Box | K11: 1LT | L11: BOX(15) | M11: 1GALLON | N11: BOX(6) | O11: PCs | P11: Box(4) | Q11: PCs | R11: 1 GALLON | S11: BOX(4) | T11: PCs | U11: PCS | V11: BOX(12) | W11: PCs | X11: PCS | Y11: BOX(12) | Z11: PC | AA11: PC | AB11: PC | AF11: OCT | AH11: NOV | AL11: OCT | AM11: NOV | AN11: DEC | AO11: TOTAL PAYMENT | AP11: REMN
B12: =B11+1 -> 1 | AC12: =(E12*E46)+(F12*F46)+(G12*G46)+(H12*H46)+(I12*I46)+(J12*J46)+(K12*K46)+(L12*L46)+(M12*M46)+(N12*N46)+(O12*O46)+(P12*P46)+(Q12*Q46)+(R12*R46)+(S12*S46)+(T12*T46)+(U12*U46)+(V12*V46)+(W12*W46)+(X12*X46)+(Y12*Y46)+(Z12*Z46)+(AA12*AA46)+(AB12*AB46) -> 0 | AD12: =10%*AC12 -> 0 | AE12: =AC12-AD12 -> 0 | AL12: =AE12/3 -> 0 | AM12: =AL12 -> 0 | AN12: =AM12 -> 0 | AO12: =AD12+AF12+AG12+AH12+AI12+AJ12+AK12 -> 0 | AP12: =AC12-AO12 -> 0
B13: =B12+1 -> 2 | AC13: =(E13*E46)+(F13*F46)+(G13*G46)+(H13*H46)+(I13*I46)+(J13*J46)+(K13*K46)+(L13*L46)+(M13*M46)+(N13*N46)+(O13*O46)+(P13*P46)+(Q13*Q46)+(R13*R46)+(S13*S46)+(T13*T46)+(U13*U46)+(V13*V46)+(W13*W46)+(X13*X46)+(Y13*Y46)+(Z13*Z46)+(AA13*AA46)+(AB13*AB46) -> 0 | AD13: =10%*AC13 -> 0 | AE13: =AC13-AD13 -> 0 | AL13: =AE13/3 -> 0 | AM13: =AL13 -> 0 | AN13: =AM13 -> 0 | AO13: =AD13+AF13+AG13+AH13+AI13+AJ13+AK13 -> 0 | AP13: =AC13-AO13 -> 0
B14: =B13+1 -> 3 | AC14: =(E14*E46)+(F14*F46)+(G14*G46)+(H14*H46)+(I14*I46)+(J14*J46)+(K14*K46)+(L14*L46)+(M14*M46)+(N14*N46)+(O14*O46)+(P14*P46)+(Q14*Q46)+(R14*R46)+(S14*S46)+(T14*T46)+(U14*U46)+(V14*V46)+(W14*W46)+(X14*X46)+(Y14*Y46)+(Z14*Z46)+(AA14*AA46)+(AB14*AB46) -> 0 | AD14: =10%*AC14 -> 0 | AE14: =AC14-AD14 -> 0 | AL14: =AE14/3 -> 0 | AM14: =AL14 -> 0 | AN14: =AM14 -> 0 | AO14: =AD14+AF14+AG14+AH14+AI14+AJ14+AK14 -> 0 | AP14: =AC14-AO14 -> 0
B15: =B14+1 -> 4 | AC15: =(E15*E46)+(F15*F46)+(G15*G46)+(H15*H46)+(I15*I46)+(J15*J46)+(K15*K46)+(L15*L46)+(M15*M46)+(N15*N46)+(O15*O46)+(P15*P46)+(Q15*Q46)+(R15*R46)+(S15*S46)+(T15*T46)+(U15*U46)+(V15*V46)+(W15*W46)+(X15*X46)+(Y15*Y46)+(Z15*Z46)+(AA15*AA46)+(AB15*AB46) -> 0 | AD15: =10%*AC15 -> 0 | AE15: =AC15-AD15 -> 0 | AL15: =AE15/3 -> 0 | AM15: =AL15 -> 0 | AN15: =AM15 -> 0 | AO15: =AD15+AF15+AG15+AH15+AI15+AJ15+AK15 -> 0 | AP15: =AC15-AO15 -> 0
B16: =B15+1 -> 5 | AC16: =(E16*E46)+(F16*F46)+(G16*G46)+(H16*H46)+(I16*I46)+(J16*J46)+(K16*K46)+(L16*L46)+(M16*M46)+(N16*N46)+(O16*O46)+(P16*P46)+(Q16*Q46)+(R16*R46)+(S16*S46)+(T16*T46)+(U16*U46)+(V16*V46)+(W16*W46)+(X16*X46)+(Y16*Y46)+(Z16*Z46)+(AA16*AA46)+(AB16*AB46) -> 0 | AD16: =10%*AC16 -> 0 | AE16: =AC16-AD16 -> 0 | AL16: =AE16/3 -> 0 | AM16: =AL16 -> 0 | AN16: =AM16 -> 0 | AO16: =AD16+AF16+AG16+AH16+AI16+AJ16+AK16 -> 0 | AP16: =AC16-AO16 -> 0
B17: =B16+1 -> 6 | AC17: =(E17*E46)+(F17*F46)+(G17*G46)+(H17*H46)+(I17*I46)+(J17*J50)+(K17*K46)+(L17*L46)+(M17*M46)+(N17*N46)+(O17*O46)+(P17*P46)+(Q17*Q46)+(R17*R46)+(S17*S46)+(T17*T46)+(U17*U46)+(V17*V46)+(W17*W46)+(X17*X46)+(Y17*Y46)+(Z17*Z46)+(AA17*AA46)+(AB17*AB46) -> 0 | AD17: =10%*AC17 -> 0 | AE17: =AC17-AD17 -> 0 | AL17: =AE17/3 -> 0 | AM17: =AL17 -> 0 | AN17: =AM17 -> 0 | AO17: =AD17+AF17+AG17+AH17+AI17+AJ17+AK17 -> 0 | AP17: =AC17-AO17 -> 0
B18: =B17+1 -> 7 | AC18: =(E18*E46)+(F18*F46)+(G18*G46)+(H18*H46)+(I18*I46)+(J18*J46)+(K18*K46)+(L18*L46)+(M18*M46)+(N18*N46)+(O18*O46)+(P18*P46)+(Q18*Q46)+(R18*R46)+(S18*S46)+(T18*T46)+(U18*U46)+(V18*V46)+(W18*W46)+(X18*X46)+(Y18*Y46)+(Z18*Z46)+(AA18*AA46)+(AB18*AB46) -> 0 | AD18: =10%*AC18 -> 0 | AE18: =AC18-AD18 -> 0 | AL18: =AE18/3 -> 0 | AM18: =AL18 -> 0 | AN18: =AM18 -> 0 | AO18: =AD18+AF18+AG18+AH18+AI18+AJ18+AK18 -> 0 | AP18: =AC18-AO18 -> 0
B19: =B18+1 -> 8 | AC19: =(E19*E46)+(F19*F46)+(G19*G46)+(H19*H46)+(I19*I46)+(J19*J46)+(K19*K46)+(L19*L46)+(M19*M46)+(N19*N46)+(O19*O46)+(P19*P46)+(Q19*Q46)+(R19*R46)+(S19*S46)+(T19*T46)+(U19*U46)+(V19*V46)+(W19*W46)+(X19*X46)+(Y19*Y46)+(Z19*Z46)+(AA19*AA46)+(AB19*AB46) -> 0 | AD19: =10%*AC19 -> 0 | AE19: =AC19-AD19 -> 0 | AL19: =AE19/3 -> 0 | AM19: =AL19 -> 0 | AN19: =AM19 -> 0 | AO19: =AD19+AF19+AG19+AH19+AI19+AJ19+AK19 -> 0 | AP19: =AC19-AO19 -> 0
B20: =B19+1 -> 9 | AC20: =(E20*E46)+(F20*F46)+(G20*G46)+(H20*H46)+(I20*I46)+(J20*J46)+(K20*K46)+(L20*L46)+(M20*M46)+(N20*N46)+(O20*O46)+(P20*P46)+(Q20*Q46)+(R20*R46)+(S20*S46)+(T20*T46)+(U20*U46)+(V20*V46)+(W20*W46)+(X20*X46)+(Y20*Y46)+(Z20*Z46)+(AA20*AA46)+(AB20*AB46) -> 0 | AD20: =10%*AC20 -> 0 | AE20: =AC20-AD20 -> 0 | AL20: =AE20/3 -> 0 | AM20: =AL20 -> 0 | AN20: =AM20 -> 0 | AO20: =AD20+AF20+AG20+AH20+AI20+AJ20+AK20 -> 0
B21: =B20+1 -> 10 | AC21: =(E21*E46)+(F21*F46)+(G21*G46)+(H21*H46)+(I21*I46)+(J21*J46)+(K21*K46)+(L21*L46)+(M21*M46)+(N21*N46)+(O21*O46)+(P21*P46)+(Q21*Q46)+(R21*R46)+(S21*S46)+(T21*T46)+(U21*U46)+(V21*V46)+(W21*W46)+(X21*X46)+(Y21*Y46)+(Z21*Z46)+(AA21*AA46)+(AB21*AB46) -> 0 | AD21: =10%*AC21 -> 0 | AE21: =AC21-AD21 -> 0 | AL21: =AE21/3 -> 0 | AM21: =AL21 -> 0 | AN21: =AM21 -> 0
B22: =B21+1 -> 11 | AC22: =(E22*E46)+(F22*F46)+(G22*G46)+(H22*H46)+(I22*I46)+(J22*J46)+(K22*K46)+(L22*L46)+(M22*M46)+(N22*N46)+(O22*O46)+(P22*P46)+(Q22*Q46)+(R22*R46)+(S22*S46)+(T22*T46)+(U22*U46)+(V22*V46)+(W22*W46)+(X22*X46)+(Y22*Y46)+(Z22*Z46)+(AA22*AA46)+(AB22*AB46) -> 0 | AD22: =10%*AC22 -> 0 | AE22: =AC22-AD22 -> 0 | AL22: =AE22/3 -> 0 | AM22: =AL22 -> 0 | AN22: =AM22 -> 0
B23: =B22+1 -> 12 | AC23: =(E23*E46)+(F23*F46)+(G23*G46)+(H23*H46)+(I23*I46)+(J23*J46)+(K23*K46)+(L23*L46)+(M23*M46)+(N23*N46)+(O23*O46)+(P23*P46)+(Q23*Q46)+(R23*R46)+(S23*S46)+(T23*T46)+(U23*U46)+(V23*V46)+(W23*W46)+(X23*X46)+(Y23*Y46)+(Z23*Z46)+(AA23*AA46)+(AB23*AB46) -> 0 | AD23: =10%*AC23 -> 0 | AE23: =AC23-AD23 -> 0 | AL23: =AE23/3 -> 0 | AM23: =AL23 -> 0 | AN23: =AM23 -> 0
B24: =B23+1 -> 13 | AC24: =(E24*E46)+(F24*F46)+(G24*G46)+(H24*H46)+(I24*I46)+(J24*J46)+(K24*K46)+(L24*L46)+(M24*M46)+(N24*N46)+(O24*O46)+(P24*P46)+(Q24*Q46)+(R24*R46)+(S24*S46)+(T24*T46)+(U24*U46)+(V24*V46)+(W24*W46)+(X24*X46)+(Y24*Y46)+(Z24*Z46)+(AA24*AA46)+(AB24*AB46) -> 0 | AD24: =10%*AC24 -> 0 | AE24: =AC24-AD24 -> 0 | AL24: =AE24/3 -> 0 | AM24: =AL24 -> 0 | AN24: =AM24 -> 0
B25: =B24+1 -> 14 | AC25: =(E25*E46)+(F25*F46)+(G25*G46)+(H25*H46)+(I25*I46)+(J25*J46)+(K25*J46)+(L25*L46)+(M25*M46)+(N25*N46)+(O25*O46)+(P25*P46)+(Q25*Q46)+(R25*R46)+(S25*S46)+(T25*T46)+(U25*U46)+(V25*V46)+(W25*W46)+(X25*X46)+(Y25*Y46)+(Z25*Z46)+(AA25*AA46)+(AB25*AB46) -> 0 | AD25: =10%*AC25 -> 0 | AE25: =AC25-AD25 -> 0 | AL25: =AE25/3 -> 0 | AM25: =AL25 -> 0 | AN25: =AM25 -> 0
B26: =B25+1 -> 15 | AC26: =(E26*E46)+(F26*F46)+(G26*G46)+(H26*H46)+(I26*I46)+(J26*J46)+(K26*K46)+(L26*L46)+(M26*M46)+(N26*N46)+(O26*O46)+(P26*P46)+(Q26*Q46)+(R26*R46)+(S26*S46)+(T26*T46)+(U26*U46)+(V26*V46)+(W26*W46)+(X26*X46)+(Y26*Y46)+(Z26*Z46)+(AA26*AA46)+(AB26*AB46) -> 0 | AD26: =10%*AC26 -> 0 | AE26: =AC26-AD26 -> 0 | AL26: =AE26/3 -> 0 | AM26: =AL26 -> 0 | AN26: =AM26 -> 0
B27: =B26+1 -> 16 | AC27: =(E27*E46)+(F27*F46)+(G27*G46)+(H27*H46)+(I27*I46)+(J27*J46)+(K27*K46)+(L27*L46)+(M27*M46)+(N27*N46)+(O27*O46)+(P27*P46)+(Q27*Q46)+(R27*R46)+(S27*S46)+(T27*T46)+(U27*U46)+(V27*V46)+(W27*W46)+(X27*X46)+(Y27*Y46)+(Z27*Z46)+(AA27*AA46)+(AB27*AB46) -> 0 | AD27: =10%*AC27 -> 0 | AE27: =AC27-AD27 -> 0 | AL27: =AE27/3 -> 0 | AM27: =AL27 -> 0 | AN27: =AM27 -> 0
B28: =B27+1 -> 17 | AC28: =(E28*E46)+(F28*F46)+(G28*G46)+(H28*H46)+(I28*I46)+(J28*J46)+(K28*J46)+(L28*L46)+(M28*M46)+(N28*N46)+(O28*O46)+(P28*P46)+(Q28*Q46)+(R28*R46)+(S28*S46)+(T28*T46)+(U28*U46)+(V28*V46)+(W28*W46)+(X28*X46)+(Y28*Y46)+(Z28*Z46)+(AA28*AA46)+(AB28*AB46) -> 0 | AD28: =10%*AC28 -> 0 | AE28: =AC28-AD28 -> 0 | AL28: =AE28/3 -> 0 | AM28: =AL28 -> 0 | AN28: =AM28 -> 0
B29: =B28+1 -> 18 | AC29: =(E29*E46)+(F29*F46)+(G29*G46)+(H29*H46)+(I29*I46)+(J29*J46)+(K29*K46)+(L29*L46)+(M29*M46)+(N29*N46)+(O29*O46)+(P29*P46)+(Q29*Q46)+(R29*R46)+(S29*S46)+(T29*T46)+(U29*U46)+(V29*V46)+(W29*W46)+(X29*X46)+(Y29*Y46)+(Z29*Z46)+(AA29*AA46)+(AB29*AB46) -> 0 | AD29: =10%*AC29 -> 0 | AE29: =AC29-AD29 -> 0 | AL29: =AE29/3 -> 0 | AM29: =AL29 -> 0 | AN29: =AM29 -> 0
B30: =B29+1 -> 19 | AC30: =(E30*E46)+(F30*F46)+(G30*G46)+(H30*H46)+(I30*I46)+(J30*J46)+(K30*K46)+(L30*L46)+(M30*M46)+(N30*N46)+(O30*O46)+(P30*P46)+(Q30*Q46)+(R30*R46)+(S30*S46)+(T30*T46)+(U30*U46)+(V30*V46)+(W30*W46)+(X30*X46)+(Y30*Y46)+(Z30*Z46)+(AA30*AA46)+(AB30*AB46) -> 0 | AD30: =10%*AC30 -> 0 | AE30: =AC30-AD30 -> 0 | AL30: =AE30/3 -> 0 | AM30: =AL30 -> 0 | AN30: =AM30 -> 0
B31: =B30+1 -> 20 | AC31: =(E31*E46)+(F31*F46)+(G31*G46)+(H31*H46)+(I31*I46)+(J31*J46)+(K31*J46)+(L31*L46)+(M31*M46)+(N31*N46)+(O31*O46)+(P31*P46)+(Q31*Q46)+(R31*R46)+(S31*S46)+(T31*T46)+(U31*U46)+(V31*V46)+(W31*W46)+(X31*X46)+(Y31*Y46)+(Z31*Z46)+(AA31*AA46)+(AB31*AB46) -> 0 | AD31: =10%*AC31 -> 0 | AE31: =AC31-AD31 -> 0 | AL31: =AE31/3 -> 0 | AM31: =AL31 -> 0 | AN31: =AM31 -> 0
B32: =B31+1 -> 21 | AC32: =(E32*E46)+(F32*F46)+(G32*G46)+(H32*H46)+(I32*I46)+(J32*J46)+(K32*K46)+(L32*L46)+(M32*M46)+(N32*N46)+(O32*O46)+(P32*P46)+(Q32*Q46)+(R32*R46)+(S32*S46)+(T32*T46)+(U32*U46)+(V32*V46)+(W32*W46)+(X32*X46)+(Y32*Y46)+(Z32*Z46)+(AA32*AA46)+(AB32*AB46) -> 0 | AD32: =10%*AC32 -> 0 | AE32: =AC32-AD32 -> 0 | AL32: =AE32/3 -> 0 | AM32: =AL32 -> 0 | AN32: =AM32 -> 0
B33: =B32+1 -> 22 | AC33: =(E33*E46)+(F33*F46)+(G33*G46)+(H33*H46)+(I33*I46)+(J33*J46)+(K33*K46)+(L33*L46)+(M33*M46)+(N33*N46)+(O33*O46)+(P33*P46)+(Q33*Q46)+(R33*R46)+(S33*S46)+(T33*T46)+(U33*U46)+(V33*V46)+(W33*W46)+(X33*X46)+(Y33*Y46)+(Z33*Z46)+(AA33*AA46)+(AB33*AB46) -> 0 | AD33: =10%*AC33 -> 0 | AE33: =AC33-AD33 -> 0 | AL33: =AE33/3 -> 0 | AM33: =AL33 -> 0 | AN33: =AM33 -> 0
B34: =B33+1 -> 23 | AC34: =(E34*E46)+(F34*F46)+(G34*G46)+(H34*H46)+(I34*I46)+(J34*J46)+(K34*J46)+(L34*L46)+(M34*M46)+(N34*N46)+(O34*O46)+(P34*P46)+(Q34*Q46)+(R34*R46)+(S34*S46)+(T34*T46)+(U34*U46)+(V34*V46)+(W34*W46)+(X34*X46)+(Y34*Y46)+(Z34*Z46)+(AA34*AA46)+(AB34*AB46) -> 0 | AD34: =10%*AC34 -> 0 | AE34: =AC34-AD34 -> 0 | AL34: =AE34/3 -> 0 | AM34: =AL34 -> 0 | AN34: =AM34 -> 0
B35: =B34+1 -> 24 | AC35: =(E35*E46)+(F35*F46)+(G35*G46)+(H35*H46)+(I35*I46)+(J35*J46)+(K35*K46)+(L35*L46)+(M35*M46)+(N35*N46)+(O35*O46)+(P35*P46)+(Q35*Q46)+(R35*R46)+(S35*S46)+(T35*T46)+(U35*U46)+(V35*V46)+(W35*W46)+(X35*X46)+(Y35*Y46)+(Z35*Z46)+(AA35*AA46)+(AB35*AB46) -> 0 | AD35: =10%*AC35 -> 0 | AE35: =AC35-AD35 -> 0 | AL35: =AE35/3 -> 0 | AM35: =AL35 -> 0 | AN35: =AM35 -> 0
B36: =B35+1 -> 25 | AC36: =(E36*E46)+(F36*F46)+(G36*G46)+(H36*H46)+(I36*I46)+(J36*J46)+(K36*K46)+(L36*L46)+(M36*M46)+(N36*N46)+(O36*O46)+(P36*P46)+(Q36*Q46)+(R36*R46)+(S36*S46)+(T36*T46)+(U36*U46)+(V36*V46)+(W36*W46)+(X36*X46)+(Y36*Y46)+(Z36*Z46)+(AA36*AA46)+(AB36*AB46) -> 0 | AD36: =10%*AC36 -> 0 | AE36: =AC36-AD36 -> 0 | AL36: =AE36/3 -> 0 | AM36: =AL36 -> 0 | AN36: =AM36 -> 0
B37: =B36+1 -> 26 | AC37: =(E37*E46)+(F37*F46)+(G37*G46)+(H37*H46)+(I37*I46)+(J37*J46)+(K37*J46)+(L37*L46)+(M37*M46)+(N37*N46)+(O37*O46)+(P37*P46)+(Q37*Q46)+(R37*R46)+(S37*S46)+(T37*T46)+(U37*U46)+(V37*V46)+(W37*W46)+(X37*X46)+(Y37*Y46)+(Z37*Z46)+(AA37*AA46)+(AB37*AB46) -> 0 | AD37: =10%*AC37 -> 0 | AE37: =AC37-AD37 -> 0 | AL37: =AE37/3 -> 0 | AM37: =AL37 -> 0 | AN37: =AM37 -> 0
B38: =B37+1 -> 27 | AC38: =(E38*E46)+(F38*F46)+(G38*G46)+(H38*H46)+(I38*I46)+(J38*J46)+(K38*K46)+(L38*L46)+(M38*M46)+(N38*N46)+(O38*O46)+(P38*P46)+(Q38*Q46)+(R38*R46)+(S38*S46)+(T38*T46)+(U38*U46)+(V38*V46)+(W38*W46)+(X38*X46)+(Y38*Y46)+(Z38*Z46)+(AA38*AA46)+(AB38*AB46) -> 0 | AD38: =10%*AC38 -> 0 | AE38: =AC38-AD38 -> 0 | AL38: =AE38/3 -> 0 | AM38: =AL38 -> 0 | AN38: =AM38 -> 0
B39: =B38+1 -> 28 | AC39: =(E39*E46)+(F39*F46)+(G39*G46)+(H39*H46)+(I39*I46)+(J39*J46)+(K39*K46)+(L39*L46)+(M39*M46)+(N39*N46)+(O39*O46)+(P39*P46)+(Q39*Q46)+(R39*R46)+(S39*S46)+(T39*T46)+(U39*U46)+(V39*V46)+(W39*W46)+(X39*X46)+(Y39*Y46)+(Z39*Z46)+(AA39*AA46)+(AB39*AB46) -> 0 | AD39: =10%*AC39 -> 0 | AE39: =AC39-AD39 -> 0 | AL39: =AE39/3 -> 0 | AM39: =AL39 -> 0 | AN39: =AM39 -> 0
B40: =B39+1 -> 29 | AC40: =(E40*E46)+(F40*F46)+(G40*G46)+(H40*H46)+(I40*I46)+(J40*J46)+(K40*J46)+(L40*L46)+(M40*M46)+(N40*N46)+(O40*O46)+(P40*P46)+(Q40*Q46)+(R40*R46)+(S40*S46)+(T40*T46)+(U40*U46)+(V40*V46)+(W40*W46)+(X40*X46)+(Y40*Y46)+(Z40*Z46)+(AA40*AA46)+(AB40*AB46) -> 0 | AD40: =10%*AC40 -> 0 | AE40: =AC40-AD40 -> 0 | AL40: =AE40/3 -> 0 | AM40: =AL40 -> 0 | AN40: =AM40 -> 0
B41: =B40+1 -> 30 | AC41: =(E41*E46)+(F41*F46)+(G41*G46)+(H41*H46)+(I41*I46)+(J41*J46)+(K41*K46)+(L41*L46)+(M41*M46)+(N41*N46)+(O41*O46)+(P41*P46)+(Q41*Q46)+(R41*R46)+(S41*S46)+(T41*T46)+(U41*U46)+(V41*V46)+(W41*W46)+(X41*X46)+(Y41*Y46)+(Z41*Z46)+(AA41*AA46)+(AB41*AB46) -> 0 | AD41: =10%*AC41 -> 0 | AE41: =AC41-AD41 -> 0 | AL41: =AE41/3 -> 0 | AM41: =AL41 -> 0 | AN41: =AM41 -> 0
B42: =B41+1 -> 31 | AC42: =(E42*E46)+(F42*F46)+(G42*G46)+(H42*H46)+(I42*I46)+(J42*J46)+(K42*K46)+(L42*L46)+(M42*M46)+(N42*N46)+(O42*O46)+(P42*P46)+(Q42*Q46)+(R42*R46)+(S42*S46)+(T42*T46)+(U42*U46)+(V42*V46)+(W42*W46)+(X42*X46)+(Y42*Y46)+(Z42*Z46)+(AA42*AA46)+(AB42*AB46) -> 0 | AD42: =10%*AC42 -> 0 | AE42: =AC42-AD42 -> 0 | AL42: =AE42/3 -> 0 | AM42: =AL42 -> 0 | AN42: =AM42 -> 0
B43: TOTAL | C43: =COUNTA(C12:C42) -> 0 | E43: =SUM(E12:E42) -> 0 | F43: =SUM(F12:F42) -> 0 | G43: =SUM(G12:G42) -> 0 | H43: =SUM(H12:H42) -> 0 | I43: =SUM(I12:I42) -> 0 | J43: =SUM(J12:J42) -> 0 | K43: =SUM(K12:K42) -> 0 | L43: =SUM(L12:L42) -> 0 | ... AE43: =SUM(AE12:AE42) -> 0 | AL43: =SUM(AL12:AL42) -> 0 | AM43: =SUM(AM12:AM42) -> 0 | AN43: =SUM(AN12:AN42) -> 0 | AO43: =SUM(AO12:AO42) -> 0
C46: Price | E46: 144 | F46: =12*E46 -> 1728 | G46: 116 | H46: =G46*48 -> 5568 | I46: 144 | J46: =I46*12 -> 1728 | K46: 116 | L46: =K46*15 -> 1740 | M46: 116 | N46: =M46*6 -> 696 | O46: 272 | P46: =O46*4 -> 1088 | Q46: 1088 | R46: 272 | S46: =R46*4 -> 1088 | T46: 4964 | U46: 82 | V46: =U46*12 -> 984 | W46: 20 | X46: 79 | Y46: =X46*12 -> 948 | Z46: 1224 | AA46: 116 | AB46: 340

Sheet 4
C2: NOTE:
C3: 1. Enter the quantity of agro inputs requested by the farmer either in pcs or boxes under each agro input
C4: 2. Do not change any thing in the excel sheet. The cells are linked
C6: REGION:
C7: DISTRICT:
C8: SOCIETY:
B10: NO. | C10: FARMER NAME | D10: MOBILE NO. | E10: AcetaStar -Adama (1Lt) | G10: Galil | I10: AKATE BRAFO | K10: PHYTOGREEN | M10: BEGREEN | O10: Agyenkwa Liquid Fertilizer (5Lt) | Q10: Matabi (15Lt) | R10: PLANTFEED | T10: Solo Machine | U10: All Wedicides (Glyphosate) | W10: NODOX | X10: ALL GRAMO | Z10: STANDARD PRUNNER | AA10: WELLINGTON BOOT | AB10: OVERALL | AC10: TOTAL AMOUNT (GHc) | AD10: DEPOSIT PAID (GHc) | AE10: OUTS. BALANCE (GHc) | AF10: REPAYMENT PLAN(GHC) | AO10: TOTAL PAYMENT | AP10: REMN
E11: PCs | F11: Box (12pcs) | G11: PCs | H11: Box | I11: PCs | J11: Box | K11: 1LT | L11: BOX(15) | M11: 1GALLON | N11: BOX(6) | O11: PCs | P11: Box(4) | Q11: PCs | R11: 1 GALLON | S11: BOX(4) | T11: PCs | U11: PCS | V11: BOX(12) | W11: PCs | X11: PCS | Y11: BOX(12) | Z11: PC | AA11: PC | AB11: PC | AF11: OCT | AG11: NOV | AH11: DEC | AL11: OCT | AM11: NOV | AN11: DEC
B12: =B11+1 -> 1 | AC12: =(E12*E45)+(F12*F45)+(G12*G45)+(H12*H45)+(I12*I45)+(J12*J45)+(K12*K45)+(L12*L45)+(M12*M45)+(N12*N45)+(O12*O45)+(P12*P45)+(Q12*Q45)+(R12*R45)+(S12*S45)+(T12*T45)+(U12*U45)+(V12*V45)+(W12*W45)+(X12*X45)+(Y12*Y45)+(Z12*Z45)+(AA12*AA45)+(AB12*AB45) -> 0 | AD12: =10%*AC12 -> 0 | AE12: =AC12-AD12 -> 0 | AL12: =AE12/3 -> 0 | AM12: =AL12 -> 0 | AN12: =AM12 -> 0 | AO12: =AD12+AF12+AG12+AH12+AI12+AJ12+AK12 -> 0 | AP12: =AC12-AO12 -> 0
